Workbook

Sheet Análisis Evaluación Crediticio
B4: ANÁLISIS Y EVALUACIÓN CREDITICIO Para uso exclusivo del Departamento de Crédito
B5: Cliente N° | C5: Apellidos y Nombres | H5: Destino | I5: COMPRA DE TERRENO | M5: Tipo de Préstamo: | O5: 4 | P5: =VLOOKUP(O5,'TIPOS DE PRÉSTAMO'!A2:B44,2,0) -> ORDINARIO SIN GARANTE
B6: 228566 | C6: NAVAS PEÑAHERRERA GABRIEL HUMBERTO | M6: Tipo de Cartera: | O6: 4 | P6: =VLOOKUP(O6,'TIPO DE CARTERA'!B29:C43,2,0) -> CONSUMO
M7: Oficina: | O7: 7 | P7: =VLOOKUP(O7,'CÓDIGO OFICINA'!A5:B18,2) -> LAGO AGRIO
B8: Monto | D8: Interés | E8: Plazo (meses) | G8: Pagos (días) | H8: 30 | J8: Cuota Decreciente | K8: Cuota Fija | M8: Oficial de Negocios asignado | Q8: Fecha
B9: 20000 | D9: 0.155 | E9: 48 | G9: =IF(H8=30,"Pagos Mensuales",IF(H8=60,"Pagos Bimestrales",IF(H8=90,"Pagos Trimestrales",IF(H8=180,"Pagos Semestrales",IF(H8=360,"Pagos Anuales"))))) -> Pagos Mensuales | J9: =IF(E9>0,B9/(E9*30/H8)+B9*D9*H8/360,"") -> 675 | K9: =IF(E9>0,(B9*D9*H8/360)/(1-(1+(D9*H8/360))^-(30*E9/H8)),"") -> 561.69718 | M9: 7-03 | N9: =VLOOKUP(M9,'OFICIALES DE NEGOCIO'!D3:E95,2,0) -> JARAMILLO JIMENEZ CARLOS ISRAEL | Q9: 46077
B10: Subsegmentación de Cartera | D10: Descripción
B11: 4-0 | C11: =VLOOKUP(B11,'SEGMENTOS DE CREDITO'!B6:C14,2,0) -> CONSUMO | D11: =VLOOKUP(C11,'SEGMENTOS DE CREDITO'!C6:D14,2,0) -> Son aquellas operaciones otorgadas a personas naturales, destinado a la compra de bienes, servicios o gastos no relacionados con una actividad productiva, comercial y otras compras y gastos, se incluyen los créditos prendarios de joyas, así como para adquisición de vehículos livianos que no sean de uso para una actividad productiva y comercial.
B13: COMENTARIOS DE CARÁCTER
B14: Segundo credito a solicitar en la CPMV. En el sistema Financiero Nacional refleja operaciones vigentes en: CPMV 11217.14 USD. Su segmentación es 911 AA, reporte crediticio favorable para un crédito ordinario sin garante. La vivienda en la que reside es arrendada, ubicada en el cantón de Lago Agrio, parroquia Nueva Loja, provincia de Sucumbíos, en el barrio Santa Isabel, a lado de la pizzeria like. Solicitante, goza de buen estado de salud con 23 años de edad, de estado civil soltero, no posee cargas familiares menores de edad; su nivel de instrucción es bachiller, labora de manera independiente. Buenas referencias de quienes la conocen, amigos y familiares cercanos al socio: señora, Deysi Peñaherrera (madre); Israel Peñaherrera (tio) y Wilson Navas (padre); quienes dan testimonio de conocer a al socio por algún tiempo, mismo que ha demostrado ser una persona proba en sus obligaciones | R14: <
B20: COMENTARIOS DE CAPACIDAD DE PAGO
B21: Solicitante es independiente, propietario de ELECTROSERVICIOS NAVAS, actividad relacionada con la electromecánica, se respalda con la presentación RUC y últimas tres declaraciones. Según el levantamiento de información sus ingresos se consideran por el valor de 1389 USD, sus gastos personales mensuales son de 595.71 USD generando un excedente mensual de 793.29 USD. Según la evaluación y luego de aplicar el castigo del 30% que es de acuerdo a la fuente de ingresos se comprueba que éstos son suficientes para cubrir las cuota del crédito; es decir que la cuota propuesta es de 481.06 USD VS el excedente 793.29 USD se compromete en un 60%. Se comprueba que el socio tiene la capacidad de pago adecuada para esta operación crediticia. Los pagos se realizarán de los ingresos mensuales percibidos por la solicitante.
B27: COMENTARIOS DE CAPITAL
B28: Sus activos están conformados por sus bienes muebles, con un total de activos de 22335.18 USD. Posee pasivos por 11271.14 USD, por lo tanto, su patrimonio es de 11064.04 USD. El monto recomendado para aprobación es de 20000 USD. Se determina que socio se encuentra en condiciones favorables, capacidad de pago acorde al monto solicitado y un patrimonio que cumple con el 200% de la política exigida en la institución.
B33: COMENTARIOS DE COLATERAL
B34: El garante, señor, PEÑAHERRERA MUÑOZ ISRAEL ALFONSO, de estado civil casado, sus ingresos son de actividad de COMERCIANTE DE ROPA y ARTÍCULOS para el hogar, se adjunta RUC,declaracion y facturas. Mantienen obligaciones vigentes en: PICHINCHA VISA 10695.90 USD; PACIFICO VISA 226.66 USD; PICHINCHA 20908.84 USD; PICHINCHA 7503.70 USD; PICHINCHA 5885.95 USD; PICHINCHA 5217.77 USD; COOP 23 DE JULIO 14149.71 USD y CONECEL 36 USD. Presenta activos por USD 155650, resultando en un patrimonio de USD 91025.47 USD. Su segmentación de riesgo AA 940. Con base en el levantamiento de información, sus ingresos mensuales ascienden a USD 4342.50, mientras que los gastos personales se consideran por 3563.38 USD , generando un excedente de USD 779.12. En consecuencia, el garante cuenta con capacidad de pago suficiente para respaldar la cuota del deudor principal.
B39: COMENTARIO DE CONDICIONES GENERALES
B40: Se recomienda la aprobación del crédito, socio con actividad estable; garante posee patrimonio. En el sistema financiero nacional no registra, reporte por mora ni vencimientos. Sector económico estable. Se recomienda su aprobación por tiempo y monto propuesto. Revisadas páginas de la Judicatura, no se encuentra inconvenientes para el otorgamiento de la operación crediticia
B45: ORDINARIO / CONSUMO: Crédito bajo reglamento. Cumple con todos los requisitos, se conceda un monto de VEINTE MIL 00/100 (USD 20.000.00) a un plazo de 60 MESES, pagos mensuales. Se recomienda su aprobación por tiempo y monto propuesto, cliente cumple con todos los requisitos.
P51: =+N9 -> JARAMILLO JIMENEZ CARLOS ISRAEL
P52: =+Q9 -> 46077
B53: RESOLUCIÓN DEL COMITÉ DE CRÉDITO OFICINA | Q53: COMITÉ DE CRÉDITO OFICINA - Nº Acta :
B55: APROBADO: | D55: OBSERVACIONES:
B57: SUSPENSO:
B59: NEGADO:
B61: FECHA:
D62: PRESIDENTE | J62: SECRETARIO | O62: VOCAL
B63: RESOLUCIÓN DEL COMITÉ DE CRÉDITO EJECUTIVO O GENERAL | Q63: COMITÉ DE CRÉDITO EJECUTIVO O GENERAL- Nº Acta :
B65: APROBADO: | D65: OBSERVACIONES:
B67: SUSPENSO:
B69: NEGADO:
B71: FECHA:
D72: PRESIDENTE | J72: SECRETARIO | O72: VOCAL
B73: RESOLUCIÓN DEL CONSEJO DE ADMINISTRACIÓN
D75: OBSERVACIONES:
B76: APROBADO:
B77: SUSPENSO:
B78: NEGADO:
B79: FECHA:
D80: PRESIDENTE | J80: SECRETARIO | O80: VOCAL

Sheet ENTRADA DE PARAMETROS
A2: PARAMETROS DE CALIFICACION DE RIESGO | D2: PARAMETROS DE CALIFICACION PARA CAPACIDAD DE PAGO
B3: Valorar sobre 10 | E3: Valorar sobre 10
A4: 1. Carácter | B4: 29 | D4: 3.1 Capacidad de pago | E4: =10+10+10 -> 30
A5: 2. Capacidad de Gestión | B5: 21 | D5: 3.2 Rentabilidad sobre Capital | E5: =9+8+8 -> 25
A6: 3. Capacidad de Pago | B6: =9+10+10 -> 29 | D6: 3.3 Sostenibilidad | E6: =8+8+8 -> 24
A7: 4. Colateral | B7: =7+7+7 -> 21 | D7: 3.4 Nivel de endeudamiento | E7: =9+8+9 -> 26
A8: 5. Condiciones de mercado | B8: =8+7+7 -> 22 | D8: 3.5 Medios de producción | E8: =8+6+6 -> 20
A9: PUNTAJE TOTAL SOBRE 100 | B9: =SUM(B4:B8) -> 122 | D9: 3.6 Razon Corriente | E9: =9+8+8 -> 25
D10: 3.7 Reprocidad de depòsitos | E10: =7+6+6 -> 19
A11: PARAMETROS DE CALIFICACION PARA CARACTER | E11: =SUM(E4:E10) -> 169
B12: Valorar sobre 10
A13: 1.1 Experiencia crediticia | B13: =10+9+10 -> 29 | D13: PARAMETROS DE CALIFICACION PARA COLATERAL
A14: 1.2 Arraigo del negocio | B14: =7+7+7 -> 21 | E14: Valorar sobre 10
A15: 1.3 Calidad de referencias | B15: =6+5+6 -> 17 | D15: 4.1 GARANTIA REAL
A16: 1.4 Calificación Interna | B16: =10+10+9 -> 29 | D16: 4.1.1 Comercialización | E16: 10
A17: 1.5 Arraigo Residencial | B17: =6+8+7 -> 21 | D17: 4.1.2 Estado | E17: 10
A18: 1.6 Estado Civil | B18: =5+5+5 -> 15 | D18: 4.1.3 Movilización | E18: 9
A19: 1.7 Genero | B19: =5+4+4 -> 13 | D19: 4.1.4 Calidad edif. Adyacentes | E19: 8
A20: 1.8 Datos Generales bàsicos | B20: 21 | D20: 4.1.5 Servicios Básicos | E20: 9
A21: PUNTAJE TOTAL SOBRE 100 | B21: =SUM(B13:B20) -> 166 | D21: 4.1.6 Avalúo | E21: 10
E22: =SUM(E16:E21) -> 56
A23: PARAMETROS DE CALIFICACION PARA CAPACIDAD DE GESTION | D23: 4.2 GARANTIA PERSONAL
B24: Valorar sobre 10 | D24: 4.2.1 Historial Credicitio | E24: 10
A25: 2.1 Experiencia en la actividad | B25: =10+8+9 -> 27 | D25: 4.2.2 Capacidad de Pago | E25: 10
A26: 2.2 Organización del negocio | B26: =8+8+8 -> 24 | D26: 4.2.3 Patrimonio | E26: 9
A27: 2.3 Dependencia de clientes | B27: =9+8+8 -> 25 | D27: 4.2.4 Documentos de respaldo | E27: 10
A28: 2.4 Dependencia de proveedores | B28: =7+7+7 -> 21 | E28: =SUM(E24:E27) -> 39
A29: 2.5 Dependencia del personal | B29: =7+6+7 -> 20
A30: 2.6 Dependencia de la actividad del socio | B30: =8+8+8 -> 24 | D30: PARAMETROS DE CALIFICACION PARA CONDICIONES DE MERCADO
A31: 2.7 Capacidad Administrativa (Educación) | B31: =7+8+7 -> 22 | E31: Valorar sobre 10
A32: 2.8 Local del negocio (SECTOR RURAL) (SECTOR URBANO) | B32: =8+6+7 -> 21 | D32: 5.1 Nivel de competencia | E32: =9+9+9 -> 27
B33: =SUM(B25:B32) -> 184 | D33: 5.2 Dinámica del sector | E33: =9+7+8 -> 24
D34: 5.3 Aceptación del producto | E34: =10+8+8 -> 26
E35: =SUM(E32:E34) -> 77
A41: 1. CARÁCTER | D41: 2. CAPACIDAD DE GESTION | G41: 3. CAPACIDAD DE PAGO | J41: 4. COLATERAL | M41: 5. CONDICIONES/MERCADO
A43: 1.1 Experiencia crediticia | D43: 2.1 Experiencia en la actividad | G43: 3.1 Capacidad de pago | J43: 4.1 GARANTIA REAL | M43: 5.1 Nivel de competencia
A44: 1 Puntual | B44: 4 | D44: 1 Más de 5 años | E44: 3.5 | G44: 1 Suficiente capacidad, cubre la cuota con exceso | J44: Comercialización: | M44: 1 Sin competencia en el medio | N44: 3
A45: 2 Atrazado | B45: 2 | D45: 2 Entre 3 y 5 años | E45: 2.5 | G45: sobre el 30%; ingresos provienen del negocio | H45: 20 | J45: 1 Corto Plazo | K45: 4 | M45: 2 Mediana competencia | N45: 2
A46: 3 Moroso | B46: 1 | D46: 3 Entre 1 y 3 años | E46: 1.5 | G46: 2 Buena capacidad, cubre la cuota con exceso de hasta | J46: 2 Mediano | K46: 2 | M46: 3 Alta competencia | N46: 1
A47: 4 Juicio o Castigado | B47: -20 | D47: 4 Menos de 1 año | E47: -40 | G47: el 29%, necesita otra fuente de ingresos | H47: 10 | J47: 3 Largo Plazo | K47: 0
G48: 3 Insuficiente capacidad, no cubre la cuota. | H48: -40 | M48: 5.2 Dinámica del sector
A49: 1.2 Arraigo del negocio | D49: 2.2 Organización del negocio | J49: Estado: | M49: 1 Sector en crecimiento. | N49: 4
A50: 1 Más de 3 años | B50: 3 | D50: 1 Buena organización, dispone de registros y | G50: 3.2 Rentabilidad sobre Capital | J50: 1 Optimo | K50: 4 | M50: 2 Sector en estabilidad. | N50: 3
A51: 2 Entre 2 y 3 años | B51: 2 | D51: sin problemas en la venta | E51: 1.75 | G51: 1 Mayor en 3% a la inflación | H51: 2.5 | J51: 2 Bueno | K51: 3 | M51: 3 Sector estancado, sin proyecciones | N51: 2
A52: 3 Entre 1 y 2 años | B52: 1 | D52: 2 Evidencia buen nivel de ventas, pero con | G52: 2 Igual a la inflación | H52: 1.5 | J52: 3 Regular | K52: 1 | M52: 4 Sector en recesión, decreciendo | N52: 1
A53: 4 Menos de 1 año | B53: -10 | D53: deficiencias en la organización | E53: 1.25 | G53: 3 Menor que la inflación | H53: 0
D54: 3 Buena o aceptable organización, pero no | G54: 4 Pérdida | H54: -2 | J54: Movilización:
A55: 1.3 Calidad de referencias | D55: posee registros y/o con medianos problemas de venta | E55: 0.75 | J55: 1 Buena | K55: 4 | M55: 5.3 Aceptación del producto
A56: Comerciales: | D56: 4 Presenta mala organización, no dispone | G56: 3.3 Sostenibilidad | J56: 2 Regular | K56: 3 | M56: 1 Alta aceptación por calidad/precio | N56: 4
A57: 1 Buena | B57: 1 | D57: de registros y/o con graves problemas en la venta | E57: 1 | G57: 1 Relación Ingresos/gastos sobre 1,25 | H57: 4 | J57: 3 Deficiente | K57: 0 | M57: 2 Mediana aceptación | N57: 2
A58: 2 Mala | B58: -1 | G58: 2 Relación Ingresos/gastos entre 1,10 y 1,25 | H58: 2 | M58: 3 Baja, dificultosa aceptación | N58: 0
A59: 3 No tiene referencias | B59: 0.2 | D59: 2.3 Dependencia de clientes | G59: 3 Relación Ingresos/gastos menor a 1,10 | H59: -20 | J59: Calidad edif. adyacentes:
D60: 1 Sin importancia/consumo masivo | E60: 1.75 | J60: 1 Buena | K60: 4
A61: Personales: | D61: 2 Entre 4 y 8 compradores | E61: 1 | G61: 3.4 Nivel de endeudamiento | J61: 2 Regular | K61: 3
A62: 1 Buena | B62: 1 | D62: 3 Intermediario (entre 1 y 3 compradores) | E62: 0 | G62: Relación Pasivos/Activos | J62: 3 Baja | K62: 0
A63: 2 Mala | B63: -1 | G63: 1 Menor al 30% | H63: 4
A64: 3 No tiene referencias | B64: 0.2 | D64: 2.4 Dependencia de proveedores | G64: 2 Entre 30% al 40% | H64: 3 | J64: Servicios Básicos:
D65: 1 Sin importancia/facilidad para proveerse | E65: 1 | G65: 3 Entre 40% y 50% | H65: 2 | J65: 1 Todos | K65: 4
A66: 1.4 Calificación Interna | D66: 2 Más de 3 proveedores | E66: 0.75 | G66: 4 Más del 50% | H66: -20 | J66: 2 Algunos | K66: 3
A67: Referencias bancarias | D67: 3 Entre 2 a 3 proveedores | E67: 0.5 | J67: 3 Ninguno | K67: 0
A68: 1 Cliente A | B68: 6 | D68: 4 Un proveedor, alta dependencia | E68: 0 | G68: 3.5 Medios de producción
A69: 2 Cliente B | B69: 4 | G69: 1 Propietario del negocio o terreno | H69: 2.5 | J69: Avalúo:
A70: 3 Cliente C | B70: -100 | D70: 2.5 Dependencia del personal | G70: 2 En sociedad (al partir) | H70: 2 | J70: 1 Más del 200% | K70: 4
A71: 4 Clente D o E | B71: -100 | D71: 1 Familiar | E71: 0.5 | G71: 3 Negocio o terreno arrendado | H71: 1.5 | J71: 2 El 200% | K71: 2
A72: 5 Cuentas cerradas | B72: -20 | D72: 2 Familiar y trabajadores | E72: 0.25 | J72: 3 Menos del 200% | K72: -15
A73: 6 No tienereferencias | B73: 1 | D73: 3 Sólo trabajadores | E73: 0 | G73: 3.6 Razon Corriente
G74: 1 Màs del 200% | H74: 4
A75: 1.5 Arraigo Residencial | D75: 2.6 Dependencia de la actividad del socio (RURAL) | G75: 2 Del 200% al 175% | H75: 3 | J75: 4.2 Garantia Personal
A76: 1 Propio | B76: 5 | D76: 1 Dos actividades o más | E76: 3.5 | G76: 3 Del 175% al 150% | H76: 2 | J76: Historial Credicitio:
A77: 2 Más de 3 años | B77: 4 | D77: 2 Dependencia de 1 sola actividad | E77: 1.5 | G77: 4 Menor a 150% | H77: 0 | J77: 1 Pagos puntuales. Primer crédito | K77: 4
A78: 3 Entre 2 y 3 años | B78: 3 | J78: 2 Atrasado | K78: 1
A79: 4 Entre 1 y 2 años | B79: 2 | D79: 2.6 Dependencia de la actividad del socio (URBANO) | G79: 3.7 Reprocidad de depòsitos | J79: 3 Moroso | K79: 0
A80: 5 Menos de 1 año | B80: -5 | D80: 1 Dependencia de 1 sola actividad | E80: 3.5 | G80: 1 Favorable | H80: 4 | J80: 4 Juicio o castigado | K80: -20
A81: 6 No residente | B81: -15 | D81: 2 Dos actividades o más | E81: 1.5 | G81: 2 Regular | H81: 2
G82: 3 Desfavorable | H82: 0 | J82: Capacidad de Pago:
A83: 1.6 Estado Civil | D83: 2.7 Capacidad Administrativa (Educación) | J83: 1 Suficiente | K83: 4
A84: 1 Casado | B84: 2 | D84: 1 Educación Superior | E84: 2.5 | J84: 2 Buena | K84: 3
A85: 2 Viudo | B85: 2 | D85: 2 Educaciòn Secundaria | E85: 2 | J85: 3 Regular | K85: 1
A86: 3 Soltero | B86: 1 | D86: 3 Educaciòn Primaria | E86: 1.5 | J86: 4 Insuficiente | K86: -20
A87: 4 Divorciado | B87: 1
A88: 5 Unión Libre | B88: 1 | D88: 2.8 Local del negocio (SECTOR URBANO) | J88: Patrimonio:
D89: 1 Propio | E89: 3 | J89: 1 Más del 200% | K89: 4
A90: 1.7 Genero | D90: 2 Arrendado | E90: 2 | J90: 2 Hasta el 200 % | K90: 3
A91: 1 Masculino | B91: 1 | D91: 3 Ambulante | E91: 1 | J91: 3 Hasta el 175% | K91: 2
A92: 2 Femenino | B92: 3 | J92: 4 Hasta el 100% | K92: 0
D93: 2.8 Local del negocio (SECTOR RURAL)
A94: 1.8 Datos Generales bàsicos | D94: 1 Propio | E94: 3 | J94: Documentos de respaldo:
A95: 1 Correctos | B95: 3 | D95: 2 Arrendado | E95: 1 | J95: 1 Todos | K95: 4
A96: 2 Incorrectos | B96: 2 | J96: 2 Aceptables | K96: 3
A97: 3 Incompletos | B97: 0 | J97: 3 No Aceptables | K97: 0
J98: 4 Ninguno | K98: -20

Sheet DETALLE DE CALIFICACIONES
A2: PARAMETROS DE CALIFICACION DE RIESGO
A4: 1. Carácter | B4: =+'ENTRADA DE PARAMETROS'!B4 -> 29 | C4: =(B4/$B$9)*100 -> 23.770492
A5: 2. Capacidad de Gestión | B5: =+'ENTRADA DE PARAMETROS'!B5 -> 21 | C5: =(B5/$B$9)*100 -> 17.213115
A6: 3. Capacidad de Pago | B6: =+'ENTRADA DE PARAMETROS'!B6 -> 29 | C6: =(B6/$B$9)*100 -> 23.770492
A7: 4. Colateral | B7: =+'ENTRADA DE PARAMETROS'!B7 -> 21 | C7: =(B7/$B$9)*100 -> 17.213115
A8: 5. Condiciones de mercado | B8: =+'ENTRADA DE PARAMETROS'!B8 -> 22 | C8: =(B8/$B$9)*100 -> 18.032787
A9: PUNTAJE TOTAL SOBRE 100 | B9: =SUM(B4:B8) -> 122 | C9: =SUM(C4:C8) -> 100
A12: PARAMETROS DE CALIFICACION PARA CARACTER
A14: 1.1 Experiencia crediticia | B14: =+'ENTRADA DE PARAMETROS'!B13 -> 29 | C14: =+B14/$B$22 -> 0.1746988 | D14: =+C14*$D$22 -> 4.1526763
A15: 1.2 Arraigo del negocio | B15: =+'ENTRADA DE PARAMETROS'!B14 -> 21 | C15: =+B15/$B$22 -> 0.12650602 | D15: =+C15*$D$22 -> 3.0071104
A16: 1.3 Calidad de referencias | B16: =+'ENTRADA DE PARAMETROS'!B15 -> 17 | C16: =+B16/$B$22 -> 0.10240964 | D16: =+C16*$D$22 -> 2.4343275
A17: 1.4 Calificación Interna | B17: =+'ENTRADA DE PARAMETROS'!B16 -> 29 | C17: =+B17/$B$22 -> 0.1746988 | D17: =+C17*$D$22 -> 4.1526763
A18: 1.5 Arraigo Residencial | B18: =+'ENTRADA DE PARAMETROS'!B17 -> 21 | C18: =+B18/$B$22 -> 0.12650602 | D18: =+C18*$D$22 -> 3.0071104
A19: 1.6 Estado Civil | B19: =+'ENTRADA DE PARAMETROS'!B18 -> 15 | C19: =+B19/$B$22 -> 0.090361446 | D19: =+C19*$D$22 -> 2.147936
A20: 1.7 Genero | B20: =+'ENTRADA DE PARAMETROS'!B19 -> 13 | C20: =+B20/$B$22 -> 0.078313253 | D20: =+C20*$D$22 -> 1.8615445
A21: 1.8 Datos Generales bàsicos | B21: =+'ENTRADA DE PARAMETROS'!B20 -> 21 | C21: =+B21/$B$22 -> 0.12650602 | D21: =+C21*$D$22 -> 3.0071104
B22: =SUM(B14:B21) -> 166 | C22: =SUM(C14:C21) -> 1 | D22: =+C4 -> 23.770492
A24: PARAMETROS DE CALIFICACION PARA CAPACIDAD DE GESTION
A26: 2.1 Experiencia en la actividad | B26: =+'ENTRADA DE PARAMETROS'!B25 -> 27 | C26: =+B26/$B$34 -> 0.14673913 | D26: =+C26*$D$34 -> 2.5258375
A27: 2.2 Organización del negocio | B27: =+'ENTRADA DE PARAMETROS'!B26 -> 24 | C27: =+B27/$B$34 -> 0.13043478 | D27: =+C27*$D$34 -> 2.2451889
A28: 2.3 Dependencia de clientes | B28: =+'ENTRADA DE PARAMETROS'!B27 -> 25 | C28: =+B28/$B$34 -> 0.13586957 | D28: =+C28*$D$34 -> 2.3387384
A29: 2.4 Dependencia de proveedores | B29: =+'ENTRADA DE PARAMETROS'!B28 -> 21 | C29: =+B29/$B$34 -> 0.11413043 | D29: =+C29*$D$34 -> 1.9645403
A30: 2.5 Dependencia del personal | B30: =+'ENTRADA DE PARAMETROS'!B29 -> 20 | C30: =+B30/$B$34 -> 0.10869565 | D30: =+C30*$D$34 -> 1.8709907
A31: 2.6 Dependencia de la actividad del socio | B31: =+'ENTRADA DE PARAMETROS'!B30 -> 24 | C31: =+B31/$B$34 -> 0.13043478 | D31: =+C31*$D$34 -> 2.2451889
A32: 2.7 Capacidad Administrativa (Educación) | B32: =+'ENTRADA DE PARAMETROS'!B31 -> 22 | C32: =+B32/$B$34 -> 0.11956522 | D32: =+C32*$D$34 -> 2.0580898
A33: 2.8 Local del negocio (SECTOR RURAL) (SECTOR URBANO) | B33: =+'ENTRADA DE PARAMETROS'!B32 -> 21 | C33: =+B33/$B$34 -> 0.11413043 | D33: =+C33*$D$34 -> 1.9645403
B34: =SUM(B26:B33) -> 184 | C34: =SUM(C26:C33) -> 1 | D34: =+C5 -> 17.213115
A36: PARAMETROS DE CALIFICACION PARA CAPACIDAD DE PAGO
A38: 3.1 Capacidad de pago | B38: =+'ENTRADA DE PARAMETROS'!E4 -> 30 | C38: =+B38/$B$45 -> 0.17751479 | D38: =+C38*$D$45 -> 4.2196139
A39: 3.2 Rentabilidad sobre Capital | B39: =+'ENTRADA DE PARAMETROS'!E5 -> 25 | C39: =+B39/$B$45 -> 0.14792899 | D39: =+C39*$D$45 -> 3.5163449
A40: 3.3 Sostenibilidad | B40: =+'ENTRADA DE PARAMETROS'!E6 -> 24 | C40: =+B40/$B$45 -> 0.14201183 | D40: =+C40*$D$45 -> 3.3756911
A41: 3.4 Nivel de endeudamiento | B41: =+'ENTRADA DE PARAMETROS'!E7 -> 26 | C41: =+B41/$B$45 -> 0.15384615 | D41: =+C41*$D$45 -> 3.6569987
A42: 3.5 Medios de producción | B42: =+'ENTRADA DE PARAMETROS'!E8 -> 20 | C42: =+B42/$B$45 -> 0.1183432 | D42: =+C42*$D$45 -> 2.813076
A43: 3.6 Razon Corriente | B43: =+'ENTRADA DE PARAMETROS'!E9 -> 25 | C43: =+B43/$B$45 -> 0.14792899 | D43: =+C43*$D$45 -> 3.5163449
A44: 3.7 Reprocidad de depòsitos | B44: =+'ENTRADA DE PARAMETROS'!E10 -> 19 | C44: =+B44/$B$45 -> 0.11242604 | D44: =+C44*$D$45 -> 2.6724222
B45: =SUM(B38:B44) -> 169 | C45: =SUM(C38:C44) -> 1 | D45: =+C6 -> 23.770492
A47: PARAMETROS DE CALIFICACION PARA COLATERAL
F48: 4.3 GARANTIA MIXTA
A49: 4.1 GARANTIA REAL | F49: 4.1 GARANTIA REAL (59%)
A50: 4.1.1 Comercialización | B50: ='ENTRADA DE PARAMETROS'!E16 -> 10 | C50: =B50/$B$56 -> 0.17857143 | D50: =$D$56*C50 -> 3.0737705 | F50: 4.1.1 Comercialización | G50: 10 | H50: =G50/$G$65 -> 0.10526316 | I50: =H50*$I$65 -> 1.8273684
A51: 4.1.2 Estado | B51: ='ENTRADA DE PARAMETROS'!E17 -> 10 | C51: =B51/$B$56 -> 0.17857143 | D51: =$D$56*C51 -> 3.0737705 | F51: 4.1.2 Estado | G51: 10 | H51: =G51/$G$65 -> 0.10526316 | I51: =H51*$I$65 -> 1.8273684
A52: 4.1.3 Movilización | B52: ='ENTRADA DE PARAMETROS'!E18 -> 9 | C52: =B52/$B$56 -> 0.16071429 | D52: =$D$56*C52 -> 2.7663934 | F52: 4.1.3 Movilización | G52: 9 | H52: =G52/$G$65 -> 0.094736842 | I52: =H52*$I$65 -> 1.6446316
A53: 4.1.4 Calidad edif. Adyacentes | B53: ='ENTRADA DE PARAMETROS'!E19 -> 8 | C53: =B53/$B$56 -> 0.14285714 | D53: =$D$56*C53 -> 2.4590164 | F53: 4.1.4 Calidad edif. Adyacentes | G53: 8 | H53: =G53/$G$65 -> 0.084210526 | I53: =H53*$I$65 -> 1.4618947
A54: 4.1.5 Servicios Básicos | B54: ='ENTRADA DE PARAMETROS'!E20 -> 9 | C54: =B54/$B$56 -> 0.16071429 | D54: =$D$56*C54 -> 2.7663934 | F54: 4.1.5 Servicios Básicos | G54: 9 | H54: =G54/$G$65 -> 0.094736842 | I54: =H54*$I$65 -> 1.6446316
A55: 4.1.6 Avalúo | B55: ='ENTRADA DE PARAMETROS'!E21 -> 10 | C55: =B55/$B$56 -> 0.17857143 | D55: =$D$56*C55 -> 3.0737705 | F55: 4.1.6 Avalúo | G55: 10 | H55: =G55/$G$65 -> 0.10526316 | I55: =H55*$I$65 -> 1.8273684
B56: =SUM(B50:B55) -> 56 | C56: =SUM(C50:C55) -> 1 | D56: =C7 -> 17.213115 | G56: =SUM(G50:G55) -> 56 | H56: =SUM(H50:H55) -> 0.58947368 | I56: =SUM(I50:I55) -> 10.233263
A59: 4.2 GARANTIA PERSONAL | F59: 4.2 GARANTIA PERSONAL (41%)
A60: 4.2.1 Historial Credicitio | B60: ='ENTRADA DE PARAMETROS'!E24 -> 10 | C60: =B60/$B$64 -> 0.25641026 | D60: =C60*$D$64 -> 4.4136192 | F60: 4.2.1 Historial Credicitio | G60: 10 | H60: =G60/$G$65 -> 0.10526316 | I60: =H60*$I$65 -> 1.8273684
A61: 4.2.2 Capacidad de Pago | B61: ='ENTRADA DE PARAMETROS'!E25 -> 10 | C61: =B61/$B$64 -> 0.25641026 | D61: =C61*$D$64 -> 4.4136192 | F61: 4.2.2 Capacidad de Pago | G61: 10 | H61: =G61/$G$65 -> 0.10526316 | I61: =H61*$I$65 -> 1.8273684
A62: 4.2.3 Patrimonio | B62: ='ENTRADA DE PARAMETROS'!E26 -> 9 | C62: =B62/$B$64 -> 0.23076923 | D62: =C62*$D$64 -> 3.9722573 | F62: 4.2.3 Patrimonio | G62: 9 | H62: =G62/$G$65 -> 0.094736842 | I62: =H62*$I$65 -> 1.6446316
A63: 4.2.4 Documentos de respaldo | B63: ='ENTRADA DE PARAMETROS'!E27 -> 10 | C63: =B63/$B$64 -> 0.25641026 | D63: =C63*$D$64 -> 4.4136192 | F63: 4.2.4 Documentos de respaldo | G63: 10 | H63: =G63/$G$65 -> 0.10526316 | I63: =H63*$I$65 -> 1.8273684
B64: =SUM(B60:B63) -> 39 | C64: =SUM(C60:C63) -> 1 | D64: =+C7 -> 17.213115 | G64: =SUM(G60:G63) -> 39 | H64: =SUM(H60:H63) -> 0.41052632 | I64: =SUM(I60:I63) -> 7.1267368
F65: TOTAL | G65: =G56+G64 -> 95 | H65: =H56+H64 -> 1 | I65: 17.36
A66: PARAMETROS DE CALIFICACION PARA CONDICIONES DE MERCADO
A68: 5.1 Nivel de competencia | B68: =+'ENTRADA DE PARAMETROS'!E32 -> 27 | C68: =+B68/$B$71 -> 0.35064935 | D68: =+C68*$D$71 -> 6.323185
A69: 5.2 Dinámica del sector | B69: =+'ENTRADA DE PARAMETROS'!E33 -> 24 | C69: =+B69/$B$71 -> 0.31168831 | D69: =+C69*$D$71 -> 5.6206089
A70: 5.3 Aceptación del producto | B70: =+'ENTRADA DE PARAMETROS'!E34 -> 26 | C70: =+B70/$B$71 -> 0.33766234 | D70: =+C70*$D$71 -> 6.088993
B71: =SUM(B68:B70) -> 77 | C71: =SUM(C68:C70) -> 1 | D71: =+C8 -> 18.032787

Sheet INGRESO DE DATOS
A1: CALIFICACION DE RIESGO DE CREDITO
A2: NUMERO DE SOCIO: | B2: ='Análisis Evaluación Crediticio'!B6:B7 -> #VALUE! | E2: ='Análisis Evaluación Crediticio'!C6 -> NAVAS PEÑAHERRERA GABRIEL HUMBERTO | F2: NOMBRE: | I2: Detalle el Sector (U = URBANO o R = RURAL) | K2: U | Q2: Detalle Garantía ( R=REAL P=PERSONAL Y SIN GARANTE M=MIXTO ) | S2: P | U2: L I S T A
U3: R | V3: REAL
A4: 1. CARÁCTER | B4: Cod | C4: Calif | E4: 2. CAPACIDAD DE GESTION | F4: Cod | G4: Calif. | I4: 3. CAPITAL | J4: Cod | K4: Calif | M4: 4. COLATERAL | N4: Cod | O4: Calif. | Q4: 5. CONDICIONES/MERCADO | R4: Cod | S4: Calif. | U4: P | V4: PERSONAL
U5: M | V5: MIXTA
A6: 1.1 Experiencia crediticia | B6: 1 | C6: =FORMULAS!E5 -> 4.1526763 | E6: 2.1 Experiencia en la actividad | F6: 1 | G6: =FORMULAS!J5 -> 2.5258375 | I6: 3.1 Capacidad de pago | J6: 1 | K6: =FORMULAS!O5 -> 4.2196139 | M6: 4.1 Garantia Real | Q6: 5.1 Nivel de competencia | R6: 2 | S6: =FORMULAS!Y5 -> 4.2154567
A7: 1 Puntual | E7: 1 Más de 5 años | I7: 1 Suficiente capacidad, cubre la | M7: Comercialización: | N7: 1 | O7: =FORMULAS!T6 -> 0 | Q7: 1 Sin competencia en el medio | U7: L I S T A
A8: 2 Atrazado | E8: 2 Entre 3 y 5 años | I8: cuota con exceso sobre el 30% | M8: 1 Corto Plazo | Q8: 2 Mediana competencia | U8: U | V8: URBANO
A9: 3 Moroso | E9: 3 Entre 1 y 3 años | I9: ingresos provienen del negocio | M9: 2 Mediano | Q9: 3 Alta competencia | U9: R | V9: RURAL
A10: 4 Juicio o Castigado | E10: 4 Menos de 1 año | F10: =IF(F6=4,"ALERTA","") | I10: 2 Buena capacidad, cubre la cuota | M10: 3 Largo Plazo | N10: =IF(N7=3,"MEJORAR GARANTIA","")
A11: 1.2 Arraigo del negocio | B11: 1 | C11: =FORMULAS!E11 -> 3.0071104 | E11: 2.2 Organización del negocio | F11: 2 | G11: =FORMULAS!J11 -> 1.6037063 | I11: con exceso de hasta el 29%, | J11: =IF(J6=3,"NEGADO","") | M11: Estado: | N11: 1 | O11: =FORMULAS!T11 -> 0 | Q11: 5.2 Dinámica del sector | R11: 2 | S11: =FORMULAS!Y10 -> 4.2154567
A12: 1 Más de 3 años | E12: 1 Buena organización, dispone de registros y | I12: necesita otra fuente de ingresos. | M12: 1 Optimo | Q12: 1 Sector en crecimiento.
A13: 2 Entre 2 y 3 años | E13: Dispone de registros y | I13: 3 Insuficiente capacidad, | M13: 2 Bueno | Q13: 2 Sector en estabilidad.
A14: 3 Entre 1 y 2 años | E14: sin problemas en la venta | I14: no cubre la cuota | M14: 3 Regular | Q14: 3 Sector estancado, sin proyecciones
A15: 4 Menos de 1 año | B15: =IF(B11=4,"ALERTA","") | E15: 2 Evidencia buen nivel de ventas | M15: Movilización: | N15: 1 | O15: =FORMULAS!T16 -> 0 | Q15: 4 Sector en recesión, decreciendo
A16: 1.3 Calidad de referencias | C16: =FORMULAS!E17 -> 2.4343275 | E16: pero con deficiencias | I16: 3.2 Rentabilidad sobre Capital | J16: 2 | K16: =FORMULAS!O12 -> 2.109807 | M16: 1 Buena
A17: Comerciales: | B17: 1 | E17: en la organización | I17: 1 Mayor en 3% a la inflación | M17: 2 Regular
A18: 1 Buena | E18: 3 Buena o aceptable organización | F18: =IF(F11=4,"ALERTA","") | I18: 2 Igual a la inflación | M18: 3 Deficiente | Q18: 5.3 Aceptación del producto | R18: 2 | S18: =FORMULAS!Y17 -> 3.0444965
A19: 2 Mala | E19: No posee registros | I19: 3 Menor que la inflación | M19: Calidad edif. adyacentes: | N19: 1 | O19: =FORMULAS!T21 -> 0 | Q19: 1 Alta aceptación por calidad/precio
A20: 3 No tiene referencias | B20: =IF(B17=3,"ALERTA","") | E20: con medianos problemas de venta | I20: 4 Pérdida | M20: 1 Buena | Q20: 2 Mediana aceptación
A21: Personales: | B21: 1 | E21: 4 Presenta mala organización | I21: 3.3 Sostenibilidad | J21: 2 | K21: =FORMULAS!O18 -> 1.6878456 | M21: 2 Regular | Q21: 3 Baja, dificultosa aceptación
A22: 1 Buena | E22: no dispone de registros | I22: 1 Relación Ingresos/gastos sobre 1,25 | M22: 3 Baja
A23: 2 Mala | E23: Con graves problemas en la venta | I23: 2 Relación Ingresos/gastos entre 1,10 y 1,25 | M23: Servicios Básicos: | N23: 1 | O23: =FORMULAS!T26 -> 0
A24: 3 No tiene referencias | B24: =IF(B21=3,"ALERTA","") | E24: 2.3 Dependencia de clientes | F24: 1 | G24: =FORMULAS!J21 -> 2.3387384 | I24: 3 Relación Ingresos/gastos menor a 1,10 | M24: 1 Todos | Q24: PUNTAJE CONDICIONES/MERCADO | S24: =SUM(S6:S21) -> 11.47541
A25: 1.4 Calificacion Interna | C25: =FORMULAS!E28 -> 4.1526763 | E25: 1 Sin importancia/consumo masivo | I25: 3.4 Nivel de endeudamiento | J25: 1 | K25: =FORMULAS!O23 -> 3.6569987 | M25: 2 Algunos
B26: 1 | E26: 2 Entre 4 y 8 compradores | I26: Relación Pasivos/Activos | M26: 3 Ninguno
A27: 1 Cliente A | E27: 3 Intermediario (entre 1 y 3 compradores) | F27: =IF(F24=3,"ALERTA","") | I27: 1 Menor al 30% | M27: Avalúo: | N27: 1 | O27: =FORMULAS!T31 -> 0 | Q27: RESUMEN CALIFICACION DE RIESGO
A28: 2 Cliente B | E28: 2.4 Dependencia de proveedores | F28: 2 | G28: =FORMULAS!J26 -> 1.4734052 | I28: 2 Entre 30% al 40% | M28: 1 Más del 200%
A29: 3 Cliente C | B29: =IF(B26=3,"NEGADO","") | E29: 1 Sin importancia/facilidad para proveerse | I29: 3 Entre 40% y 50% | M29: 2 El 200% | R29: Calif. Obtenida | S29: Calif. Optima
A30: 4 Clente D o E | B30: =IF(B26=4,"NEGADO","") | E30: 2 Más de 3 proveedores | I30: 4 Más del 50% | J30: =IF(J25=4,"NEGADO","") | M30: 3 Menos del 200% | Q30: Carácter | R30: =C54 -> 23.612976 | S30: ='DETALLE DE CALIFICACIONES'!C4 -> 23.770492
A31: 5 Cuentas cerradas | B31: =IF(B26=5,"ALERTA","") | E31: 3 Entre 2 a 3 proveedores | I31: 3.5 Medios de producción | J31: 1 | K31: =FORMULAS!O30 -> 2.813076 | Q31: Capacidad de Gestión | R31: =G57 -> 16.080497 | S31: ='DETALLE DE CALIFICACIONES'!C5 -> 17.213115
A32: 6 No tienereferencias | E32: 4 Un proveedor, alta dependencia | F32: =IF(F28=4,"ALERTA","") | I32: 1 Propietario del negocio o terreno | Q32: Capital | R32: =K46 -> 18.460811 | S32: ='DETALLE DE CALIFICACIONES'!C6 -> 23.770492
A33: 1.5 Arraigo Residencial | B33: 4 | C33: =FORMULAS!E37 -> 1.2028442 | E33: 2.5 Dependencia del personal | F33: 1 | G33: =FORMULAS!J32 -> 1.8709907 | I33: 2 En sociedad (al partir) | M33: 4.2 Garantia Personal y Sin Garante | Q33: Colateral | R33: =O55 -> 17.213115 | S33: ='DETALLE DE CALIFICACIONES'!C7 -> 17.213115
A34: 1 Propio | E34: 1 Familiar | I34: 3 Negocio o terreno arrendado | M34: Historial Credicitio: | N34: 1 | O34: =FORMULAS!T38 -> 4.4136192 | Q34: Condiciones de mercado | R34: =S24 -> 11.47541 | S34: ='DETALLE DE CALIFICACIONES'!C8 -> 18.032787
A35: 2 Más de 3 años | E35: 2 Familiar y trabajadores | I35: 3.6 Razon Corriente | J35: 2 | K35: =FORMULAS!O35 -> 2.6372587 | M35: 1 Pagos puntuales. Primer crédito
A36: 3 Entre 2 y 3 años | E36: 3 Sólo trabajadores | I36: 1 Màs del 200% | M36: 2 Atrasado | Q36: PUNTAJE TOTAL SOBRE 100 | R36: =SUM(R30:R34) -> 86.842809 | S36: =SUM(S30:S35) -> 100
A37: 4 Entre 1 y 2 años | E37: 2.6 Dependencia de la actividad del socio (RURAL) | F37: 1 | G37: =FORMULAS!J37 -> 2.2451889 | I37: 2 Del 200% al 175% | M37: 3 Moroso
A38: 5 Menos de 1 año | B38: =IF(B33=5,"ALERTA","") | E38: 1 Dos actividades o más | I38: 3 Del 175% al 150% | M38: 4 Juicio o castigado | Q38: Nivel de riesgo
A39: 6 No residente | B39: =IF(B33=6,"NEGADO","") | E39: 2 Dependencia de 1 sola actividad | I39: 4 Menor a 150% | M39: Capacidad de Pago: | N39: 1 | O39: =FORMULAS!T44 -> 4.4136192
A40: 1.6 Estado Civil | B40: 5 | C40: =FORMULAS!E45 -> 1.073968 | I40: 3.7 Reprocidad de depòsitos | J40: 2 | K40: =FORMULAS!O41 -> 1.3362111 | M40: 1 Suficiente | Q40: Bajo mayor o igual a 85 | R40: =IF(R36>=85,"APROBADO","") -> APROBADO
A41: 1 Casado | E41: 2.6 Dependencia de la actividad del socio (URBANO) | F41: 1 | G41: =FORMULAS!J41 -> 0 | I41: 1 Favorable | M41: 2 Buena | Q41: Normal entre 70 y 85 | R41: =IF(AND(R36>=70,R36<85),"APROBADO","")
A42: 2 Viudo | E42: 1 Dependencia de 1 sola actividad | I42: 2 Regular | M42: 3 Regular | Q42: Potencial entre 60 y 70 | R42: =IF(AND(R36>=60,R36<70),"REVISAR","")
A43: 3 Soltero | E43: 2 Dos actividades o más | I43: 3 Desfavorable | M43: 4 Insuficiente | Q43: Real entre 50 y 60 | R43: =IF(AND(R36>=50,R36<60),"NEGADO","")
A44: 4 Divorciado | M44: Patrimonio: | N44: 1 | O44: =FORMULAS!T50 -> 3.9722573 | Q44: Alto menor a 50 | R44: =IF(R36<50,"NEGADO","")
A45: 5 Unión Libre | E45: 2.7 Capacidad Administrativa (Educación) | F45: 1 | G45: =FORMULAS!J45 -> 2.0580898 | M45: 1 Más del 200%
A46: 1.7 Genero | B46: 2 | C46: =FORMULAS!E52 -> 5.5846336 | E46: 1 Educación Superior | I46: PUNTAJE TOTAL CAPITAL | K46: =SUM(K6:K45) -> 18.460811 | M46: 2 Hasta el 200 %
A47: 1 Masculino | E47: 2 Educaciòn Secundaria | M47: 3 Hasta el 175%
A48: 2 Femenino | E48: 3 Educaciòn Primaria | M48: 4 Hasta el 100%
A49: 1.8 Datos Generales bàsicos | B49: 2 | C49: =FORMULAS!E56 -> 2.0047403 | E49: 2.8 Local del negocio (SECTOR URBANO) | F49: 1 | G49: =FORMULAS!J50 -> 1.9645403 | M49: Documentos de respaldo: | N49: 1 | O49: =FORMULAS!T56 -> 4.4136192
A50: 1 Correctos | E50: 1 Propio | M50: 1 Todos
A51: 2 Incorrectos | E51: 2 Arrendado | M51: 2 Aceptables
A52: 3 Incompletos | E52: 3 Ambulante | M52: 3 No Aceptables
E53: 2.8 Local del negocio (SECTOR RURAL) | F53: 2 | M53: 4 Ninguno
A54: PUNTAJE CARÁCTER | C54: =SUM(C6:C53) -> 23.612976 | E54: 1 Propio
E55: 2 Arrendado | M55: PUNTAJE TOTAL COLATERAL | O55: =SUM(O6:O53) -> 17.213115
E57: PUNTAJE CAPACIDAD DE GESTIÓN | G57: =SUM(G6:G56) -> 16.080497

Sheet FECHAS DE ACTUALIZACI{ON
A1: FECHA | B1: MOTIVO
A2: 44685 | B2: INCREMENTO DE OFICIALES DE NEGOCIOS
A3: 44708 | B3: INCREMENTO DE OFICIALES DE NEGOCIOS

Sheet FORMULAS
A1: N° socio | F1: Detalle el Sector ( U = URBANO o R = RURAL ) | G1: ='INGRESO DE DATOS'!K2 -> U | P1: Detalle Garantía ( R=REAL P=PERSONAL M=MIXTO ) | R1: ='INGRESO DE DATOS'!S2 -> P
A2: N° solicitud
A3: ='ENTRADA DE PARAMETROS'!A41 -> 1. CARÁCTER | E3: ='DETALLE DE CALIFICACIONES'!C4 -> 23.770492 | F3: ='ENTRADA DE PARAMETROS'!D41 -> 2. CAPACIDAD DE GESTION | J3: ='DETALLE DE CALIFICACIONES'!C5 -> 17.213115 | K3: ='ENTRADA DE PARAMETROS'!G41 -> 3. CAPACIDAD DE PAGO | O3: ='DETALLE DE CALIFICACIONES'!C6 -> 23.770492 | P3: ='ENTRADA DE PARAMETROS'!J41 -> 4. COLATERAL | T3: ='DETALLE DE CALIFICACIONES'!C7 -> 17.213115 | U3: ='ENTRADA DE PARAMETROS'!M41 -> 5. CONDICIONES/MERCADO | Y3: ='DETALLE DE CALIFICACIONES'!C8 -> 18.032787
B4: Parámetros | C4: Calificación | D4: % | E4: Total | G4: Parámetros | H4: Calificación | I4: % | J4: Total | L4: Parámetros | M4: Calificación | N4: % | O4: Total | Q4: Parámetros | R4: Calificación | S4: % | T4: Total | V4: Parámetros | W4: Calificación | X4: % | Y4: Total
A5: ='ENTRADA DE PARAMETROS'!A43 -> 1.1 Experiencia crediticia | D5: ='DETALLE DE CALIFICACIONES'!C14 -> 0.1746988 | E5: =C10 -> 4.1526763 | F5: ='ENTRADA DE PARAMETROS'!D43 -> 2.1 Experiencia en la actividad | I5: ='DETALLE DE CALIFICACIONES'!C26 -> 0.14673913 | J5: =H10 -> 2.5258375 | K5: ='ENTRADA DE PARAMETROS'!G43 -> 3.1 Capacidad de pago | N5: ='DETALLE DE CALIFICACIONES'!C38 -> 0.17751479 | O5: =M11 -> 4.2196139 | P5: ='ENTRADA DE PARAMETROS'!J43 -> 4.1 GARANTIA REAL | U5: ='ENTRADA DE PARAMETROS'!M43 -> 5.1 Nivel de competencia | X5: ='DETALLE DE CALIFICACIONES'!C68 -> 0.35064935 | Y5: =W9 -> 4.2154567
A6: ='ENTRADA DE PARAMETROS'!A44 -> 1 Puntual | B6: ='ENTRADA DE PARAMETROS'!B44 -> 4 | C6: =IF('INGRESO DE DATOS'!$B$6=1,FORMULAS!B6/$B$6*$D$5*$E$3,0) -> 4.1526763 | F6: ='ENTRADA DE PARAMETROS'!D44 -> 1 Más de 5 años | G6: ='ENTRADA DE PARAMETROS'!E44 -> 3.5 | H6: =IF('INGRESO DE DATOS'!$F$6=1,FORMULAS!G6/FORMULAS!$G$6*FORMULAS!$I$5*FORMULAS!$J$3,0) -> 2.5258375 | K6: ='ENTRADA DE PARAMETROS'!G44 -> 1 Suficiente capacidad, cubre la cuota con exceso | P6: ='ENTRADA DE PARAMETROS'!J44 -> Comercialización: | S6: ='DETALLE DE CALIFICACIONES'!C50 -> 0.17857143 | T6: =IF($R$1="R",R10,IF($R$1="M",(R10*0.59),0)) -> 0 | U6: ='ENTRADA DE PARAMETROS'!M44 -> 1 Sin competencia en el medio | V6: ='ENTRADA DE PARAMETROS'!N44 -> 3 | W6: =IF('INGRESO DE DATOS'!$R$6=1,V6/$V$6*$X$5*$Y$3,0) -> 0
A7: ='ENTRADA DE PARAMETROS'!A45 -> 2 Atrazado | B7: ='ENTRADA DE PARAMETROS'!B45 -> 2 | C7: =IF('INGRESO DE DATOS'!$B$6=2,FORMULAS!B7/$B$6*$D$5*$E$3,0) -> 0 | F7: ='ENTRADA DE PARAMETROS'!D45 -> 2 Entre 3 y 5 años | G7: ='ENTRADA DE PARAMETROS'!E45 -> 2.5 | H7: =IF('INGRESO DE DATOS'!$F$6=2,FORMULAS!G7/FORMULAS!$G$6*FORMULAS!$I$5*FORMULAS!$J$3,0) -> 0 | K7: ='ENTRADA DE PARAMETROS'!G45 -> sobre el 30%; ingresos provienen del negocio | L7: ='ENTRADA DE PARAMETROS'!H45 -> 20 | M7: =IF('INGRESO DE DATOS'!$J$6=1,L7/$L$7*$N$5*$O$3,0) -> 4.2196139 | P7: ='ENTRADA DE PARAMETROS'!J45 -> 1 Corto Plazo | Q7: ='ENTRADA DE PARAMETROS'!K45 -> 4 | R7: =IF('INGRESO DE DATOS'!$N$7=1,Q7/$Q$7*$S$6*$T$3,0) -> 3.0737705 | U7: ='ENTRADA DE PARAMETROS'!M45 -> 2 Mediana competencia | V7: ='ENTRADA DE PARAMETROS'!N45 -> 2 | W7: =IF('INGRESO DE DATOS'!$R$6=2,V7/$V$6*$X$5*$Y$3,0) -> 4.2154567
A8: ='ENTRADA DE PARAMETROS'!A46 -> 3 Moroso | B8: ='ENTRADA DE PARAMETROS'!B46 -> 1 | C8: =IF('INGRESO DE DATOS'!$B$6=3,FORMULAS!B8/$B$6*$D$5*$E$3,0) -> 0 | F8: ='ENTRADA DE PARAMETROS'!D46 -> 3 Entre 1 y 3 años | G8: ='ENTRADA DE PARAMETROS'!E46 -> 1.5 | H8: =IF('INGRESO DE DATOS'!$F$6=3,FORMULAS!G8/FORMULAS!$G$6*FORMULAS!$I$5*FORMULAS!$J$3,0) -> 0 | K8: ='ENTRADA DE PARAMETROS'!G46 -> 2 Buena capacidad, cubre la cuota con exceso de hasta | P8: ='ENTRADA DE PARAMETROS'!J46 -> 2 Mediano | Q8: ='ENTRADA DE PARAMETROS'!K46 -> 2 | R8: =IF('INGRESO DE DATOS'!$N$7=2,Q8/$Q$7*$S$6*$T$3,0) -> 0 | U8: ='ENTRADA DE PARAMETROS'!M46 -> 3 Alta competencia | V8: ='ENTRADA DE PARAMETROS'!N46 -> 1 | W8: =IF('INGRESO DE DATOS'!$R$6=3,V8/$V$6*$X$5*$Y$3,0) -> 0
A9: ='ENTRADA DE PARAMETROS'!A47 -> 4 Juicio o Castigado | B9: ='ENTRADA DE PARAMETROS'!B47 -> -20 | C9: =IF('INGRESO DE DATOS'!$B$6=4,FORMULAS!B9/$B$6*$D$5*$E$3,0) -> 0 | F9: ='ENTRADA DE PARAMETROS'!D47 -> 4 Menos de 1 año | G9: ='ENTRADA DE PARAMETROS'!E47 -> -40 | H9: =IF('INGRESO DE DATOS'!$F$6=4,FORMULAS!G9/FORMULAS!$G$6*FORMULAS!$I$5*FORMULAS!$J$3,0) -> 0 | K9: ='ENTRADA DE PARAMETROS'!G47 -> el 29%, necesita otra fuente de ingresos | L9: ='ENTRADA DE PARAMETROS'!H47 -> 10 | M9: =IF('INGRESO DE DATOS'!$J$6=2,L9/$L$7*$N$5*$O$3,0) -> 0 | P9: ='ENTRADA DE PARAMETROS'!J47 -> 3 Largo Plazo | Q9: ='ENTRADA DE PARAMETROS'!K47 -> 0 | R9: =IF('INGRESO DE DATOS'!$N$7=3,Q9/$Q$7*$S$6*$T$3,0) -> 0 | W9: =SUM(W6:W8) -> 4.2154567
C10: =SUM(C6:C9) -> 4.1526763 | H10: =SUM(H6:H9) -> 2.5258375 | K10: ='ENTRADA DE PARAMETROS'!G48 -> 3 Insuficiente capacidad, no cubre la cuota. | L10: ='ENTRADA DE PARAMETROS'!H48 -> -40 | M10: =IF('INGRESO DE DATOS'!$J$6=3,L10/$L$7*$N$5*$O$3,0) -> 0 | R10: =SUM(R7:R9) -> 3.0737705 | U10: ='ENTRADA DE PARAMETROS'!M48 -> 5.2 Dinámica del sector | X10: ='DETALLE DE CALIFICACIONES'!C69 -> 0.31168831 | Y10: =W15 -> 4.2154567
A11: ='ENTRADA DE PARAMETROS'!A49 -> 1.2 Arraigo del negocio | D11: ='DETALLE DE CALIFICACIONES'!C15 -> 0.12650602 | E11: =C16 -> 3.0071104 | F11: ='ENTRADA DE PARAMETROS'!D49 -> 2.2 Organización del negocio | I11: ='DETALLE DE CALIFICACIONES'!C27 -> 0.13043478 | J11: =H20 -> 1.6037063 | M11: =SUM(M7:M10) -> 4.2196139 | P11: ='ENTRADA DE PARAMETROS'!J49 -> Estado: | S11: ='DETALLE DE CALIFICACIONES'!C51 -> 0.17857143 | T11: =IF($R$1="R",R15,IF($R$1="M",(R15*0.59),0)) -> 0 | U11: ='ENTRADA DE PARAMETROS'!M49 -> 1 Sector en crecimiento. | V11: ='ENTRADA DE PARAMETROS'!N49 -> 4 | W11: =IF('INGRESO DE DATOS'!$R$11=1,V11/$V$11*$X$10*$Y$3,0) -> 0
A12: ='ENTRADA DE PARAMETROS'!A50 -> 1 Más de 3 años | B12: ='ENTRADA DE PARAMETROS'!B50 -> 3 | C12: =IF('INGRESO DE DATOS'!$B$11=1,FORMULAS!B12/$B$12*$D$11*$E$3,0) -> 3.0071104 | F12: ='ENTRADA DE PARAMETROS'!D50 -> 1 Buena organización, dispone de registros y | K12: ='ENTRADA DE PARAMETROS'!G50 -> 3.2 Rentabilidad sobre Capital | N12: ='DETALLE DE CALIFICACIONES'!C39 -> 0.14792899 | O12: =M17 -> 2.109807 | P12: ='ENTRADA DE PARAMETROS'!J50 -> 1 Optimo | Q12: ='ENTRADA DE PARAMETROS'!K50 -> 4 | R12: =IF('INGRESO DE DATOS'!$N$11=1,Q12/$Q$12*$S$11*$T$3,0) -> 3.0737705 | U12: ='ENTRADA DE PARAMETROS'!M50 -> 2 Sector en estabilidad. | V12: ='ENTRADA DE PARAMETROS'!N50 -> 3 | W12: =IF('INGRESO DE DATOS'!$R$11=2,V12/$V$11*$X$10*$Y$3,0) -> 4.2154567
A13: ='ENTRADA DE PARAMETROS'!A51 -> 2 Entre 2 y 3 años | B13: ='ENTRADA DE PARAMETROS'!B51 -> 2 | C13: =IF('INGRESO DE DATOS'!$B$11=2,FORMULAS!B13/$B$12*$D$11*$E$3,0) -> 0 | F13: ='ENTRADA DE PARAMETROS'!D51 -> sin problemas en la venta | G13: ='ENTRADA DE PARAMETROS'!E51 -> 1.75 | H13: =IF('INGRESO DE DATOS'!$F$11=1,FORMULAS!G13/FORMULAS!$G$13*FORMULAS!$I$11*FORMULAS!$J$3,0) -> 0 | K13: ='ENTRADA DE PARAMETROS'!G51 -> 1 Mayor en 3% a la inflación | L13: ='ENTRADA DE PARAMETROS'!H51 -> 2.5 | M13: =IF('INGRESO DE DATOS'!$J$16=1,L13/$L$13*$N$12*$O$3,0) -> 0 | P13: ='ENTRADA DE PARAMETROS'!J51 -> 2 Bueno | Q13: ='ENTRADA DE PARAMETROS'!K51 -> 3 | R13: =IF('INGRESO DE DATOS'!$N$11=2,Q13/$Q$12*$S$11*$T$3,0) -> 0 | U13: ='ENTRADA DE PARAMETROS'!M51 -> 3 Sector estancado, sin proyecciones | V13: ='ENTRADA DE PARAMETROS'!N51 -> 2 | W13: =IF('INGRESO DE DATOS'!$R$11=3,V13/$V$11*$X$10*$Y$3,0) -> 0
A14: ='ENTRADA DE PARAMETROS'!A52 -> 3 Entre 1 y 2 años | B14: ='ENTRADA DE PARAMETROS'!B52 -> 1 | C14: =IF('INGRESO DE DATOS'!$B$11=3,FORMULAS!B14/$B$12*$D$11*$E$3,0) -> 0 | F14: ='ENTRADA DE PARAMETROS'!D52 -> 2 Evidencia buen nivel de ventas, pero con | K14: ='ENTRADA DE PARAMETROS'!G52 -> 2 Igual a la inflación | L14: ='ENTRADA DE PARAMETROS'!H52 -> 1.5 | M14: =IF('INGRESO DE DATOS'!$J$16=2,L14/$L$13*$N$12*$O$3,0) -> 2.109807 | P14: ='ENTRADA DE PARAMETROS'!J52 -> 3 Regular | Q14: ='ENTRADA DE PARAMETROS'!K52 -> 1 | R14: =IF('INGRESO DE DATOS'!$N$11=3,Q14/$Q$12*$S$11*$T$3,0) -> 0 | U14: ='ENTRADA DE PARAMETROS'!M52 -> 4 Sector en recesión, decreciendo | V14: ='ENTRADA DE PARAMETROS'!N52 -> 1 | W14: =IF('INGRESO DE DATOS'!$R$11=4,V14/$V$11*$X$10*$Y$3,0) -> 0
A15: ='ENTRADA DE PARAMETROS'!A53 -> 4 Menos de 1 año | B15: ='ENTRADA DE PARAMETROS'!B53 -> -10 | C15: =IF('INGRESO DE DATOS'!$B$11=4,FORMULAS!B15/$B$12*$D$11*$E$3,0) -> 0 | F15: ='ENTRADA DE PARAMETROS'!D53 -> deficiencias en la organización | G15: ='ENTRADA DE PARAMETROS'!E53 -> 1.25 | H15: =IF('INGRESO DE DATOS'!$F$11=2,FORMULAS!G15/FORMULAS!$G$13*FORMULAS!$I$11*FORMULAS!$J$3,0) -> 1.6037063 | K15: ='ENTRADA DE PARAMETROS'!G53 -> 3 Menor que la inflación | L15: ='ENTRADA DE PARAMETROS'!H53 -> 0 | M15: =IF('INGRESO DE DATOS'!$J$16=3,L15/$L$13*$N$12*$O$3,0) -> 0 | R15: =SUM(R12:R14) -> 3.0737705 | W15: =SUM(W11:W14) -> 4.2154567
C16: =SUM(C12:C15) -> 3.0071104 | F16: ='ENTRADA DE PARAMETROS'!D54 -> 3 Buena o aceptable organización, pero no | K16: ='ENTRADA DE PARAMETROS'!G54 -> 4 Pérdida | L16: ='ENTRADA DE PARAMETROS'!H54 -> -2 | M16: =IF('INGRESO DE DATOS'!$J$16=4,L16/$L$13*$N$12*$O$3,0) -> 0 | P16: ='ENTRADA DE PARAMETROS'!J54 -> Movilización: | S16: ='DETALLE DE CALIFICACIONES'!C52 -> 0.16071429 | T16: =IF($R$1="R",R20,IF($R$1="M",(R20*0.59),0)) -> 0
A17: ='ENTRADA DE PARAMETROS'!A55 -> 1.3 Calidad de referencias | D17: ='DETALLE DE CALIFICACIONES'!C16 -> 0.10240964 | E17: =C27 -> 2.4343275 | F17: ='ENTRADA DE PARAMETROS'!D55 -> posee registros y/o con medianos problemas de venta | G17: ='ENTRADA DE PARAMETROS'!E55 -> 0.75 | H17: =IF('INGRESO DE DATOS'!$F$11=3,FORMULAS!G17/FORMULAS!$G$13*FORMULAS!$I$11*FORMULAS!$J$3,0) -> 0 | M17: =SUM(M13:M16) -> 2.109807 | P17: ='ENTRADA DE PARAMETROS'!J55 -> 1 Buena | Q17: ='ENTRADA DE PARAMETROS'!K55 -> 4 | R17: =IF('INGRESO DE DATOS'!$N$15=1,Q17/$Q$17*$S$16*$T$3,0) -> 2.7663934 | U17: ='ENTRADA DE PARAMETROS'!M55 -> 5.3 Aceptación del producto | X17: ='DETALLE DE CALIFICACIONES'!C70 -> 0.33766234 | Y17: =W21 -> 3.0444965
A18: ='ENTRADA DE PARAMETROS'!A56 -> Comerciales: | F18: ='ENTRADA DE PARAMETROS'!D56 -> 4 Presenta mala organización, no dispone | K18: ='ENTRADA DE PARAMETROS'!G56 -> 3.3 Sostenibilidad | N18: ='DETALLE DE CALIFICACIONES'!C40 -> 0.14201183 | O18: =M22 -> 1.6878456 | P18: ='ENTRADA DE PARAMETROS'!J56 -> 2 Regular | Q18: ='ENTRADA DE PARAMETROS'!K56 -> 3 | R18: =IF('INGRESO DE DATOS'!$N$15=2,Q18/$Q$17*$S$16*$T$3,0) -> 0 | U18: ='ENTRADA DE PARAMETROS'!M56 -> 1 Alta aceptación por calidad/precio | V18: ='ENTRADA DE PARAMETROS'!N56 -> 4 | W18: =IF('INGRESO DE DATOS'!$R$18=1,V18/$V$18*$X$17*$Y$3,0) -> 0
A19: ='ENTRADA DE PARAMETROS'!A57 -> 1 Buena | B19: ='ENTRADA DE PARAMETROS'!B57 -> 1 | C19: =IF('INGRESO DE DATOS'!$B$17=1,FORMULAS!B19/$B$19*($D$17*$E$3)/2,0) -> 1.2171637 | F19: ='ENTRADA DE PARAMETROS'!D57 -> de registros y/o con graves problemas en la venta | G19: ='ENTRADA DE PARAMETROS'!E57 -> 1 | H19: =IF('INGRESO DE DATOS'!$F$11=4,FORMULAS!G19/FORMULAS!$G$13*FORMULAS!$I$11*FORMULAS!$J$3,0) -> 0 | K19: ='ENTRADA DE PARAMETROS'!G57 -> 1 Relación Ingresos/gastos sobre 1,25 | L19: ='ENTRADA DE PARAMETROS'!H57 -> 4 | M19: =IF('INGRESO DE DATOS'!$J$21=1,L19/$L$19*$N$18*$O$3,0) -> 0 | P19: ='ENTRADA DE PARAMETROS'!J57 -> 3 Deficiente | Q19: ='ENTRADA DE PARAMETROS'!K57 -> 0 | R19: =IF('INGRESO DE DATOS'!$N$15=3,Q19/$Q$17*$S$16*$T$3,0) -> 0 | U19: ='ENTRADA DE PARAMETROS'!M57 -> 2 Mediana aceptación | V19: ='ENTRADA DE PARAMETROS'!N57 -> 2 | W19: =IF('INGRESO DE DATOS'!$R$18=2,V19/$V$18*$X$17*$Y$3,0) -> 3.0444965
A20: ='ENTRADA DE PARAMETROS'!A58 -> 2 Mala | B20: ='ENTRADA DE PARAMETROS'!B58 -> -1 | C20: =IF('INGRESO DE DATOS'!$B$17=2,FORMULAS!B20/$B$19*($D$17*$E$3)/2,0) -> 0 | H20: =SUM(H13:H19) -> 1.6037063 | K20: ='ENTRADA DE PARAMETROS'!G58 -> 2 Relación Ingresos/gastos entre 1,10 y 1,25 | L20: ='ENTRADA DE PARAMETROS'!H58 -> 2 | M20: =IF('INGRESO DE DATOS'!$J$21=2,L20/$L$19*$N$18*$O$3,0) -> 1.6878456 | R20: =SUM(R17:R19) -> 2.7663934 | U20: ='ENTRADA DE PARAMETROS'!M58 -> 3 Baja, dificultosa aceptación | V20: ='ENTRADA DE PARAMETROS'!N58 -> 0 | W20: =IF('INGRESO DE DATOS'!$R$18=3,V20/$V$18*$X$17*$Y$3,0) -> 0
A21: ='ENTRADA DE PARAMETROS'!A59 -> 3 No tiene referencias | B21: ='ENTRADA DE PARAMETROS'!B59 -> 0.2 | C21: =IF('INGRESO DE DATOS'!$B$17=3,FORMULAS!B21/$B$19*($D$17*$E$3)/2,0) -> 0 | F21: ='ENTRADA DE PARAMETROS'!D59 -> 2.3 Dependencia de clientes | I21: ='DETALLE DE CALIFICACIONES'!C28 -> 0.13586957 | J21: =H25 -> 2.3387384 | K21: ='ENTRADA DE PARAMETROS'!G59 -> 3 Relación Ingresos/gastos menor a 1,10 | L21: ='ENTRADA DE PARAMETROS'!H59 -> -20 | M21: =IF('INGRESO DE DATOS'!$J$21=3,L21/$L$19*$N$18*$O$3,0) -> 0 | P21: ='ENTRADA DE PARAMETROS'!J59 -> Calidad edif. adyacentes: | S21: ='DETALLE DE CALIFICACIONES'!C53 -> 0.14285714 | T21: =IF($R$1="R",R25,IF($R$1="M",(R25*0.59),0)) -> 0 | W21: =SUM(W18:W20) -> 3.0444965
F22: ='ENTRADA DE PARAMETROS'!D60 -> 1 Sin importancia/consumo masivo | G22: ='ENTRADA DE PARAMETROS'!E60 -> 1.75 | H22: =IF('INGRESO DE DATOS'!$F$24=1,FORMULAS!G22/FORMULAS!$G$22*FORMULAS!$I$21*FORMULAS!$J$3,0) -> 2.3387384 | M22: =SUM(M19:M21) -> 1.6878456 | P22: ='ENTRADA DE PARAMETROS'!J60 -> 1 Buena | Q22: ='ENTRADA DE PARAMETROS'!K60 -> 4 | R22: =IF('INGRESO DE DATOS'!$N$19=1,Q22/$Q$22*$S$21*$T$3,0) -> 2.4590164 | U22: PUNTAJE TOTAL | X22: =SUM(X5:X21) -> 1 | Y22: =SUM(Y5:Y21) -> 11.47541
A23: ='ENTRADA DE PARAMETROS'!A61 -> Personales: | F23: ='ENTRADA DE PARAMETROS'!D61 -> 2 Entre 4 y 8 compradores | G23: ='ENTRADA DE PARAMETROS'!E61 -> 1 | H23: =IF('INGRESO DE DATOS'!$F$24=2,FORMULAS!G23/FORMULAS!$G$22*FORMULAS!$I$21*FORMULAS!$J$3,0) -> 0 | K23: ='ENTRADA DE PARAMETROS'!G61 -> 3.4 Nivel de endeudamiento | N23: ='DETALLE DE CALIFICACIONES'!C41 -> 0.15384615 | O23: =M29 -> 3.6569987 | P23: ='ENTRADA DE PARAMETROS'!J61 -> 2 Regular | Q23: ='ENTRADA DE PARAMETROS'!K61 -> 3 | R23: =IF('INGRESO DE DATOS'!$N$19=2,Q23/$Q$22*$S$21*$T$3,0) -> 0
A24: ='ENTRADA DE PARAMETROS'!A62 -> 1 Buena | B24: ='ENTRADA DE PARAMETROS'!B62 -> 1 | C24: =IF('INGRESO DE DATOS'!$B$21=1,FORMULAS!B24/$B$24*($D$17*$E$3)/2,0) -> 1.2171637 | F24: ='ENTRADA DE PARAMETROS'!D62 -> 3 Intermediario (entre 1 y 3 compradores) | G24: ='ENTRADA DE PARAMETROS'!E62 -> 0 | H24: =IF('INGRESO DE DATOS'!$F$24=3,FORMULAS!G24/FORMULAS!$G$22*FORMULAS!$I$21*FORMULAS!$J$3,0) -> 0 | K24: ='ENTRADA DE PARAMETROS'!G62 -> Relación Pasivos/Activos | P24: ='ENTRADA DE PARAMETROS'!J62 -> 3 Baja | Q24: ='ENTRADA DE PARAMETROS'!K62 -> 0 | R24: =IF('INGRESO DE DATOS'!$N$19=3,Q24/$Q$22*$S$21*$T$3,0) -> 0
A25: ='ENTRADA DE PARAMETROS'!A63 -> 2 Mala | B25: ='ENTRADA DE PARAMETROS'!B63 -> -1 | C25: =IF('INGRESO DE DATOS'!$B$21=2,FORMULAS!B25/$B$24*($D$17*$E$3)/2,0) -> 0 | H25: =SUM(H22:H24) -> 2.3387384 | K25: ='ENTRADA DE PARAMETROS'!G63 -> 1 Menor al 30% | L25: ='ENTRADA DE PARAMETROS'!H63 -> 4 | M25: =IF('INGRESO DE DATOS'!$J$25=1,L25/$L$25*$N$23*$O$3,0) -> 3.6569987 | R25: =SUM(R22:R24) -> 2.4590164
A26: ='ENTRADA DE PARAMETROS'!A64 -> 3 No tiene referencias | B26: ='ENTRADA DE PARAMETROS'!B64 -> 0.2 | C26: =IF('INGRESO DE DATOS'!$B$21=3,FORMULAS!B26/$B$24*($D$17*$E$3)/2,0) -> 0 | F26: ='ENTRADA DE PARAMETROS'!D64 -> 2.4 Dependencia de proveedores | I26: ='DETALLE DE CALIFICACIONES'!C29 -> 0.11413043 | J26: =H31 -> 1.4734052 | K26: ='ENTRADA DE PARAMETROS'!G64 -> 2 Entre 30% al 40% | L26: ='ENTRADA DE PARAMETROS'!H64 -> 3 | M26: =IF('INGRESO DE DATOS'!$J$25=2,L26/$L$25*$N$23*$O$3,0) -> 0 | P26: ='ENTRADA DE PARAMETROS'!J64 -> Servicios Básicos: | S26: ='DETALLE DE CALIFICACIONES'!C54 -> 0.16071429 | T26: =IF($R$1="R",R30,IF($R$1="M",(R30*0.59),0)) -> 0
C27: =SUM(C19:C26) -> 2.4343275 | F27: ='ENTRADA DE PARAMETROS'!D65 -> 1 Sin importancia/facilidad para proveerse | G27: ='ENTRADA DE PARAMETROS'!E65 -> 1 | H27: =IF('INGRESO DE DATOS'!$F$28=1,FORMULAS!G27/FORMULAS!$G$27*FORMULAS!$I$26*FORMULAS!$J$3,0) -> 0 | K27: ='ENTRADA DE PARAMETROS'!G65 -> 3 Entre 40% y 50% | L27: ='ENTRADA DE PARAMETROS'!H65 -> 2 | M27: =IF('INGRESO DE DATOS'!$J$25=3,L27/$L$25*$N$23*$O$3,0) -> 0 | P27: ='ENTRADA DE PARAMETROS'!J65 -> 1 Todos | Q27: ='ENTRADA DE PARAMETROS'!K65 -> 4 | R27: =IF('INGRESO DE DATOS'!$N$23=1,Q27/$Q$27*$S$26*$T$3,0) -> 2.7663934
A28: ='ENTRADA DE PARAMETROS'!A66 -> 1.4 Calificación Interna | D28: ='DETALLE DE CALIFICACIONES'!C17 -> 0.1746988 | E28: =C36 -> 4.1526763 | F28: ='ENTRADA DE PARAMETROS'!D66 -> 2 Más de 3 proveedores | G28: ='ENTRADA DE PARAMETROS'!E66 -> 0.75 | H28: =IF('INGRESO DE DATOS'!$F$28=2,FORMULAS!G28/FORMULAS!$G$27*FORMULAS!$I$26*FORMULAS!$J$3,0) -> 1.4734052 | K28: ='ENTRADA DE PARAMETROS'!G66 -> 4 Más del 50% | L28: ='ENTRADA DE PARAMETROS'!H66 -> -20 | M28: =IF('INGRESO DE DATOS'!$J$25=4,L28/$L$25*$N$23*$O$3,0) -> 0 | P28: ='ENTRADA DE PARAMETROS'!J66 -> 2 Algunos | Q28: ='ENTRADA DE PARAMETROS'!K66 -> 3 | R28: =IF('INGRESO DE DATOS'!$N$23=2,Q28/$Q$27*$S$26*$T$3,0) -> 0
A29: ='ENTRADA DE PARAMETROS'!A67 -> Referencias bancarias | F29: ='ENTRADA DE PARAMETROS'!D67 -> 3 Entre 2 a 3 proveedores | G29: ='ENTRADA DE PARAMETROS'!E67 -> 0.5 | H29: =IF('INGRESO DE DATOS'!$F$28=3,FORMULAS!G29/FORMULAS!$G$27*FORMULAS!$I$26*FORMULAS!$J$3,0) -> 0 | M29: =SUM(M25:M28) -> 3.6569987 | P29: ='ENTRADA DE PARAMETROS'!J67 -> 3 Ninguno | Q29: ='ENTRADA DE PARAMETROS'!K67 -> 0 | R29: =IF('INGRESO DE DATOS'!$N$23=3,Q29/$Q$27*$S$26*$T$3,0) -> 0
A30: ='ENTRADA DE PARAMETROS'!A68 -> 1 Cliente A | B30: ='ENTRADA DE PARAMETROS'!B68 -> 6 | C30: =IF('INGRESO DE DATOS'!$B$26=1,FORMULAS!B30/$B$30*$D$28*$E$3,0) -> 4.1526763 | F30: ='ENTRADA DE PARAMETROS'!D68 -> 4 Un proveedor, alta dependencia | G30: ='ENTRADA DE PARAMETROS'!E68 -> 0 | H30: =IF('INGRESO DE DATOS'!$F$28=4,FORMULAS!G30/FORMULAS!$G$27*FORMULAS!$I$26*FORMULAS!$J$3,0) -> 0 | K30: ='ENTRADA DE PARAMETROS'!G68 -> 3.5 Medios de producción | N30: ='DETALLE DE CALIFICACIONES'!C42 -> 0.1183432 | O30: =M34 -> 2.813076 | R30: =SUM(R27:R29) -> 2.7663934
A31: ='ENTRADA DE PARAMETROS'!A69 -> 2 Cliente B | B31: ='ENTRADA DE PARAMETROS'!B69 -> 4 | C31: =IF('INGRESO DE DATOS'!$B$26=2,FORMULAS!B31/$B$30*$D$28*$E$3,0) -> 0 | H31: =SUM(H27:H30) -> 1.4734052 | K31: ='ENTRADA DE PARAMETROS'!G69 -> 1 Propietario del negocio o terreno | L31: ='ENTRADA DE PARAMETROS'!H69 -> 2.5 | M31: =IF('INGRESO DE DATOS'!$J$31=1,L31/$L$31*$N$30*$O$3,0) -> 2.813076 | P31: ='ENTRADA DE PARAMETROS'!J69 -> Avalúo: | S31: ='DETALLE DE CALIFICACIONES'!C55 -> 0.17857143 | T31: =IF($R$1="R",R35,IF($R$1="M",(R35*0.59),0)) -> 0
A32: ='ENTRADA DE PARAMETROS'!A70 -> 3 Cliente C | B32: ='ENTRADA DE PARAMETROS'!B70 -> -100 | C32: =IF('INGRESO DE DATOS'!$B$26=3,FORMULAS!B32/$B$30*$D$28*$E$3,0) -> 0 | F32: ='ENTRADA DE PARAMETROS'!D70 -> 2.5 Dependencia del personal | I32: ='DETALLE DE CALIFICACIONES'!C30 -> 0.10869565 | J32: =H36 -> 1.8709907 | K32: ='ENTRADA DE PARAMETROS'!G70 -> 2 En sociedad (al partir) | L32: ='ENTRADA DE PARAMETROS'!H70 -> 2 | M32: =IF('INGRESO DE DATOS'!$J$31=2,L32/$L$31*$N$30*$O$3,0) -> 0 | P32: ='ENTRADA DE PARAMETROS'!J70 -> 1 Más del 200% | Q32: ='ENTRADA DE PARAMETROS'!K70 -> 4 | R32: =IF('INGRESO DE DATOS'!$N$27=1,Q32/$Q$32*$S$31*$T$3,0) -> 3.0737705
A33: ='ENTRADA DE PARAMETROS'!A71 -> 4 Clente D o E | B33: ='ENTRADA DE PARAMETROS'!B71 -> -100 | C33: =IF('INGRESO DE DATOS'!$B$26=4,FORMULAS!B33/$B$30*$D$28*$E$3,0) -> 0 | F33: ='ENTRADA DE PARAMETROS'!D71 -> 1 Familiar | G33: ='ENTRADA DE PARAMETROS'!E71 -> 0.5 | H33: =IF('INGRESO DE DATOS'!$F$33=1,FORMULAS!G33/FORMULAS!$G$33*FORMULAS!$I$32*FORMULAS!$J$3,0) -> 1.8709907 | K33: ='ENTRADA DE PARAMETROS'!G71 -> 3 Negocio o terreno arrendado | L33: ='ENTRADA DE PARAMETROS'!H71 -> 1.5 | M33: =IF('INGRESO DE DATOS'!$J$31=3,L33/$L$31*$N$30*$O$3,0) -> 0 | P33: ='ENTRADA DE PARAMETROS'!J71 -> 2 El 200% | Q33: ='ENTRADA DE PARAMETROS'!K71 -> 2 | R33: =IF('INGRESO DE DATOS'!$N$27=2,Q33/$Q$32*$S$31*$T$3,0) -> 0
A34: ='ENTRADA DE PARAMETROS'!A72 -> 5 Cuentas cerradas | B34: ='ENTRADA DE PARAMETROS'!B72 -> -20 | C34: =IF('INGRESO DE DATOS'!$B$26=5,FORMULAS!B34/$B$30*$D$28*$E$3,0) -> 0 | F34: ='ENTRADA DE PARAMETROS'!D72 -> 2 Familiar y trabajadores | G34: ='ENTRADA DE PARAMETROS'!E72 -> 0.25 | H34: =IF('INGRESO DE DATOS'!$F$33=2,FORMULAS!G34/FORMULAS!$G$33*FORMULAS!$I$32*FORMULAS!$J$3,0) -> 0 | M34: =SUM(M31:M33) -> 2.813076 | P34: ='ENTRADA DE PARAMETROS'!J72 -> 3 Menos del 200% | Q34: ='ENTRADA DE PARAMETROS'!K72 -> -15 | R34: =IF('INGRESO DE DATOS'!$N$27=3,Q34/$Q$32*$S$31*$T$3,0) -> 0
A35: ='ENTRADA DE PARAMETROS'!A73 -> 6 No tienereferencias | B35: ='ENTRADA DE PARAMETROS'!B73 -> 1 | C35: =IF('INGRESO DE DATOS'!$B$26=6,FORMULAS!B35/$B$30*$D$28*$E$3,0) -> 0 | F35: ='ENTRADA DE PARAMETROS'!D73 -> 3 Sólo trabajadores | G35: ='ENTRADA DE PARAMETROS'!E73 -> 0 | H35: =IF('INGRESO DE DATOS'!$F$33=3,FORMULAS!G35/FORMULAS!$G$33*FORMULAS!$I$32*FORMULAS!$J$3,0) -> 0 | K35: ='ENTRADA DE PARAMETROS'!G73 -> 3.6 Razon Corriente | N35: ='DETALLE DE CALIFICACIONES'!C43 -> 0.14792899 | O35: =M40 -> 2.6372587 | R35: =SUM(R32:R34) -> 3.0737705
C36: =SUM(C30:C35) -> 4.1526763 | H36: =SUM(H33:H35) -> 1.8709907 | K36: ='ENTRADA DE PARAMETROS'!G74 -> 1 Màs del 200% | L36: ='ENTRADA DE PARAMETROS'!H74 -> 4 | M36: =IF('INGRESO DE DATOS'!$J$35=1,L36/$L$36*$N$35*$O$3,0) -> 0 | P36: PUNTAJE TOTAL | S36: =SUM(S5:S35) -> 1 | T36: =SUM(T5:T35) -> 0
A37: ='ENTRADA DE PARAMETROS'!A75 -> 1.5 Arraigo Residencial | D37: ='DETALLE DE CALIFICACIONES'!C18 -> 0.12650602 | E37: =C44 -> 1.2028442 | F37: ='ENTRADA DE PARAMETROS'!D75 -> 2.6 Dependencia de la actividad del socio (RURAL) | I37: ='DETALLE DE CALIFICACIONES'!C31 -> 0.13043478 | J37: =IF($G$1="R",H40,IF($G$1="U",H44,0)) -> 2.2451889 | K37: ='ENTRADA DE PARAMETROS'!G75 -> 2 Del 200% al 175% | L37: ='ENTRADA DE PARAMETROS'!H75 -> 3 | M37: =IF('INGRESO DE DATOS'!$J$35=2,L37/$L$36*$N$35*$O$3,0) -> 2.6372587 | P37: ='ENTRADA DE PARAMETROS'!J75 -> 4.2 Garantia Personal
A38: ='ENTRADA DE PARAMETROS'!A76 -> 1 Propio | B38: ='ENTRADA DE PARAMETROS'!B76 -> 5 | C38: =IF('INGRESO DE DATOS'!$B$33=1,FORMULAS!B38/$B$38*$D$37*$E$3,0) -> 0 | F38: ='ENTRADA DE PARAMETROS'!D76 -> 1 Dos actividades o más | G38: ='ENTRADA DE PARAMETROS'!E76 -> 3.5 | H38: =IF('INGRESO DE DATOS'!$F$37=1,FORMULAS!G38/FORMULAS!$G$38*FORMULAS!$I$37*FORMULAS!$J$3,0) -> 2.2451889 | K38: ='ENTRADA DE PARAMETROS'!G76 -> 3 Del 175% al 150% | L38: ='ENTRADA DE PARAMETROS'!H76 -> 2 | M38: =IF('INGRESO DE DATOS'!$J$35=3,L38/$L$36*$N$35*$O$3,0) -> 0 | P38: ='ENTRADA DE PARAMETROS'!J76 -> Historial Credicitio: | S38: ='DETALLE DE CALIFICACIONES'!C60 -> 0.25641026 | T38: =IF($R$1="P",R43,IF($R$1="M",(R43*0.41),0)) -> 4.4136192
A39: ='ENTRADA DE PARAMETROS'!A77 -> 2 Más de 3 años | B39: ='ENTRADA DE PARAMETROS'!B77 -> 4 | C39: =IF('INGRESO DE DATOS'!$B$33=2,FORMULAS!B39/$B$38*$D$37*$E$3,0) -> 0 | F39: ='ENTRADA DE PARAMETROS'!D77 -> 2 Dependencia de 1 sola actividad | G39: ='ENTRADA DE PARAMETROS'!E77 -> 1.5 | H39: =IF('INGRESO DE DATOS'!$F$37=2,FORMULAS!G39/FORMULAS!$G$38*FORMULAS!$I$37*FORMULAS!$J$3,0) -> 0 | K39: ='ENTRADA DE PARAMETROS'!G77 -> 4 Menor a 150% | L39: ='ENTRADA DE PARAMETROS'!H77 -> 0 | M39: =IF('INGRESO DE DATOS'!$J$35=4,L39/$L$36*$N$35*$O$3,0) -> 0 | P39: ='ENTRADA DE PARAMETROS'!J77 -> 1 Pagos puntuales. Primer crédito | Q39: ='ENTRADA DE PARAMETROS'!K77 -> 4 | R39: =IF('INGRESO DE DATOS'!$N$34=1,Q39/$Q$39*$S$38*$T$3,0) -> 4.4136192
A40: ='ENTRADA DE PARAMETROS'!A78 -> 3 Entre 2 y 3 años | B40: ='ENTRADA DE PARAMETROS'!B78 -> 3 | C40: =IF('INGRESO DE DATOS'!$B$33=3,FORMULAS!B40/$B$38*$D$37*$E$3,0) -> 0 | H40: =SUM(H38:H39) -> 2.2451889 | M40: =SUM(M36:M39) -> 2.6372587 | P40: ='ENTRADA DE PARAMETROS'!J78 -> 2 Atrasado | Q40: ='ENTRADA DE PARAMETROS'!K78 -> 1 | R40: =IF('INGRESO DE DATOS'!$N$34=2,Q40/$Q$39*$S$38*$T$3,0) -> 0
A41: ='ENTRADA DE PARAMETROS'!A79 -> 4 Entre 1 y 2 años | B41: ='ENTRADA DE PARAMETROS'!B79 -> 2 | C41: =IF('INGRESO DE DATOS'!$B$33=4,FORMULAS!B41/$B$38*$D$37*$E$3,0) -> 1.2028442 | F41: ='ENTRADA DE PARAMETROS'!D79 -> 2.6 Dependencia de la actividad del socio (URBANO) | K41: ='ENTRADA DE PARAMETROS'!G79 -> 3.7 Reprocidad de depòsitos | N41: ='DETALLE DE CALIFICACIONES'!C44 -> 0.11242604 | O41: =M45 -> 1.3362111 | P41: ='ENTRADA DE PARAMETROS'!J79 -> 3 Moroso | Q41: ='ENTRADA DE PARAMETROS'!K79 -> 0 | R41: =IF('INGRESO DE DATOS'!$N$34=3,Q41/$Q$39*$S$38*$T$3,0) -> 0
A42: ='ENTRADA DE PARAMETROS'!A80 -> 5 Menos de 1 año | B42: ='ENTRADA DE PARAMETROS'!B80 -> -5 | C42: =IF('INGRESO DE DATOS'!$B$33=5,FORMULAS!B42/$B$38*$D$37*$E$3,0) -> 0 | F42: ='ENTRADA DE PARAMETROS'!D80 -> 1 Dependencia de 1 sola actividad | G42: ='ENTRADA DE PARAMETROS'!E80 -> 3.5 | H42: =IF('INGRESO DE DATOS'!$F$41=1,FORMULAS!G42/FORMULAS!$G$42*FORMULAS!$I$37*FORMULAS!$J$3,0) -> 2.2451889 | K42: ='ENTRADA DE PARAMETROS'!G80 -> 1 Favorable | L42: ='ENTRADA DE PARAMETROS'!H80 -> 4 | M42: =IF('INGRESO DE DATOS'!$J$40=1,L42/$L$42*$N$41*$O$3,0) -> 0 | P42: ='ENTRADA DE PARAMETROS'!J80 -> 4 Juicio o castigado | Q42: ='ENTRADA DE PARAMETROS'!K80 -> -20 | R42: =IF('INGRESO DE DATOS'!$N$34=4,Q42/$Q$39*$S$38*$T$3,0) -> 0
A43: ='ENTRADA DE PARAMETROS'!A81 -> 6 No residente | B43: ='ENTRADA DE PARAMETROS'!B81 -> -15 | C43: =IF('INGRESO DE DATOS'!$B$33=6,FORMULAS!B43/$B$38*$D$37*$E$3,0) -> 0 | F43: ='ENTRADA DE PARAMETROS'!D81 -> 2 Dos actividades o más | G43: ='ENTRADA DE PARAMETROS'!E81 -> 1.5 | H43: =IF('INGRESO DE DATOS'!$F$41=2,FORMULAS!G43/FORMULAS!$G$42*FORMULAS!$I$37*FORMULAS!$J$3,0) -> 0 | K43: ='ENTRADA DE PARAMETROS'!G81 -> 2 Regular | L43: ='ENTRADA DE PARAMETROS'!H81 -> 2 | M43: =IF('INGRESO DE DATOS'!$J$40=2,L43/$L$42*$N$41*$O$3,0) -> 1.3362111 | R43: =SUM(R39:R42) -> 4.4136192
C44: =SUM(C38:C43) -> 1.2028442 | H44: =SUM(H42:H43) -> 2.2451889 | K44: ='ENTRADA DE PARAMETROS'!G82 -> 3 Desfavorable | L44: ='ENTRADA DE PARAMETROS'!H82 -> 0 | M44: =IF('INGRESO DE DATOS'!$J$40=3,L44/$L$42*$N$41*$O$3,0) -> 0 | P44: ='ENTRADA DE PARAMETROS'!J82 -> Capacidad de Pago: | S44: ='DETALLE DE CALIFICACIONES'!C61 -> 0.25641026 | T44: =IF($R$1="P",R49,IF($R$1="M",(R49*0.41),0)) -> 4.4136192
A45: ='ENTRADA DE PARAMETROS'!A83 -> 1.6 Estado Civil | D45: ='DETALLE DE CALIFICACIONES'!C19 -> 0.090361446 | E45: =C51 -> 1.073968 | F45: ='ENTRADA DE PARAMETROS'!D83 -> 2.7 Capacidad Administrativa (Educación) | I45: ='DETALLE DE CALIFICACIONES'!C32 -> 0.11956522 | J45: =H49 -> 2.0580898 | M45: =SUM(M42:M44) -> 1.3362111 | P45: ='ENTRADA DE PARAMETROS'!J83 -> 1 Suficiente | Q45: ='ENTRADA DE PARAMETROS'!K83 -> 4 | R45: =IF('INGRESO DE DATOS'!$N$39=1,Q45/$Q$45*$S$44*$T$3,0) -> 4.4136192
A46: ='ENTRADA DE PARAMETROS'!A84 -> 1 Casado | B46: ='ENTRADA DE PARAMETROS'!B84 -> 2 | C46: =IF('INGRESO DE DATOS'!$B$40=1,FORMULAS!B46/$B$46*$D$45*$E$3,0) -> 0 | F46: ='ENTRADA DE PARAMETROS'!D84 -> 1 Educación Superior | G46: ='ENTRADA DE PARAMETROS'!E84 -> 2.5 | H46: =IF('INGRESO DE DATOS'!$F$45=1,FORMULAS!G46/FORMULAS!$G$46*FORMULAS!$I$45*FORMULAS!$J$3,0) -> 2.0580898 | K46: PUNTAJE TOTAL | N46: =SUM(N5:N45) -> 1 | O46: =SUM(O5:O45) -> 18.460811 | P46: ='ENTRADA DE PARAMETROS'!J84 -> 2 Buena | Q46: ='ENTRADA DE PARAMETROS'!K84 -> 3 | R46: =IF('INGRESO DE DATOS'!$N$39=2,Q46/$Q$45*$S$44*$T$3,0) -> 0
A47: ='ENTRADA DE PARAMETROS'!A85 -> 2 Viudo | B47: ='ENTRADA DE PARAMETROS'!B85 -> 2 | C47: =IF('INGRESO DE DATOS'!$B$40=2,FORMULAS!B47/$B$46*$D$45*$E$3,0) -> 0 | F47: ='ENTRADA DE PARAMETROS'!D85 -> 2 Educaciòn Secundaria | G47: ='ENTRADA DE PARAMETROS'!E85 -> 2 | H47: =IF('INGRESO DE DATOS'!$F$45=2,FORMULAS!G47/FORMULAS!$G$46*FORMULAS!$I$45*FORMULAS!$J$3,0) -> 0 | P47: ='ENTRADA DE PARAMETROS'!J85 -> 3 Regular | Q47: ='ENTRADA DE PARAMETROS'!K85 -> 1 | R47: =IF('INGRESO DE DATOS'!$N$39=3,Q47/$Q$45*$S$44*$T$3,0) -> 0
A48: ='ENTRADA DE PARAMETROS'!A86 -> 3 Soltero | B48: ='ENTRADA DE PARAMETROS'!B86 -> 1 | C48: =IF('INGRESO DE DATOS'!$B$40=3,FORMULAS!B48/$B$46*$D$45*$E$3,0) -> 0 | F48: ='ENTRADA DE PARAMETROS'!D86 -> 3 Educaciòn Primaria | G48: ='ENTRADA DE PARAMETROS'!E86 -> 1.5 | H48: =IF('INGRESO DE DATOS'!$F$45=3,FORMULAS!G48/FORMULAS!$G$46*FORMULAS!$I$45*FORMULAS!$J$3,0) -> 0 | P48: ='ENTRADA DE PARAMETROS'!J86 -> 4 Insuficiente | Q48: ='ENTRADA DE PARAMETROS'!K86 -> -20 | R48: =IF('INGRESO DE DATOS'!$N$39=4,Q48/$Q$45*$S$44*$T$3,0) -> 0
A49: ='ENTRADA DE PARAMETROS'!A87 -> 4 Divorciado | B49: ='ENTRADA DE PARAMETROS'!B87 -> 1 | C49: =IF('INGRESO DE DATOS'!$B$40=4,FORMULAS!B49/$B$46*$D$45*$E$3,0) -> 0 | H49: =SUM(H46:H48) -> 2.0580898 | P49: ='ENTRADA DE PARAMETROS'!J87 -> 0 | R49: =SUM(R45:R48) -> 4.4136192
A50: ='ENTRADA DE PARAMETROS'!A88 -> 5 Unión Libre | B50: ='ENTRADA DE PARAMETROS'!B88 -> 1 | C50: =IF('INGRESO DE DATOS'!$B$40=5,FORMULAS!B50/$B$46*$D$45*$E$3,0) -> 1.073968 | F50: ='ENTRADA DE PARAMETROS'!D88 -> 2.8 Local del negocio (SECTOR URBANO) | I50: ='DETALLE DE CALIFICACIONES'!C33 -> 0.11413043 | J50: =IF($G$1="U",H54,IF($G$1="R",H58,"#nombre?")) -> 1.9645403 | P50: ='ENTRADA DE PARAMETROS'!J88 -> Patrimonio: | S50: ='DETALLE DE CALIFICACIONES'!C62 -> 0.23076923 | T50: =IF($R$1="P",R55,IF($R$1="M",(R55*0.41),0)) -> 3.9722573
C51: =SUM(C46:C50) -> 1.073968 | F51: ='ENTRADA DE PARAMETROS'!D89 -> 1 Propio | G51: ='ENTRADA DE PARAMETROS'!E89 -> 3 | H51: =IF('INGRESO DE DATOS'!$F$49=1,FORMULAS!G51/FORMULAS!$G$51*FORMULAS!$I$50*FORMULAS!$J$3,0) -> 1.9645403 | P51: ='ENTRADA DE PARAMETROS'!J89 -> 1 Más del 200% | Q51: ='ENTRADA DE PARAMETROS'!K89 -> 4 | R51: =IF('INGRESO DE DATOS'!$N$44=1,Q51/$Q$51*$S$50*$T$3,0) -> 3.9722573
A52: ='ENTRADA DE PARAMETROS'!A90 -> 1.7 Genero | D52: ='DETALLE DE CALIFICACIONES'!C20 -> 0.078313253 | E52: =C55 -> 5.5846336 | F52: ='ENTRADA DE PARAMETROS'!D90 -> 2 Arrendado | G52: ='ENTRADA DE PARAMETROS'!E90 -> 2 | H52: =IF('INGRESO DE DATOS'!$F$49=2,FORMULAS!G52/FORMULAS!$G$51*FORMULAS!$I$50*FORMULAS!$J$3,0) -> 0 | P52: ='ENTRADA DE PARAMETROS'!J90 -> 2 Hasta el 200 % | Q52: ='ENTRADA DE PARAMETROS'!K90 -> 3 | R52: =IF('INGRESO DE DATOS'!$N$44=2,Q52/$Q$51*$S$50*$T$3,0) -> 0
A53: ='ENTRADA DE PARAMETROS'!A91 -> 1 Masculino | B53: ='ENTRADA DE PARAMETROS'!B91 -> 1 | C53: =IF('INGRESO DE DATOS'!$B$46=1,FORMULAS!B53/$B$53*$D$52*$E$3,0) -> 0 | F53: ='ENTRADA DE PARAMETROS'!D91 -> 3 Ambulante | G53: ='ENTRADA DE PARAMETROS'!E91 -> 1 | H53: =IF('INGRESO DE DATOS'!$F$49=3,FORMULAS!G53/FORMULAS!$G$51*FORMULAS!$I$50*FORMULAS!$J$3,0) -> 0 | P53: ='ENTRADA DE PARAMETROS'!J91 -> 3 Hasta el 175% | Q53: ='ENTRADA DE PARAMETROS'!K91 -> 2 | R53: =IF('INGRESO DE DATOS'!$N$44=3,Q53/$Q$51*$S$50*$T$3,0) -> 0
A54: ='ENTRADA DE PARAMETROS'!A92 -> 2 Femenino | B54: ='ENTRADA DE PARAMETROS'!B92 -> 3 | C54: =IF('INGRESO DE DATOS'!$B$46=2,FORMULAS!B54/$B$53*$D$52*$E$3,0) -> 5.5846336 | H54: =SUM(H51:H53) -> 1.9645403 | P54: ='ENTRADA DE PARAMETROS'!J92 -> 4 Hasta el 100% | Q54: ='ENTRADA DE PARAMETROS'!K92 -> 0 | R54: =IF('INGRESO DE DATOS'!$N$44=4,Q54/$Q$51*$S$50*$T$3,0) -> 0
C55: =SUM(C53:C54) -> 5.5846336 | F55: ='ENTRADA DE PARAMETROS'!D93 -> 2.8 Local del negocio (SECTOR RURAL) | R55: =SUM(R51:R54) -> 3.9722573
A56: ='ENTRADA DE PARAMETROS'!A94 -> 1.8 Datos Generales bàsicos | D56: ='DETALLE DE CALIFICACIONES'!C21 -> 0.12650602 | E56: =C60 -> 2.0047403 | F56: ='ENTRADA DE PARAMETROS'!D94 -> 1 Propio | G56: ='ENTRADA DE PARAMETROS'!E94 -> 3 | H56: =IF('INGRESO DE DATOS'!$F$53=1,FORMULAS!G56/FORMULAS!$G$56*FORMULAS!$I$50*FORMULAS!$J$3,0) -> 0 | P56: ='ENTRADA DE PARAMETROS'!J94 -> Documentos de respaldo: | S56: ='DETALLE DE CALIFICACIONES'!C63 -> 0.25641026 | T56: =IF($R$1="P",R61,IF($R$1="M",(R61*0.41),0)) -> 4.4136192
A57: ='ENTRADA DE PARAMETROS'!A95 -> 1 Correctos | B57: ='ENTRADA DE PARAMETROS'!B95 -> 3 | C57: =IF('INGRESO DE DATOS'!$B$49=1,FORMULAS!B57/$B$57*$D$56*$E$3,0) -> 0 | F57: ='ENTRADA DE PARAMETROS'!D95 -> 2 Arrendado | G57: ='ENTRADA DE PARAMETROS'!E95 -> 1 | H57: =IF('INGRESO DE DATOS'!$F$53=2,FORMULAS!G57/FORMULAS!$G$56*FORMULAS!$I$50*FORMULAS!$J$3,0) -> 0.65484676 | P57: ='ENTRADA DE PARAMETROS'!J95 -> 1 Todos | Q57: ='ENTRADA DE PARAMETROS'!K95 -> 4 | R57: =IF('INGRESO DE DATOS'!$N$49=1,Q57/$Q$57*$S$56*$T$3,0) -> 4.4136192
A58: ='ENTRADA DE PARAMETROS'!A96 -> 2 Incorrectos | B58: ='ENTRADA DE PARAMETROS'!B96 -> 2 | C58: =IF('INGRESO DE DATOS'!$B$49=2,FORMULAS!B58/$B$57*$D$56*$E$3,0) -> 2.0047403 | H58: =SUM(H56:H57) -> 0.65484676 | P58: ='ENTRADA DE PARAMETROS'!J96 -> 2 Aceptables | Q58: ='ENTRADA DE PARAMETROS'!K96 -> 3 | R58: =IF('INGRESO DE DATOS'!$N$49=2,Q58/$Q$57*$S$56*$T$3,0) -> 0
A59: ='ENTRADA DE PARAMETROS'!A97 -> 3 Incompletos | B59: ='ENTRADA DE PARAMETROS'!B97 -> 0 | C59: =IF('INGRESO DE DATOS'!$B$49=3,FORMULAS!B59/$B$57*$D$56*$E$3,0) -> 0 | P59: ='ENTRADA DE PARAMETROS'!J97 -> 3 No Aceptables | Q59: ='ENTRADA DE PARAMETROS'!K97 -> 0 | R59: =IF('INGRESO DE DATOS'!$N$49=3,Q59/$Q$57*$S$56*$T$3,0) -> 0
C60: =SUM(C57:C59) -> 2.0047403 | P60: ='ENTRADA DE PARAMETROS'!J98 -> 4 Ninguno | Q60: ='ENTRADA DE PARAMETROS'!K98 -> -20 | R60: =IF('INGRESO DE DATOS'!$N$49=4,Q60/$Q$57*$S$56*$T$3,0) -> 0
A61: PUNTAJE TOTAL | D61: =SUM(D5:D60) -> 1 | E61: =SUM(E5:E60) -> 23.612976 | F61: PUNTAJE TOTAL | I61: =SUM(I5:I60) -> 1 | J61: =SUM(J5:J60) -> 16.080497 | R61: =SUM(R57:R60) -> 4.4136192
P62: PUNTAJE TOTAL | S62: =SUM(S38:S61) -> 1 | T62: =SUM(T38:T61) -> 17.213115
P64: TOTAL GARANTIAS MIXTAS | S64: 1 | T64: =T36+T62 -> 17.213115

Sheet OFICIALES DE NEGOCIO
A3: Nº | B3: OFICINA | C3: CÓDIGO | D3: CÓDIGO OFICIAL DE NEG. | E3: NOMBRES Y APELLIDOS
A4: 1 | B4: TULCAN | C4: 1 | D4: 1-01 | E4: CHIRIBOGA VALENCIA SOFIA CAROLINA
A5: 2 | B5: TULCAN | C5: 1 | D5: 1-02 | E5: GUZMAN TATES JOHANA LICETH
A6: 3 | B6: TULCAN | C6: 1 | D6: 1-03 | E6: ENRIQUEZ MERA DARWIN JAVIER
A7: 4 | B7: TULCAN | C7: 1 | D7: 1-04 | E7: FUEL CHINGAL ANA KAREN
A8: 5 | B8: TULCAN | C8: 1 | D8: 1-05 | E8: ERAZO DEL CASTILLO DIANA MILENA
A9: 6 | B9: TULCAN | C9: 1 | D9: 1-06 | E9: DISPONIBLE
A10: 7 | B10: TULCAN | C10: 1 | D10: 1-07 | E10: FUENTES BOLAÑOS JENNIFFER JOHANNA
A11: 8 | B11: TULCAN | C11: 1 | D11: 1-08 | E11: QUIÑONEZ MONTERO MARGOTH KATHERINE
A12: 9 | B12: TULCAN | C12: 1 | D12: 1-09 | E12: NARVAEZ CARDENAS ELSSIE MABEL
A13: 10 | B13: TULCAN | C13: 1 | D13: 1-10 | E13: RODRIGUEZ BUSTOS LUCIA GRACIELA
A14: 11 | B14: TULCAN | C14: 1 | D14: 1-11 | E14: DISPONIBLE
A15: 12 | B15: TULCAN | C15: 1 | D15: 1-12 | E15: DISPONIBLE
... A50: 47 | B50: QUITO | C50: 6 | D50: 6-10 | E50: RUANO FLORES ROSA VIRGINIA
B51: QUITO | C51: 6 | D51: 6-11 | E51: ESPINOZA JARAMILLO MARIA EUGENIA
A52: 48 | B52: LAGO AGRIO | C52: 7 | D52: 7-01 | E52: BRAVO ORELLANA LILIANA ELIZABETH
A53: 49 | B53: LAGO AGRIO | C53: 7 | D53: 7-02 | E53: MENDIETA VELEZ TANYI MARIA
A54: 50 | B54: LAGO AGRIO | C54: 7 | D54: 7-03 | E54: JARAMILLO JIMENEZ CARLOS ISRAEL
A55: 51 | B55: LAGO AGRIO | C55: 7 | D55: 7-04 | E55: CHANGO CAMACHO MARCIA VERONICA
A56: 52 | B56: IBARRA AMAZONAS | C56: 8 | D56: 8-01 | E56: FIALLOS GRIJALVA BLANCA RUBY
A57: 53 | B57: IBARRA AMAZONAS | C57: 8 | D57: 8-02 | E57: HERNANDEZ CHACUA AURA SUSANA
A58: 54 | B58: IBARRA AMAZONAS | C58: 8 | D58: 8-03 | E58: ALBAN ARCOS SEBASTIAN LEONARDO
A59: 55 | B59: IBARRA AMAZONAS | C59: 8 | D59: 8-04 | E59: MORETA CACUANGO JUANA XIMENA
A60: 56 | B60: IBARRA AMAZONAS | C60: 8 | D60: 8-05 | E60: CRIOLLO SANDOVAL LUISA GIOCONDA
A61: 57 | B61: IBARRA AMAZONAS | C61: 8 | D61: 8-06 | E61: URCUANGO YACELGA JORGE IVAN
B62: IBARRA AMAZONAS | C62: 8 | D62: 8-07 | E62: BOLAÑOS BASTIDAS PAUL ALEJANDRO
B63: IBARRA AMAZONAS | C63: 8 | D63: 8-08 | E63: CONDOR TUTILLO MAYRA ALEJANDRA
A64: 58 | B64: IBARRA MAYORISTA | C64: 9 | D64: 9-01 | E64: MORILLO POZO IRENE PATRICIA
A65: 59 | B65: IBARRA MAYORISTA | C65: 9 | D65: 9-02 | E65: BOLAÑOS ITAS ESTEBAN FABRICIO
A66: 60 | B66: ATUNTAQUI | C66: 10 | D66: 10-01 | E66: ARTIEDA CHUMA KARINA GABRIELA
A67: 61 | B67: ATUNTAQUI | C67: 10 | D67: 10-02 | E67: MONTALVO ENDARA MARCO ANTONIO
A68: 62 | B68: ATUNTAQUI | C68: 10 | D68: 10-03 | E68: MONTENEGRO LOPEZ KATHERINE FERNANDA
A69: 63 | B69: ATUNTAQUI | C69: 10 | D69: 10-04 | E69: TERAN POSSO SILVIA VANESSA
A70: 64 | B70: ATUNTAQUI | C70: 10 | D70: 10-05 | E70: IBADANGO SANCHEZ SONIA MARLENE
A71: 65 | B71: OTAVALO | C71: 11 | D71: 11-01 | E71: BENALCAZAR CHULDE EDWIN RENE
A72: 66 | B72: OTAVALO | C72: 11 | D72: 11-02 | E72: PAREDES GRANIZO MARCO PATRICIO
A73: 67 | B73: OTAVALO | C73: 11 | D73: 11-03 | E73: LOPEZ CAMUENDO CRISTINA DEL CARMEN
A74: 68 | B74: OTAVALO | C74: 11 | D74: 11-04 | E74: PAREDES ALMEIDA LUIS ANDRES
A75: 69 | B75: OTAVALO | C75: 11 | D75: 11-05 | E75: FLORES BETANCOURT DIANA CAROLINA
... A92: 87 | B92: TUMBACO | C92: 14 | D92: 14-08 | E92: ALMEIDA PIEDRA JOSSELIN FERNANDA
C93: 14 | D93: 14-09 | E93: ROJAS JARAMILLO JEANETH MARIA
E98: 89
D99: DISPONIBLE | E99: 12
D100: TOTAL OFICIALES | E100: =+E98-E99 -> 77

Sheet TIPOS DE PRÉSTAMO
A1: TIPO DE PRÉSTAMO
A2: 1 | B2: A EMPLEADOS Y DIRECTIVOS ORDINARIO
A3: 1-01 | B3: A EMPLEADOS Y DIRECTIVOS ORDINARIO NOVADO REFINANCIADO REESTRUCTURADO
A4: 2 | B4: A PROFESIONALES DE LA CONSTRUCCION
A5: 2-01 | B5: A PROFESIONALES DE LA CONSTRUCCION NOVADO REFINANCIADO REESTRUCTURADO
A6: 3 | B6: CREDITO EDUCATIVO
A7: 3-01 | B7: CREDITO EDUCATIVO NOVADO REFINANCIADO REESTRUCTURADO
A8: 4 | B8: ORDINARIO SIN GARANTE
A9: 4-01 | B9: ORDINARIO SIN GARANTE NOVADO REFINANCIADO REESTRUCTURADO
A10: 5 | B10: ESPECIAL A INSTITUCIONES ORDINARIO
A11: 5-01 | B11: ESPECIAL INSTITUCIONES ORDINARIO NOVADO REFINANCIADO REESTRUCTURADO
A12: 6 | B12: ESPECIAL INSTITUCIONES HIPOTECARIO
A13: 6-01 | B13: ESPECIAL INSTITUCIONES HIPOTECARIO NOVADO REFINANCIADO REESTRUCTURADO
... A44: 29 | B44: CRÉDITO POST SIN GARANTE

Sheet  Seguro de Desgravamen Tit+Cony
A6: Cálculo del Seguro de Desgravamen
A8: CAPITAL | B8: 100000
A9: INTERES | B9: 0.14
A10: PLAZO | B10: 84
A11: PAGO POR AÑO | B11: 12 | C11: CUOTA FIJA | D11: =+B8/((1-(1+B13)^-B10)/B13) -> 1874.0012
A12: FRECUENCIA | B12: 30
A13: INTERES MENSUAL | B13: =+B9/B11 -> 0.011666667 | C13: VALOR TOTAL SEGURO | D13: =SUMIF(M19:M198,">0",M19:M198) -> 6039.5173
A14: INTERES DIARIO | B14: =+B9/360 -> 0.00038888889
A15: TASA NETA SEGURO | B15: 0.0118
A17: CUOTA | B17: FECHA | C17: CAPITAL | D17: INTERES | E17: DIAS | F17: CUOTAFIJA | G17: CUOTA+ SEGURO | H17: SALDO | J17: Seguro | K17: Aporte Seps | L17: Seg. Campesivo | M17: Total seguro
B18: =NOW() -> 46079.336 | H18: =+B8 -> 100000 | J18: 0.00118 | K18: 0.035 | L18: 0.005 | M18: =+J18+K18+L18 -> 0.04118
A19: 1 | B19: =+B18+E19 -> 46109.336 | C19: =+$D$11-D19 -> 707.33449 | D19: =+H18*$B$9/360*E19 -> 1166.6667 | E19: 30 | F19: =+C19+D19 -> 1874.0012 | G19: =+F19+M19 -> 1996.7212 | H19: =+H18-C19 -> 99292.666 | J19: =+H18*$J$18 -> 118 | K19: =+J19*$K$18 -> 4.13 | L19: =+J19*$L$18 -> 0.59 | M19: =+J19+K19+L19 -> 122.72
A20: 2 | B20: =+B19+E20 -> 46139.336 | C20: =+$D$11-D20 -> 715.58673 | D20: =+H19*$B$9/360*E20 -> 1158.4144 | E20: 30 | F20: =+C20+D20 -> 1874.0012 | G20: =+F20+M20 -> 1995.8531 | H20: =+H19-C20 -> 98577.079 | J20: =+H19*$J$18 -> 117.16535 | K20: =+J20*$K$18 -> 4.1007871 | L20: =+J20*$L$18 -> 0.58582673 | M20: =+J20+K20+L20 -> 121.85196
A21: 3 | B21: =+B20+E21 -> 46169.336 | C21: =+$D$11-D21 -> 723.93524 | D21: =+H20*$B$9/360*E21 -> 1150.0659 | E21: 30 | F21: =+C21+D21 -> 1874.0012 | G21: =+F21+M21 -> 1994.975 | H21: =+H20-C21 -> 97853.144 | J21: =+H20*$J$18 -> 116.32095 | K21: =+J21*$K$18 -> 4.0712334 | L21: =+J21*$L$18 -> 0.58160476 | M21: =+J21+K21+L21 -> 120.97379
A22: 4 | B22: =NOW() -> 46079.336 | C22: =+$D$11-D22 -> 732.38115 | D22: =+H21*$B$9/360*E22 -> 1141.62 | E22: 30 | F22: =+C22+D22 -> 1874.0012 | G22: =+F22+M22 -> 1994.0865 | H22: =+H21-C22 -> 97120.762 | J22: =+H21*$J$18 -> 115.46671 | K22: =+J22*$K$18 -> 4.0413348 | L22: =+J22*$L$18 -> 0.57733355 | M22: =+J22+K22+L22 -> 120.08538
A23: 5 | B23: =+B22+E23 -> 46109.336 | C23: =+$D$11-D23 -> 740.9256 | D23: =+H22*$B$9/360*E23 -> 1133.0756 | E23: 30 | F23: =+C23+D23 -> 1874.0012 | G23: =+F23+M23 -> 1993.1878 | H23: =+H22-C23 -> 96379.837 | J23: =+H22*$J$18 -> 114.6025 | K23: =+J23*$K$18 -> 4.0110875 | L23: =+J23*$L$18 -> 0.5730125 | M23: =+J23+K23+L23 -> 119.1866
A24: 6 | B24: =+B23+E24 -> 46139.336 | C24: =+$D$11-D24 -> 749.56973 | D24: =+H23*$B$9/360*E24 -> 1124.4314 | E24: 30 | F24: =+C24+D24 -> 1874.0012 | G24: =+F24+M24 -> 1992.2785 | H24: =+H23-C24 -> 95630.267 | J24: =+H23*$J$18 -> 113.72821 | K24: =+J24*$K$18 -> 3.9804873 | L24: =+J24*$L$18 -> 0.56864104 | M24: =+J24+K24+L24 -> 118.27734
A25: 7 | B25: =+B24+E25 -> 46169.336 | C25: =+$D$11-D25 -> 758.31471 | D25: =+H24*$B$9/360*E25 -> 1115.6864 | E25: 30 | F25: =+C25+D25 -> 1874.0012 | G25: =+F25+M25 -> 1991.3586 | H25: =+H24-C25 -> 94871.952 | J25: =+H24*$J$18 -> 112.84372 | K25: =+J25*$K$18 -> 3.94953 | L25: =+J25*$L$18 -> 0.56421858 | M25: =+J25+K25+L25 -> 117.35746
A26: 8 | B26: =NOW() -> 46079.336 | C26: =+$D$11-D26 -> 767.16172 | D26: =+H25*$B$9/360*E26 -> 1106.8394 | E26: 30 | F26: =+C26+D26 -> 1874.0012 | G26: =+F26+M26 -> 1990.428 | H26: =+H25-C26 -> 94104.791 | J26: =+H25*$J$18 -> 111.9489 | K26: =+J26*$K$18 -> 3.9182116 | L26: =+J26*$L$18 -> 0.55974452 | M26: =+J26+K26+L26 -> 116.42686
A27: 9 | B27: =+B26+E27 -> 46109.336 | C27: =+$D$11-D27 -> 776.11194 | D27: =+H26*$B$9/360*E27 -> 1097.8892 | E27: 30 | F27: =+C27+D27 -> 1874.0012 | G27: =+F27+M27 -> 1989.4866 | H27: =+H26-C27 -> 93328.679 | J27: =+H26*$J$18 -> 111.04365 | K27: =+J27*$K$18 -> 3.8865279 | L27: =+J27*$L$18 -> 0.55521826 | M27: =+J27+K27+L27 -> 115.4854
A28: 10 | B28: =+B27+E28 -> 46139.336 | C28: =+$D$11-D28 -> 785.16658 | D28: =+H27*$B$9/360*E28 -> 1088.8346 | E28: 30 | F28: =+C28+D28 -> 1874.0012 | G28: =+F28+M28 -> 1988.5341 | H28: =+H27-C28 -> 92543.512 | J28: =+H27*$J$18 -> 110.12784 | K28: =+J28*$K$18 -> 3.8544744 | L28: =+J28*$L$18 -> 0.5506392 | M28: =+J28+K28+L28 -> 114.53295
A29: 11 | B29: =+B28+E29 -> 46169.336 | C29: =+$D$11-D29 -> 794.32685 | D29: =+H28*$B$9/360*E29 -> 1079.6743 | E29: 30 | F29: =+C29+D29 -> 1874.0012 | G29: =+F29+M29 -> 1987.5706 | H29: =+H28-C29 -> 91749.185 | J29: =+H28*$J$18 -> 109.20134 | K29: =+J29*$K$18 -> 3.8220471 | L29: =+J29*$L$18 -> 0.54600672 | M29: =+J29+K29+L29 -> 113.5694
A30: 12 | B30: =NOW() -> 46079.336 | C30: =+$D$11-D30 -> 803.594 | D30: =+H29*$B$9/360*E30 -> 1070.4072 | E30: 30 | F30: =+C30+D30 -> 1874.0012 | G30: =+F30+M30 -> 1986.5958 | H30: =+H29-C30 -> 90945.591 | J30: =+H29*$J$18 -> 108.26404 | K30: =+J30*$K$18 -> 3.7892414 | L30: =+J30*$L$18 -> 0.54132019 | M30: =+J30+K30+L30 -> 112.5946
A31: 13 | B31: =+B30+E31 -> 46109.336 | C31: =+$D$11-D31 -> 812.96926 | D31: =+H30*$B$9/360*E31 -> 1061.0319 | E31: 30 | F31: =+C31+D31 -> 1874.0012 | G31: =+F31+M31 -> 1985.6096 | H31: =+H30-C31 -> 90132.622 | J31: =+H30*$J$18 -> 107.3158 | K31: =+J31*$K$18 -> 3.7560529 | L31: =+J31*$L$18 -> 0.53657899 | M31: =+J31+K31+L31 -> 111.60843
A32: 14 | B32: =+B31+E32 -> 46139.336 | C32: =+$D$11-D32 -> 822.4539 | D32: =+H31*$B$9/360*E32 -> 1051.5473 | E32: 30 | F32: =+C32+D32 -> 1874.0012 | G32: =+F32+M32 -> 1984.6119 | H32: =+H31-C32 -> 89310.168 | J32: =+H31*$J$18 -> 106.35649 | K32: =+J32*$K$18 -> 3.7224773 | L32: =+J32*$L$18 -> 0.53178247 | M32: =+J32+K32+L32 -> 110.61075
A33: 15 | B33: =+B32+E33 -> 46169.336 | C33: =+$D$11-D33 -> 832.0492 | D33: =+H32*$B$9/360*E33 -> 1041.952 | E33: 30 | F33: =+C33+D33 -> 1874.0012 | G33: =+F33+M33 -> 1983.6026 | H33: =+H32-C33 -> 88478.119 | J33: =+H32*$J$18 -> 105.386 | K33: =+J33*$K$18 -> 3.6885099 | L33: =+J33*$L$18 -> 0.52692999 | M33: =+J33+K33+L33 -> 109.60144
A34: 16 | B34: =NOW() -> 46079.336 | C34: =+$D$11-D34 -> 841.75644 | D34: =+H33*$B$9/360*E34 -> 1032.2447 | E34: 30 | F34: =+C34+D34 -> 1874.0012 | G34: =+F34+M34 -> 1982.5815 | H34: =+H33-C34 -> 87636.362 | J34: =+H33*$J$18 -> 104.40418 | K34: =+J34*$K$18 -> 3.6541463 | L34: =+J34*$L$18 -> 0.5220209 | M34: =+J34+K34+L34 -> 108.58035
A35: 17 | B35: =+B34+E35 -> 46109.336 | C35: =+$D$11-D35 -> 851.57693 | D35: =+H34*$B$9/360*E35 -> 1022.4242 | E35: 30 | F35: =+C35+D35 -> 1874.0012 | G35: =+F35+M35 -> 1981.5485 | H35: =+H34-C35 -> 86784.786 | J35: =+H34*$J$18 -> 103.41091 | K35: =+J35*$K$18 -> 3.6193818 | L35: =+J35*$L$18 -> 0.51705454 | M35: =+J35+K35+L35 -> 107.54734
A36: 18 | B36: =+B35+E36 -> 46139.336 | C36: =+$D$11-D36 -> 861.512 | D36: =+H35*$B$9/360*E36 -> 1012.4892 | E36: 30 | F36: =+C36+D36 -> 1874.0012 | G36: =+F36+M36 -> 1980.5034 | H36: =+H35-C36 -> 85923.274 | J36: =+H35*$J$18 -> 102.40605 | K36: =+J36*$K$18 -> 3.5842116 | L36: =+J36*$L$18 -> 0.51203023 | M36: =+J36+K36+L36 -> 106.50229
A37: 19 | B37: =+B36+E37 -> 46169.336 | C37: =+$D$11-D37 -> 871.56297 | D37: =+H36*$B$9/360*E37 -> 1002.4382 | E37: 30 | F37: =+C37+D37 -> 1874.0012 | G37: =+F37+M37 -> 1979.4462 | H37: =+H36-C37 -> 85051.711 | J37: =+H36*$J$18 -> 101.38946 | K37: =+J37*$K$18 -> 3.5486312 | L37: =+J37*$L$18 -> 0.50694731 | M37: =+J37+K37+L37 -> 105.44504
A38: 20 | B38: =NOW() -> 46079.336 | C38: =+$D$11-D38 -> 881.7312 | D38: =+H37*$B$9/360*E38 -> 992.26996 | E38: 30 | F38: =+C38+D38 -> 1874.0012 | G38: =+F38+M38 -> 1978.3766 | H38: =+H37-C38 -> 84169.979 | J38: =+H37*$J$18 -> 100.36102 | K38: =+J38*$K$18 -> 3.5126356 | L38: =+J38*$L$18 -> 0.50180509 | M38: =+J38+K38+L38 -> 104.37546
A39: 21 | B39: =+B38+E39 -> 46109.336 | C39: =+$D$11-D39 -> 892.01807 | D39: =+H38*$B$9/360*E39 -> 981.98309 | E39: 30 | F39: =+C39+D39 -> 1874.0012 | G39: =+F39+M39 -> 1977.2946 | H39: =+H38-C39 -> 83277.961 | J39: =+H38*$J$18 -> 99.320576 | K39: =+J39*$K$18 -> 3.4762201 | L39: =+J39*$L$18 -> 0.49660288 | M39: =+J39+K39+L39 -> 103.2934
A40: 22 | B40: =+B39+E40 -> 46139.336 | C40: =+$D$11-D40 -> 902.42495 | D40: =+H39*$B$9/360*E40 -> 971.57621 | E40: 30 | F40: =+C40+D40 -> 1874.0012 | G40: =+F40+M40 -> 1976.1999 | H40: =+H39-C40 -> 82375.536 | J40: =+H39*$J$18 -> 98.267994 | K40: =+J40*$K$18 -> 3.4393798 | L40: =+J40*$L$18 -> 0.49133997 | M40: =+J40+K40+L40 -> 102.19871
A41: 23 | B41: =+B40+E41 -> 46169.336 | C41: =+$D$11-D41 -> 912.95324 | D41: =+H40*$B$9/360*E41 -> 961.04792 | E41: 30 | F41: =+C41+D41 -> 1874.0012 | G41: =+F41+M41 -> 1975.0924 | H41: =+H40-C41 -> 81462.583 | J41: =+H40*$J$18 -> 97.203133 | K41: =+J41*$K$18 -> 3.4021097 | L41: =+J41*$L$18 -> 0.48601566 | M41: =+J41+K41+L41 -> 101.09126
A42: 24 | B42: =NOW() -> 46079.336 | C42: =+$D$11-D42 -> 923.60436 | D42: =+H41*$B$9/360*E42 -> 950.3968 | E42: 30 | F42: =+C42+D42 -> 1874.0012 | G42: =+F42+M42 -> 1973.972 | H42: =+H41-C42 -> 80538.979 | J42: =+H41*$J$18 -> 96.125848 | K42: =+J42*$K$18 -> 3.3644047 | L42: =+J42*$L$18 -> 0.48062924 | M42: =+J42+K42+L42 -> 99.970882
A43: 25 | B43: =NOW() -> 46079.336 | C43: =+$D$11-D43 -> 934.37974 | D43: =+H42*$B$9/360*E43 -> 939.62142 | E43: 30 | F43: =+C43+D43 -> 1874.0012 | G43: =+F43+M43 -> 1972.8386 | H43: =+H42-C43 -> 79604.599 | J43: =+H42*$J$18 -> 95.035995 | K43: =+J43*$K$18 -> 3.3262598 | L43: =+J43*$L$18 -> 0.47517997 | M43: =+J43+K43+L43 -> 98.837435
A44: 26 | B44: =+B43+E44 -> 46109.336 | C44: =+$D$11-D44 -> 945.28084 | D44: =+H43*$B$9/360*E44 -> 928.72032 | E44: 30 | F44: =+C44+D44 -> 1874.0012 | G44: =+F44+M44 -> 1971.6919 | H44: =+H43-C44 -> 78659.318 | J44: =+H43*$J$18 -> 93.933427 | K44: =+J44*$K$18 -> 3.2876699 | L44: =+J44*$L$18 -> 0.46966713 | M44: =+J44+K44+L44 -> 97.690764
A45: 27 | B45: =+B44+E45 -> 46139.336 | C45: =+$D$11-D45 -> 956.30912 | D45: =+H44*$B$9/360*E45 -> 917.69205 | E45: 30 | F45: =+C45+D45 -> 1874.0012 | G45: =+F45+M45 -> 1970.5319 | H45: =+H44-C45 -> 77703.009 | J45: =+H44*$J$18 -> 92.817995 | K45: =+J45*$K$18 -> 3.2486298 | L45: =+J45*$L$18 -> 0.46408998 | M45: =+J45+K45+L45 -> 96.530715
A46: 28 | B46: =+B45+E46 -> 46169.336 | C46: =+$D$11-D46 -> 967.46606 | D46: =+H45*$B$9/360*E46 -> 906.53511 | E46: 30 | F46: =+C46+D46 -> 1874.0012 | G46: =+F46+M46 -> 1969.3583 | H46: =+H45-C46 -> 76735.543 | J46: =+H45*$J$18 -> 91.689551 | K46: =+J46*$K$18 -> 3.2091343 | L46: =+J46*$L$18 -> 0.45844775 | M46: =+J46+K46+L46 -> 95.357133
A47: 29 | B47: =NOW() -> 46079.336 | C47: =+$D$11-D47 -> 978.75316 | D47: =+H46*$B$9/360*E47 -> 895.248 | E47: 30 | F47: =+C47+D47 -> 1874.0012 | G47: =+F47+M47 -> 1968.171 | H47: =+H46-C47 -> 75756.79 | J47: =+H46*$J$18 -> 90.547941 | K47: =+J47*$K$18 -> 3.1691779 | L47: =+J47*$L$18 -> 0.4527397 | M47: =+J47+K47+L47 -> 94.169858
A48: 30 | B48: =+B47+E48 -> 46109.336 | C48: =+$D$11-D48 -> 990.17195 | D48: =+H47*$B$9/360*E48 -> 883.82921 | E48: 30 | F48: =+C48+D48 -> 1874.0012 | G48: =+F48+M48 -> 1966.9699 | H48: =+H47-C48 -> 74766.618 | J48: =+H47*$J$18 -> 89.393012 | K48: =+J48*$K$18 -> 3.1287554 | L48: =+J48*$L$18 -> 0.44696506 | M48: =+J48+K48+L48 -> 92.968732
A49: 31 | B49: =+B48+E49 -> 46139.336 | C49: =+$D$11-D49 -> 1001.724 | D49: =+H48*$B$9/360*E49 -> 872.27721 | E49: 30 | F49: =+C49+D49 -> 1874.0012 | G49: =+F49+M49 -> 1965.7548 | H49: =+H48-C49 -> 73764.894 | J49: =+H48*$J$18 -> 88.224609 | K49: =+J49*$K$18 -> 3.0878613 | L49: =+J49*$L$18 -> 0.44112305 | M49: =+J49+K49+L49 -> 91.753593
A50: 32 | B50: =+B49+E50 -> 46169.336 | C50: =+$D$11-D50 -> 1013.4107 | D50: =+H49*$B$9/360*E50 -> 860.59043 | E50: 30 | F50: =+C50+D50 -> 1874.0012 | G50: =+F50+M50 -> 1964.5254 | H50: =+H49-C50 -> 72751.483 | J50: =+H49*$J$18 -> 87.042575 | K50: =+J50*$K$18 -> 3.0464901 | L50: =+J50*$L$18 -> 0.43521287 | M50: =+J50+K50+L50 -> 90.524278
A51: 33 | B51: =NOW() -> 46079.336 | C51: =+$D$11-D51 -> 1025.2339 | D51: =+H50*$B$9/360*E51 -> 848.7673 | E51: 30 | F51: =+C51+D51 -> 1874.0012 | G51: =+F51+M51 -> 1963.2818 | H51: =+H50-C51 -> 71726.249 | J51: =+H50*$J$18 -> 85.84675 | K51: =+J51*$K$18 -> 3.0046363 | L51: =+J51*$L$18 -> 0.42923375 | M51: =+J51+K51+L51 -> 89.28062
A52: 34 | B52: =+B51+E52 -> 46109.336 | C52: =+$D$11-D52 -> 1037.1949 | D52: =+H51*$B$9/360*E52 -> 836.80624 | E52: 30 | F52: =+C52+D52 -> 1874.0012 | G52: =+F52+M52 -> 1962.0236 | H52: =+H51-C52 -> 70689.054 | J52: =+H51*$J$18 -> 84.636974 | K52: =+J52*$K$18 -> 2.9622941 | L52: =+J52*$L$18 -> 0.42318487 | M52: =+J52+K52+L52 -> 88.022453
A53: 35 | B53: =+B52+E53 -> 46139.336 | C53: =+$D$11-D53 -> 1049.2955 | D53: =+H52*$B$9/360*E53 -> 824.70564 | E53: 30 | F53: =+C53+D53 -> 1874.0012 | G53: =+F53+M53 -> 1960.7508 | H53: =+H52-C53 -> 69639.759 | J53: =+H52*$J$18 -> 83.413084 | K53: =+J53*$K$18 -> 2.9194579 | L53: =+J53*$L$18 -> 0.41706542 | M53: =+J53+K53+L53 -> 86.749608
A54: 36 | B54: =+B53+E54 -> 46169.336 | C54: =+$D$11-D54 -> 1061.5373 | D54: =+H53*$B$9/360*E54 -> 812.46385 | E54: 30 | F54: =+C54+D54 -> 1874.0012 | G54: =+F54+M54 -> 1959.4631 | H54: =+H53-C54 -> 68578.222 | J54: =+H53*$J$18 -> 82.174916 | K54: =+J54*$K$18 -> 2.876122 | L54: =+J54*$L$18 -> 0.41087458 | M54: =+J54+K54+L54 -> 85.461912
A55: 37 | B55: =NOW() -> 46079.336 | C55: =+$D$11-D55 -> 1073.9219 | D55: =+H54*$B$9/360*E55 -> 800.07925 | E55: 30 | F55: =+C55+D55 -> 1874.0012 | G55: =+F55+M55 -> 1958.1604 | H55: =+H54-C55 -> 67504.3 | J55: =+H54*$J$18 -> 80.922301 | K55: =+J55*$K$18 -> 2.8322806 | L55: =+J55*$L$18 -> 0.40461151 | M55: =+J55+K55+L55 -> 84.159194
A56: 38 | B56: =+B55+E56 -> 46109.336 | C56: =+$D$11-D56 -> 1086.451 | D56: =+H55*$B$9/360*E56 -> 787.55016 | E56: 30 | F56: =+C56+D56 -> 1874.0012 | G56: =+F56+M56 -> 1956.8424 | H56: =+H55-C56 -> 66417.849 | J56: =+H55*$J$18 -> 79.655074 | K56: =+J56*$K$18 -> 2.7879276 | L56: =+J56*$L$18 -> 0.39827537 | M56: =+J56+K56+L56 -> 82.841277
A57: 39 | B57: =+B56+E57 -> 46139.336 | C57: =+$D$11-D57 -> 1099.1263 | D57: =+H56*$B$9/360*E57 -> 774.8749 | E57: 30 | F57: =+C57+D57 -> 1874.0012 | G57: =+F57+M57 -> 1955.5091 | H57: =+H56-C57 -> 65318.722 | J57: =+H56*$J$18 -> 78.373061 | K57: =+J57*$K$18 -> 2.7430572 | L57: =+J57*$L$18 -> 0.39186531 | M57: =+J57+K57+L57 -> 81.507984
A58: 40 | B58: =+B57+E58 -> 46169.336 | C58: =+$D$11-D58 -> 1111.9494 | D58: =+H57*$B$9/360*E58 -> 762.05176 | E58: 30 | F58: =+C58+D58 -> 1874.0012 | G58: =+F58+M58 -> 1954.1603 | H58: =+H57-C58 -> 64206.773 | J58: =+H57*$J$18 -> 77.076092 | K58: =+J58*$K$18 -> 2.6976632 | L58: =+J58*$L$18 -> 0.38538046 | M58: =+J58+K58+L58 -> 80.159136
A59: 41 | B59: =NOW() -> 46079.336 | C59: =+$D$11-D59 -> 1124.9221 | D59: =+H58*$B$9/360*E59 -> 749.07902 | E59: 30 | F59: =+C59+D59 -> 1874.0012 | G59: =+F59+M59 -> 1952.7957 | H59: =+H58-C59 -> 63081.851 | J59: =+H58*$J$18 -> 75.763992 | K59: =+J59*$K$18 -> 2.6517397 | L59: =+J59*$L$18 -> 0.37881996 | M59: =+J59+K59+L59 -> 78.794552
A60: 42 | B60: =+B59+E60 -> 46109.336 | C60: =+$D$11-D60 -> 1138.0462 | D60: =+H59*$B$9/360*E60 -> 735.95493 | E60: 30 | F60: =+C60+D60 -> 1874.0012 | G60: =+F60+M60 -> 1951.4152 | H60: =+H59-C60 -> 61943.805 | J60: =+H59*$J$18 -> 74.436584 | K60: =+J60*$K$18 -> 2.6052804 | L60: =+J60*$L$18 -> 0.37218292 | M60: =+J60+K60+L60 -> 77.414047
A61: 43 | B61: =+B60+E61 -> 46139.336 | C61: =+$D$11-D61 -> 1151.3234 | D61: =+H60*$B$9/360*E61 -> 722.67772 | E61: 30 | F61: =+C61+D61 -> 1874.0012 | G61: =+F61+M61 -> 1950.0186 | H61: =+H60-C61 -> 60792.481 | J61: =+H60*$J$18 -> 73.093689 | K61: =+J61*$K$18 -> 2.5582791 | L61: =+J61*$L$18 -> 0.36546845 | M61: =+J61+K61+L61 -> 76.017437
A62: 44 | B62: =+B61+E62 -> 46169.336 | C62: =+$D$11-D62 -> 1164.7555 | D62: =+H61*$B$9/360*E62 -> 709.24561 | E62: 30 | F62: =+C62+D62 -> 1874.0012 | G62: =+F62+M62 -> 1948.6057 | H62: =+H61-C62 -> 59627.726 | J62: =+H61*$J$18 -> 71.735128 | K62: =+J62*$K$18 -> 2.5107295 | L62: =+J62*$L$18 -> 0.35867564 | M62: =+J62+K62+L62 -> 74.604533
A63: 45 | B63: =NOW() -> 46079.336 | C63: =+$D$11-D63 -> 1178.3444 | D63: =+H62*$B$9/360*E63 -> 695.6568 | E63: 30 | F63: =+C63+D63 -> 1874.0012 | G63: =+F63+M63 -> 1947.1763 | H63: =+H62-C63 -> 58449.381 | J63: =+H62*$J$18 -> 70.360716 | K63: =+J63*$K$18 -> 2.4626251 | L63: =+J63*$L$18 -> 0.35180358 | M63: =+J63+K63+L63 -> 73.175145
A64: 46 | B64: =+B63+E64 -> 46109.336 | C64: =+$D$11-D64 -> 1192.0917 | D64: =+H63*$B$9/360*E64 -> 681.90945 | E64: 30 | F64: =+C64+D64 -> 1874.0012 | G64: =+F64+M64 -> 1945.7302 | H64: =+H63-C64 -> 57257.29 | J64: =+H63*$J$18 -> 68.97027 | K64: =+J64*$K$18 -> 2.4139594 | L64: =+J64*$L$18 -> 0.34485135 | M64: =+J64+K64+L64 -> 71.729081
A65: 47 | B65: =+B64+E65 -> 46139.336 | C65: =+$D$11-D65 -> 1205.9994 | D65: =+H64*$B$9/360*E65 -> 668.00171 | E65: 30 | F65: =+C65+D65 -> 1874.0012 | G65: =+F65+M65 -> 1944.2673 | H65: =+H64-C65 -> 56051.29 | J65: =+H64*$J$18 -> 67.563602 | K65: =+J65*$K$18 -> 2.3647261 | L65: =+J65*$L$18 -> 0.33781801 | M65: =+J65+K65+L65 -> 70.266146
A66: 48 | B66: =+B65+E66 -> 46169.336 | C66: =+$D$11-D66 -> 1220.0694 | D66: =+H65*$B$9/360*E66 -> 653.93172 | E66: 30 | F66: =+C66+D66 -> 1874.0012 | G66: =+F66+M66 -> 1942.7873 | H66: =+H65-C66 -> 54831.221 | J66: =+H65*$J$18 -> 66.140522 | K66: =+J66*$K$18 -> 2.3149183 | L66: =+J66*$L$18 -> 0.33070261 | M66: =+J66+K66+L66 -> 68.786143
A67: 49 | B67: =NOW() -> 46079.336 | C67: =+$D$11-D67 -> 1234.3036 | D67: =+H66*$B$9/360*E67 -> 639.69757 | E67: 30 | F67: =+C67+D67 -> 1874.0012 | G67: =+F67+M67 -> 1941.29 | H67: =+H66-C67 -> 53596.917 | J67: =+H66*$J$18 -> 64.70084 | K67: =+J67*$K$18 -> 2.2645294 | L67: =+J67*$L$18 -> 0.3235042 | M67: =+J67+K67+L67 -> 67.288874
A68: 50 | B68: =NOW() -> 46079.336 | C68: =+$D$11-D68 -> 1248.7038 | D68: =+H67*$B$9/360*E68 -> 625.29737 | E68: 30 | F68: =+C68+D68 -> 1874.0012 | G68: =+F68+M68 -> 1939.7753 | H68: =+H67-C68 -> 52348.213 | J68: =+H67*$J$18 -> 63.244362 | K68: =+J68*$K$18 -> 2.2135527 | L68: =+J68*$L$18 -> 0.31622181 | M68: =+J68+K68+L68 -> 65.774137
A69: 51 | B69: =+B68+E69 -> 46109.336 | C69: =+$D$11-D69 -> 1263.272 | D69: =+H68*$B$9/360*E69 -> 610.72916 | E69: 30 | F69: =+C69+D69 -> 1874.0012 | G69: =+F69+M69 -> 1938.2429 | H69: =+H68-C69 -> 51084.941 | J69: =+H68*$J$18 -> 61.770892 | K69: =+J69*$K$18 -> 2.1619812 | L69: =+J69*$L$18 -> 0.30885446 | M69: =+J69+K69+L69 -> 64.241727
A70: 52 | B70: =+B69+E70 -> 46139.336 | C70: =+$D$11-D70 -> 1278.0102 | D70: =+H69*$B$9/360*E70 -> 595.99098 | E70: 30 | F70: =+C70+D70 -> 1874.0012 | G70: =+F70+M70 -> 1936.6926 | H70: =+H69-C70 -> 49806.931 | J70: =+H69*$J$18 -> 60.280231 | K70: =+J70*$K$18 -> 2.1098081 | L70: =+J70*$L$18 -> 0.30140115 | M70: =+J70+K70+L70 -> 62.69144
A71: 53 | B71: =+B70+E71 -> 46169.336 | C71: =+$D$11-D71 -> 1292.9203 | D71: =+H70*$B$9/360*E71 -> 581.08086 | E71: 30 | F71: =+C71+D71 -> 1874.0012 | G71: =+F71+M71 -> 1935.1242 | H71: =+H70-C71 -> 48514.011 | J71: =+H70*$J$18 -> 58.772179 | K71: =+J71*$K$18 -> 2.0570263 | L71: =+J71*$L$18 -> 0.29386089 | M71: =+J71+K71+L71 -> 61.123066
A72: 54 | B72: =NOW() -> 46079.336 | C72: =+$D$11-D72 -> 1308.0044 | D72: =+H71*$B$9/360*E72 -> 565.99679 | E72: 30 | F72: =+C72+D72 -> 1874.0012 | G72: =+F72+M72 -> 1933.5376 | H72: =+H71-C72 -> 47206.006 | J72: =+H71*$J$18 -> 57.246533 | K72: =+J72*$K$18 -> 2.0036286 | L72: =+J72*$L$18 -> 0.28623266 | M72: =+J72+K72+L72 -> 59.536394
A73: 55 | B73: =+B72+E73 -> 46109.336 | C73: =+$D$11-D73 -> 1323.2644 | D73: =+H72*$B$9/360*E73 -> 550.73674 | E73: 30 | F73: =+C73+D73 -> 1874.0012 | G73: =+F73+M73 -> 1931.9324 | H73: =+H72-C73 -> 45882.742 | J73: =+H72*$J$18 -> 55.703088 | K73: =+J73*$K$18 -> 1.9496081 | L73: =+J73*$L$18 -> 0.27851544 | M73: =+J73+K73+L73 -> 57.931211
A74: 56 | B74: =+B73+E74 -> 46139.336 | C74: =+$D$11-D74 -> 1338.7025 | D74: =+H73*$B$9/360*E74 -> 535.29866 | E74: 30 | F74: =+C74+D74 -> 1874.0012 | G74: =+F74+M74 -> 1930.3085 | H74: =+H73-C74 -> 44544.04 | J74: =+H73*$J$18 -> 54.141636 | K74: =+J74*$K$18 -> 1.8949572 | L74: =+J74*$L$18 -> 0.27070818 | M74: =+J74+K74+L74 -> 56.307301
A75: 57 | B75: =+B74+E75 -> 46169.336 | C75: =+$D$11-D75 -> 1354.3207 | D75: =+H74*$B$9/360*E75 -> 519.68046 | E75: 30 | F75: =+C75+D75 -> 1874.0012 | G75: =+F75+M75 -> 1928.6656 | H75: =+H74-C75 -> 43189.719 | J75: =+H74*$J$18 -> 52.561967 | K75: =+J75*$K$18 -> 1.8396688 | L75: =+J75*$L$18 -> 0.26280983 | M75: =+J75+K75+L75 -> 54.664445
A76: 58 | B76: =NOW() -> 46079.336 | C76: =+$D$11-D76 -> 1370.1211 | D76: =+H75*$B$9/360*E76 -> 503.88005 | E76: 30 | F76: =+C76+D76 -> 1874.0012 | G76: =+F76+M76 -> 1927.0036 | H76: =+H75-C76 -> 41819.598 | J76: =+H75*$J$18 -> 50.963868 | K76: =+J76*$K$18 -> 1.7837354 | L76: =+J76*$L$18 -> 0.25481934 | M76: =+J76+K76+L76 -> 53.002423
A77: 59 | B77: =+B76+E77 -> 46109.336 | C77: =+$D$11-D77 -> 1386.1059 | D77: =+H76*$B$9/360*E77 -> 487.89531 | E77: 30 | F77: =+C77+D77 -> 1874.0012 | G77: =+F77+M77 -> 1925.3222 | H77: =+H76-C77 -> 40433.492 | J77: =+H76*$J$18 -> 49.347125 | K77: =+J77*$K$18 -> 1.7271494 | L77: =+J77*$L$18 -> 0.24673563 | M77: =+J77+K77+L77 -> 51.32101
A78: 60 | B78: =+B77+E78 -> 46139.336 | C78: =+$D$11-D78 -> 1402.2771 | D78: =+H77*$B$9/360*E78 -> 471.72407 | E78: 30 | F78: =+C78+D78 -> 1874.0012 | G78: =+F78+M78 -> 1923.6211 | H78: =+H77-C78 -> 39031.215 | J78: =+H77*$J$18 -> 47.71152 | K78: =+J78*$K$18 -> 1.6699032 | L78: =+J78*$L$18 -> 0.2385576 | M78: =+J78+K78+L78 -> 49.619981
A79: 61 | B79: =+B78+E79 -> 46169.336 | C79: =+$D$11-D79 -> 1418.637 | D79: =+H78*$B$9/360*E79 -> 455.36417 | E79: 30 | F79: =+C79+D79 -> 1874.0012 | G79: =+F79+M79 -> 1921.9003 | H79: =+H78-C79 -> 37612.578 | J79: =+H78*$J$18 -> 46.056833 | K79: =+J79*$K$18 -> 1.6119892 | L79: =+J79*$L$18 -> 0.23028417 | M79: =+J79+K79+L79 -> 47.899107
A80: 62 | B80: =NOW() -> 46079.336 | C80: =+$D$11-D80 -> 1435.1878 | D80: =+H79*$B$9/360*E80 -> 438.81341 | E80: 30 | F80: =+C80+D80 -> 1874.0012 | G80: =+F80+M80 -> 1920.1593 | H80: =+H79-C80 -> 36177.39 | J80: =+H79*$J$18 -> 44.382842 | K80: =+J80*$K$18 -> 1.5533995 | L80: =+J80*$L$18 -> 0.22191421 | M80: =+J80+K80+L80 -> 46.158156
A81: 63 | B81: =+B80+E81 -> 46109.336 | C81: =+$D$11-D81 -> 1451.9316 | D81: =+H80*$B$9/360*E81 -> 422.06955 | E81: 30 | F81: =+C81+D81 -> 1874.0012 | G81: =+F81+M81 -> 1918.3981 | H81: =+H80-C81 -> 34725.458 | J81: =+H80*$J$18 -> 42.68932 | K81: =+J81*$K$18 -> 1.4941262 | L81: =+J81*$L$18 -> 0.2134466 | M81: =+J81+K81+L81 -> 44.396893
A82: 64 | B82: =+B81+E82 -> 46139.336 | C82: =+$D$11-D82 -> 1468.8708 | D82: =+H81*$B$9/360*E82 -> 405.13035 | E82: 30 | F82: =+C82+D82 -> 1874.0012 | G82: =+F82+M82 -> 1916.6162 | H82: =+H81-C82 -> 33256.588 | J82: =+H81*$J$18 -> 40.976041 | K82: =+J82*$K$18 -> 1.4341614 | L82: =+J82*$L$18 -> 0.2048802 | M82: =+J82+K82+L82 -> 42.615083
A83: 65 | B83: =+B82+E83 -> 46169.336 | C83: =+$D$11-D83 -> 1486.0076 | D83: =+H82*$B$9/360*E83 -> 387.99352 | E83: 30 | F83: =+C83+D83 -> 1874.0012 | G83: =+F83+M83 -> 1914.8136 | H83: =+H82-C83 -> 31770.58 | J83: =+H82*$J$18 -> 39.242773 | K83: =+J83*$K$18 -> 1.3734971 | L83: =+J83*$L$18 -> 0.19621387 | M83: =+J83+K83+L83 -> 40.812484
A84: 66 | B84: =NOW() -> 46079.336 | C84: =+$D$11-D84 -> 1503.3444 | D84: =+H83*$B$9/360*E84 -> 370.65677 | E84: 30 | F84: =+C84+D84 -> 1874.0012 | G84: =+F84+M84 -> 1912.99 | H84: =+H83-C84 -> 30267.236 | J84: =+H83*$J$18 -> 37.489284 | K84: =+J84*$K$18 -> 1.312125 | L84: =+J84*$L$18 -> 0.18744642 | M84: =+J84+K84+L84 -> 38.988856
A85: 67 | B85: =+B84+E85 -> 46109.336 | C85: =+$D$11-D85 -> 1520.8834 | D85: =+H84*$B$9/360*E85 -> 353.11775 | E85: 30 | F85: =+C85+D85 -> 1874.0012 | G85: =+F85+M85 -> 1911.1451 | H85: =+H84-C85 -> 28746.352 | J85: =+H84*$J$18 -> 35.715338 | K85: =+J85*$K$18 -> 1.2500368 | L85: =+J85*$L$18 -> 0.17857669 | M85: =+J85+K85+L85 -> 37.143952
A86: 68 | B86: =+B85+E86 -> 46139.336 | C86: =+$D$11-D86 -> 1538.6271 | D86: =+H85*$B$9/360*E86 -> 335.37411 | E86: 30 | F86: =+C86+D86 -> 1874.0012 | G86: =+F86+M86 -> 1909.2787 | H86: =+H85-C86 -> 27207.725 | J86: =+H85*$J$18 -> 33.920696 | K86: =+J86*$K$18 -> 1.1872243 | L86: =+J86*$L$18 -> 0.16960348 | M86: =+J86+K86+L86 -> 35.277523
A87: 69 | B87: =+B86+E87 -> 46169.336 | C87: =+$D$11-D87 -> 1556.5777 | D87: =+H86*$B$9/360*E87 -> 317.42346 | E87: 30 | F87: =+C87+D87 -> 1874.0012 | G87: =+F87+M87 -> 1907.3905 | H87: =+H86-C87 -> 25651.147 | J87: =+H86*$J$18 -> 32.105116 | K87: =+J87*$K$18 -> 1.123679 | L87: =+J87*$L$18 -> 0.16052558 | M87: =+J87+K87+L87 -> 33.38932
A88: 70 | B88: =NOW() -> 46079.336 | C88: =+$D$11-D88 -> 1574.7378 | D88: =+H87*$B$9/360*E88 -> 299.26339 | E88: 30 | F88: =+C88+D88 -> 1874.0012 | G88: =+F88+M88 -> 1905.4802 | H88: =+H87-C88 -> 24076.41 | J88: =+H87*$J$18 -> 30.268354 | K88: =+J88*$K$18 -> 1.0593924 | L88: =+J88*$L$18 -> 0.15134177 | M88: =+J88+K88+L88 -> 31.479088
A89: 71 | B89: =+B88+E89 -> 46109.336 | C89: =+$D$11-D89 -> 1593.1097 | D89: =+H88*$B$9/360*E89 -> 280.89145 | E89: 30 | F89: =+C89+D89 -> 1874.0012 | G89: =+F89+M89 -> 1903.5477 | H89: =+H88-C89 -> 22483.3 | J89: =+H88*$J$18 -> 28.410163 | K89: =+J89*$K$18 -> 0.99435572 | L89: =+J89*$L$18 -> 0.14205082 | M89: =+J89+K89+L89 -> 29.54657
A90: 72 | B90: =+B89+E90 -> 46139.336 | C90: =+$D$11-D90 -> 1611.696 | D90: =+H89*$B$9/360*E90 -> 262.30517 | E90: 30 | F90: =+C90+D90 -> 1874.0012 | G90: =+F90+M90 -> 1901.5927 | H90: =+H89-C90 -> 20871.604 | J90: =+H89*$J$18 -> 26.530294 | K90: =+J90*$K$18 -> 0.92856029 | L90: =+J90*$L$18 -> 0.13265147 | M90: =+J90+K90+L90 -> 27.591506
A91: 73 | B91: =+B90+E91 -> 46169.336 | C91: =+$D$11-D91 -> 1630.4991 | D91: =+H90*$B$9/360*E91 -> 243.50205 | E91: 30 | F91: =+C91+D91 -> 1874.0012 | G91: =+F91+M91 -> 1899.6148 | H91: =+H90-C91 -> 19241.105 | J91: =+H90*$J$18 -> 24.628493 | K91: =+J91*$K$18 -> 0.86199724 | L91: =+J91*$L$18 -> 0.12314246 | M91: =+J91+K91+L91 -> 25.613632
A92: 74 | B92: =NOW() -> 46079.336 | C92: =+$D$11-D92 -> 1649.5216 | D92: =+H91*$B$9/360*E92 -> 224.47956 | E92: 30 | F92: =+C92+D92 -> 1874.0012 | G92: =+F92+M92 -> 1897.6138 | H92: =+H91-C92 -> 17591.583 | J92: =+H91*$J$18 -> 22.704504 | K92: =+J92*$K$18 -> 0.79465763 | L92: =+J92*$L$18 -> 0.11352252 | M92: =+J92+K92+L92 -> 23.612684
A93: 75 | B93: =NOW() -> 46079.336 | C93: =+$D$11-D93 -> 1668.766 | D93: =+H92*$B$9/360*E93 -> 205.23514 | E93: 30 | F93: =+C93+D93 -> 1874.0012 | G93: =+F93+M93 -> 1895.5896 | H93: =+H92-C93 -> 15922.817 | J93: =+H92*$J$18 -> 20.758068 | K93: =+J93*$K$18 -> 0.72653239 | L93: =+J93*$L$18 -> 0.10379034 | M93: =+J93+K93+L93 -> 21.588391
A94: 76 | B94: =+B93+E94 -> 46109.336 | C94: =+$D$11-D94 -> 1688.235 | D94: =+H93*$B$9/360*E94 -> 185.7662 | E94: 30 | F94: =+C94+D94 -> 1874.0012 | G94: =+F94+M94 -> 1893.5416 | H94: =+H93-C94 -> 14234.582 | J94: =+H93*$J$18 -> 18.788924 | K94: =+J94*$K$18 -> 0.65761235 | L94: =+J94*$L$18 -> 0.093944622 | M94: =+J94+K94+L94 -> 19.540481
A95: 77 | B95: =+B94+E95 -> 46139.336 | C95: =+$D$11-D95 -> 1707.931 | D95: =+H94*$B$9/360*E95 -> 166.07013 | E95: 30 | F95: =+C95+D95 -> 1874.0012 | G95: =+F95+M95 -> 1891.4698 | H95: =+H94-C95 -> 12526.651 | J95: =+H94*$J$18 -> 16.796807 | K95: =+J95*$K$18 -> 0.58788825 | L95: =+J95*$L$18 -> 0.083984035 | M95: =+J95+K95+L95 -> 17.468679
A96: 78 | B96: =+B95+E96 -> 46169.336 | C96: =+$D$11-D96 -> 1727.8569 | D96: =+H95*$B$9/360*E96 -> 146.14426 | E96: 30 | F96: =+C96+D96 -> 1874.0012 | G96: =+F96+M96 -> 1889.3739 | H96: =+H95-C96 -> 10798.794 | J96: =+H95*$J$18 -> 14.781448 | K96: =+J96*$K$18 -> 0.5173507 | L96: =+J96*$L$18 -> 0.073907242 | M96: =+J96+K96+L96 -> 15.372706
A97: 79 | B97: =NOW() -> 46079.336 | C97: =+$D$11-D97 -> 1748.0152 | D97: =+H96*$B$9/360*E97 -> 125.98593 | E97: 30 | F97: =+C97+D97 -> 1874.0012 | G97: =+F97+M97 -> 1887.2534 | H97: =+H96-C97 -> 9050.7791 | J97: =+H96*$J$18 -> 12.742577 | K97: =+J97*$K$18 -> 0.44599021 | L97: =+J97*$L$18 -> 0.063712887 | M97: =+J97+K97+L97 -> 13.25228
A98: 80 | B98: =+B97+E98 -> 46109.336 | C98: =+$D$11-D98 -> 1768.4087 | D98: =+H97*$B$9/360*E98 -> 105.59242 | E98: 30 | F98: =+C98+D98 -> 1874.0012 | G98: =+F98+M98 -> 1885.1083 | H98: =+H97-C98 -> 7282.3704 | J98: =+H97*$J$18 -> 10.679919 | K98: =+J98*$K$18 -> 0.37379718 | L98: =+J98*$L$18 -> 0.053399597 | M98: =+J98+K98+L98 -> 11.107116
A99: 81 | B99: =+B98+E99 -> 46139.336 | C99: =+$D$11-D99 -> 1789.0402 | D99: =+H98*$B$9/360*E99 -> 84.960988 | E99: 30 | F99: =+C99+D99 -> 1874.0012 | G99: =+F99+M99 -> 1882.9381 | H99: =+H98-C99 -> 5493.3302 | J99: =+H98*$J$18 -> 8.593197 | K99: =+J99*$K$18 -> 0.3007619 | L99: =+J99*$L$18 -> 0.042965985 | M99: =+J99+K99+L99 -> 8.9369249
A100: 82 | B100: =+B99+E100 -> 46169.336 | C100: =+$D$11-D100 -> 1809.9123 | D100: =+H99*$B$9/360*E100 -> 64.088852 | E100: 30 | F100: =+C100+D100 -> 1874.0012 | G100: =+F100+M100 -> 1880.7426 | H100: =+H99-C100 -> 3683.4179 | J100: =+H99*$J$18 -> 6.4821296 | K100: =+J100*$K$18 -> 0.22687454 | L100: =+J100*$L$18 -> 0.032410648 | M100: =+J100+K100+L100 -> 6.7414148
A101: 83 | B101: =NOW() -> 46079.336 | C101: =+$D$11-D101 -> 1831.028 | D101: =+H100*$B$9/360*E101 -> 42.973209 | E101: 30 | F101: =+C101+D101 -> 1874.0012 | G101: =+F101+M101 -> 1878.5215 | H101: =+H100-C101 -> 1852.3899 | J101: =+H100*$J$18 -> 4.3464331 | K101: =+J101*$K$18 -> 0.15212516 | L101: =+J101*$L$18 -> 0.021732166 | M101: =+J101+K101+L101 -> 4.5202904
A102: 84 | B102: =+B101+E102 -> 46109.336 | C102: =+$D$11-D102 -> 1852.3899 | D102: =+H101*$B$9/360*E102 -> 21.611216 | E102: 30 | F102: =+C102+D102 -> 1874.0012 | G102: =+F102+M102 -> 1876.2744 | H102: =+H101-C102 -> 7.1918294e-10 | J102: =+H101*$J$18 -> 2.1858201 | K102: =+J102*$K$18 -> 0.076503705 | L102: =+J102*$L$18 -> 0.010929101 | M102: =+J102+K102+L102 -> 2.2732529
A103: 85 | B103: =+B102+E103 -> 46139.336 | C103: =+$D$11-D103 -> 1874.0012 | D103: =+H102*$B$9/360*E103 -> 8.3904676e-12 | E103: 30 | F103: =+C103+D103 -> 1874.0012 | G103: =+F103+M103 -> 1874.0012 | H103: =+H102-C103 -> -1874.0012 | J103: =+H102*$J$18 -> 8.4863586e-13 | K103: =+J103*$K$18 -> 2.9702255e-14 | L103: =+J103*$L$18 -> 4.2431793e-15 | M103: =+J103+K103+L103 -> 8.825813e-13
A104: 86 | B104: =+B103+E104 -> 46169.336 | C104: =+$D$11-D104 -> 1895.8645 | D104: =+H103*$B$9/360*E104 -> -21.863347 | E104: 30 | F104: =+C104+D104 -> 1874.0012 | G104: =+F104+M104 -> 1871.7014 | H104: =+H103-C104 -> -3769.8657 | J104: =+H103*$J$18 -> -2.2113214 | K104: =+J104*$K$18 -> -0.077396248 | L104: =+J104*$L$18 -> -0.011056607 | M104: =+J104+K104+L104 -> -2.2997742
A105: 87 | B105: =NOW() -> 46079.336 | C105: =+$D$11-D105 -> 1917.9829 | D105: =+H104*$B$9/360*E105 -> -43.981766 | E105: 30 | F105: =+C105+D105 -> 1874.0012 | G105: =+F105+M105 -> 1869.3748 | H105: =+H104-C105 -> -5687.8486 | J105: =+H104*$J$18 -> -4.4484415 | K105: =+J105*$K$18 -> -0.15569545 | L105: =+J105*$L$18 -> -0.022242207 | M105: =+J105+K105+L105 -> -4.6263791
A106: 88 | B106: =+B105+E106 -> 46109.336 | C106: =+$D$11-D106 -> 1940.3594 | D106: =+H105*$B$9/360*E106 -> -66.358234 | E106: 30 | F106: =+C106+D106 -> 1874.0012 | G106: =+F106+M106 -> 1867.021 | H106: =+H105-C106 -> -7628.208 | J106: =+H105*$J$18 -> -6.7116613 | K106: =+J106*$K$18 -> -0.23490815 | L106: =+J106*$L$18 -> -0.033558307 | M106: =+J106+K106+L106 -> -6.9801278
A107: 89 | B107: =+B106+E107 -> 46139.336 | C107: =+$D$11-D107 -> 1962.9969 | D107: =+H106*$B$9/360*E107 -> -88.99576 | E107: 30 | F107: =+C107+D107 -> 1874.0012 | G107: =+F107+M107 -> 1864.6398 | H107: =+H106-C107 -> -9591.2049 | J107: =+H106*$J$18 -> -9.0012854 | K107: =+J107*$K$18 -> -0.31504499 | L107: =+J107*$L$18 -> -0.045006427 | M107: =+J107+K107+L107 -> -9.3613368
...

Sheet  Seguro de Desgravamen Titular
A6: Cálculo del Seguro de Desgravamen
A8: CAPITAL | B8: 10000
A9: INTERES | B9: 0.14
A10: PLAZO | B10: 84
A11: PAGO POR AÑO | B11: 12 | C11: CUOTA FIJA | D11: =+B8/((1-(1+B13)^-B10)/B13) -> 187.40012
A12: FRECUENCIA | B12: 30
A13: INTERES MENSUAL | B13: =+B9/B11 -> 0.011666667 | C13: VALOR TOTAL SEGURO | D13: =SUMIF(M19:M198,">0",M19:M198) -> 388.98586
A14: INTERES DIARIO | B14: =+B9/360 -> 0.00038888889
A15: TASA NETA SEGURO | B15: 0.0076
A17: CUOTA | B17: FECHA | C17: CAPITAL | D17: INTERES | E17: DIAS | F17: CUOTA FIJA | G17: CUOTA+ SEGURO | H17: SALDO | J17: Seguro | K17: Aporte Seps | L17: Seg. Campesivo | M17: Total seguro
B18: =NOW() -> 46079.336 | H18: =+B8 -> 10000 | J18: 0.00076 | K18: 0.035 | L18: 0.005 | M18: =+J18+K18+L18 -> 0.04076
A19: 1 | B19: =+B18+E19 -> 46109.336 | C19: =+$D$11-D19 -> 70.733449 | D19: =+H18*$B$9/360*E19 -> 116.66667 | E19: 30 | F19: =+C19+D19 -> 187.40012 | G19: =+F19+M19 -> 195.30412 | H19: =+H18-C19 -> 9929.2666 | J19: =+H18*$J$18 -> 7.6 | K19: =+J19*$K$18 -> 0.266 | L19: =+J19*$L$18 -> 0.038 | M19: =+J19+K19+L19 -> 7.904
A20: 2 | B20: =+B19+E20 -> 46139.336 | C20: =+$D$11-D20 -> 71.558673 | D20: =+H19*$B$9/360*E20 -> 115.84144 | E20: 30 | F20: =+C20+D20 -> 187.40012 | G20: =+F20+M20 -> 195.24821 | H20: =+H19-C20 -> 9857.7079 | J20: =+H19*$J$18 -> 7.5462426 | K20: =+J20*$K$18 -> 0.26411849 | L20: =+J20*$L$18 -> 0.037731213 | M20: =+J20+K20+L20 -> 7.8480923
A21: 3 | B21: =+B20+E21 -> 46169.336 | C21: =+$D$11-D21 -> 72.393524 | D21: =+H20*$B$9/360*E21 -> 115.00659 | E21: 30 | F21: =+C21+D21 -> 187.40012 | G21: =+F21+M21 -> 195.19165 | H21: =+H20-C21 -> 9785.3144 | J21: =+H20*$J$18 -> 7.491858 | K21: =+J21*$K$18 -> 0.26221503 | L21: =+J21*$L$18 -> 0.03745929 | M21: =+J21+K21+L21 -> 7.7915323
A22: 4 | B22: =NOW() -> 46079.336 | C22: =+$D$11-D22 -> 73.238115 | D22: =+H21*$B$9/360*E22 -> 114.162 | E22: 30 | F22: =+C22+D22 -> 187.40012 | G22: =+F22+M22 -> 195.13443 | H22: =+H21-C22 -> 9712.0762 | J22: =+H21*$J$18 -> 7.4368389 | K22: =+J22*$K$18 -> 0.26028936 | L22: =+J22*$L$18 -> 0.037184195 | M22: =+J22+K22+L22 -> 7.7343125
A23: 5 | B23: =+B22+E23 -> 46109.336 | C23: =+$D$11-D23 -> 74.09256 | D23: =+H22*$B$9/360*E23 -> 113.30756 | E23: 30 | F23: =+C23+D23 -> 187.40012 | G23: =+F23+M23 -> 195.07654 | H23: =+H22-C23 -> 9637.9837 | J23: =+H22*$J$18 -> 7.3811779 | K23: =+J23*$K$18 -> 0.25834123 | L23: =+J23*$L$18 -> 0.03690589 | M23: =+J23+K23+L23 -> 7.6764251
A24: 6 | B24: =+B23+E24 -> 46139.336 | C24: =+$D$11-D24 -> 74.956973 | D24: =+H23*$B$9/360*E24 -> 112.44314 | E24: 30 | F24: =+C24+D24 -> 187.40012 | G24: =+F24+M24 -> 195.01798 | H24: =+H23-C24 -> 9563.0267 | J24: =+H23*$J$18 -> 7.3248676 | K24: =+J24*$K$18 -> 0.25637037 | L24: =+J24*$L$18 -> 0.036624338 | M24: =+J24+K24+L24 -> 7.6178623
A25: 7 | B25: =+B24+E25 -> 46169.336 | C25: =+$D$11-D25 -> 75.831471 | D25: =+H24*$B$9/360*E25 -> 111.56864 | E25: 30 | F25: =+C25+D25 -> 187.40012 | G25: =+F25+M25 -> 194.95873 | H25: =+H24-C25 -> 9487.1952 | J25: =+H24*$J$18 -> 7.2679003 | K25: =+J25*$K$18 -> 0.25437651 | L25: =+J25*$L$18 -> 0.036339501 | M25: =+J25+K25+L25 -> 7.5586163
A26: 8 | B26: =NOW() -> 46079.336 | C26: =+$D$11-D26 -> 76.716172 | D26: =+H25*$B$9/360*E26 -> 110.68394 | E26: 30 | F26: =+C26+D26 -> 187.40012 | G26: =+F26+M26 -> 194.8988 | H26: =+H25-C26 -> 9410.4791 | J26: =+H25*$J$18 -> 7.2102684 | K26: =+J26*$K$18 -> 0.25235939 | L26: =+J26*$L$18 -> 0.036051342 | M26: =+J26+K26+L26 -> 7.4986791
A27: 9 | B27: =+B26+E27 -> 46109.336 | C27: =+$D$11-D27 -> 77.611194 | D27: =+H26*$B$9/360*E27 -> 109.78892 | E27: 30 | F27: =+C27+D27 -> 187.40012 | G27: =+F27+M27 -> 194.83816 | H27: =+H26-C27 -> 9332.8679 | J27: =+H26*$J$18 -> 7.1519641 | K27: =+J27*$K$18 -> 0.25031874 | L27: =+J27*$L$18 -> 0.03575982 | M27: =+J27+K27+L27 -> 7.4380427
A28: 10 | B28: =+B27+E28 -> 46139.336 | C28: =+$D$11-D28 -> 78.516658 | D28: =+H27*$B$9/360*E28 -> 108.88346 | E28: 30 | F28: =+C28+D28 -> 187.40012 | G28: =+F28+M28 -> 194.77681 | H28: =+H27-C28 -> 9254.3512 | J28: =+H27*$J$18 -> 7.0929796 | K28: =+J28*$K$18 -> 0.24825429 | L28: =+J28*$L$18 -> 0.035464898 | M28: =+J28+K28+L28 -> 7.3766988
A29: 11 | B29: =+B28+E29 -> 46169.336 | C29: =+$D$11-D29 -> 79.432685 | D29: =+H28*$B$9/360*E29 -> 107.96743 | E29: 30 | F29: =+C29+D29 -> 187.40012 | G29: =+F29+M29 -> 194.71476 | H29: =+H28-C29 -> 9174.9185 | J29: =+H28*$J$18 -> 7.0333069 | K29: =+J29*$K$18 -> 0.24616574 | L29: =+J29*$L$18 -> 0.035166535 | M29: =+J29+K29+L29 -> 7.3146392
A30: 12 | B30: =NOW() -> 46079.336 | C30: =+$D$11-D30 -> 80.3594 | D30: =+H29*$B$9/360*E30 -> 107.04072 | E30: 30 | F30: =+C30+D30 -> 187.40012 | G30: =+F30+M30 -> 194.65197 | H30: =+H29-C30 -> 9094.5591 | J30: =+H29*$J$18 -> 6.9729381 | K30: =+J30*$K$18 -> 0.24405283 | L30: =+J30*$L$18 -> 0.03486469 | M30: =+J30+K30+L30 -> 7.2518556
A31: 13 | B31: =+B30+E31 -> 46109.336 | C31: =+$D$11-D31 -> 81.296926 | D31: =+H30*$B$9/360*E31 -> 106.10319 | E31: 30 | F31: =+C31+D31 -> 187.40012 | G31: =+F31+M31 -> 194.58846 | H31: =+H30-C31 -> 9013.2622 | J31: =+H30*$J$18 -> 6.9118649 | K31: =+J31*$K$18 -> 0.24191527 | L31: =+J31*$L$18 -> 0.034559325 | M31: =+J31+K31+L31 -> 7.1883395
A32: 14 | B32: =+B31+E32 -> 46139.336 | C32: =+$D$11-D32 -> 82.24539 | D32: =+H31*$B$9/360*E32 -> 105.15473 | E32: 30 | F32: =+C32+D32 -> 187.40012 | G32: =+F32+M32 -> 194.5242 | H32: =+H31-C32 -> 8931.0168 | J32: =+H31*$J$18 -> 6.8500793 | K32: =+J32*$K$18 -> 0.23975277 | L32: =+J32*$L$18 -> 0.034250396 | M32: =+J32+K32+L32 -> 7.1240824
A33: 15 | B33: =+B32+E33 -> 46169.336 | C33: =+$D$11-D33 -> 83.20492 | D33: =+H32*$B$9/360*E33 -> 104.1952 | E33: 30 | F33: =+C33+D33 -> 187.40012 | G33: =+F33+M33 -> 194.45919 | H33: =+H32-C33 -> 8847.8119 | J33: =+H32*$J$18 -> 6.7875728 | K33: =+J33*$K$18 -> 0.23756505 | L33: =+J33*$L$18 -> 0.033937864 | M33: =+J33+K33+L33 -> 7.0590757
A34: 16 | B34: =NOW() -> 46079.336 | C34: =+$D$11-D34 -> 84.175644 | D34: =+H33*$B$9/360*E34 -> 103.22447 | E34: 30 | F34: =+C34+D34 -> 187.40012 | G34: =+F34+M34 -> 194.39343 | H34: =+H33-C34 -> 8763.6362 | J34: =+H33*$J$18 -> 6.724337 | K34: =+J34*$K$18 -> 0.2353518 | L34: =+J34*$L$18 -> 0.033621685 | M34: =+J34+K34+L34 -> 6.9933105
A35: 17 | B35: =+B34+E35 -> 46109.336 | C35: =+$D$11-D35 -> 85.157693 | D35: =+H34*$B$9/360*E35 -> 102.24242 | E35: 30 | F35: =+C35+D35 -> 187.40012 | G35: =+F35+M35 -> 194.32689 | H35: =+H34-C35 -> 8678.4786 | J35: =+H34*$J$18 -> 6.6603635 | K35: =+J35*$K$18 -> 0.23311272 | L35: =+J35*$L$18 -> 0.033301818 | M35: =+J35+K35+L35 -> 6.9267781
A36: 18 | B36: =+B35+E36 -> 46139.336 | C36: =+$D$11-D36 -> 86.1512 | D36: =+H35*$B$9/360*E36 -> 101.24892 | E36: 30 | F36: =+C36+D36 -> 187.40012 | G36: =+F36+M36 -> 194.25959 | H36: =+H35-C36 -> 8592.3274 | J36: =+H35*$J$18 -> 6.5956437 | K36: =+J36*$K$18 -> 0.23084753 | L36: =+J36*$L$18 -> 0.032978218 | M36: =+J36+K36+L36 -> 6.8594694
A37: 19 | B37: =+B36+E37 -> 46169.336 | C37: =+$D$11-D37 -> 87.156297 | D37: =+H36*$B$9/360*E37 -> 100.24382 | E37: 30 | F37: =+C37+D37 -> 187.40012 | G37: =+F37+M37 -> 194.19149 | H37: =+H36-C37 -> 8505.1711 | J37: =+H36*$J$18 -> 6.5301688 | K37: =+J37*$K$18 -> 0.22855591 | L37: =+J37*$L$18 -> 0.032650844 | M37: =+J37+K37+L37 -> 6.7913755
A38: 20 | B38: =NOW() -> 46079.336 | C38: =+$D$11-D38 -> 88.17312 | D38: =+H37*$B$9/360*E38 -> 99.226996 | E38: 30 | F38: =+C38+D38 -> 187.40012 | G38: =+F38+M38 -> 194.1226 | H38: =+H37-C38 -> 8416.9979 | J38: =+H37*$J$18 -> 6.46393 | K38: =+J38*$K$18 -> 0.22623755 | L38: =+J38*$L$18 -> 0.03231965 | M38: =+J38+K38+L38 -> 6.7224872
A39: 21 | B39: =+B38+E39 -> 46109.336 | C39: =+$D$11-D39 -> 89.201807 | D39: =+H38*$B$9/360*E39 -> 98.198309 | E39: 30 | F39: =+C39+D39 -> 187.40012 | G39: =+F39+M39 -> 194.05291 | H39: =+H38-C39 -> 8327.7961 | J39: =+H38*$J$18 -> 6.3969184 | K39: =+J39*$K$18 -> 0.22389215 | L39: =+J39*$L$18 -> 0.031984592 | M39: =+J39+K39+L39 -> 6.6527952
A40: 22 | B40: =+B39+E40 -> 46139.336 | C40: =+$D$11-D40 -> 90.242495 | D40: =+H39*$B$9/360*E40 -> 97.157621 | E40: 30 | F40: =+C40+D40 -> 187.40012 | G40: =+F40+M40 -> 193.98241 | H40: =+H39-C40 -> 8237.5536 | J40: =+H39*$J$18 -> 6.3291251 | K40: =+J40*$K$18 -> 0.22151938 | L40: =+J40*$L$18 -> 0.031645625 | M40: =+J40+K40+L40 -> 6.5822901
A41: 23 | B41: =+B40+E41 -> 46169.336 | C41: =+$D$11-D41 -> 91.295324 | D41: =+H40*$B$9/360*E41 -> 96.104792 | E41: 30 | F41: =+C41+D41 -> 187.40012 | G41: =+F41+M41 -> 193.91108 | H41: =+H40-C41 -> 8146.2583 | J41: =+H40*$J$18 -> 6.2605408 | K41: =+J41*$K$18 -> 0.21911893 | L41: =+J41*$L$18 -> 0.031302704 | M41: =+J41+K41+L41 -> 6.5109624
A42: 24 | B42: =NOW() -> 46079.336 | C42: =+$D$11-D42 -> 92.360436 | D42: =+H41*$B$9/360*E42 -> 95.03968 | E42: 30 | F42: =+C42+D42 -> 187.40012 | G42: =+F42+M42 -> 193.83892 | H42: =+H41-C42 -> 8053.8979 | J42: =+H41*$J$18 -> 6.1911563 | K42: =+J42*$K$18 -> 0.21669047 | L42: =+J42*$L$18 -> 0.030955782 | M42: =+J42+K42+L42 -> 6.4388026
A43: 25 | B43: =NOW() -> 46079.336 | C43: =+$D$11-D43 -> 93.437974 | D43: =+H42*$B$9/360*E43 -> 93.962142 | E43: 30 | F43: =+C43+D43 -> 187.40012 | G43: =+F43+M43 -> 193.76592 | H43: =+H42-C43 -> 7960.4599 | J43: =+H42*$J$18 -> 6.1209624 | K43: =+J43*$K$18 -> 0.21423368 | L43: =+J43*$L$18 -> 0.030604812 | M43: =+J43+K43+L43 -> 6.3658009
A44: 26 | B44: =+B43+E44 -> 46109.336 | C44: =+$D$11-D44 -> 94.528084 | D44: =+H43*$B$9/360*E44 -> 92.872032 | E44: 30 | F44: =+C44+D44 -> 187.40012 | G44: =+F44+M44 -> 193.69206 | H44: =+H43-C44 -> 7865.9318 | J44: =+H43*$J$18 -> 6.0499495 | K44: =+J44*$K$18 -> 0.21174823 | L44: =+J44*$L$18 -> 0.030249748 | M44: =+J44+K44+L44 -> 6.2919475
A45: 27 | B45: =+B44+E45 -> 46139.336 | C45: =+$D$11-D45 -> 95.630912 | D45: =+H44*$B$9/360*E45 -> 91.769205 | E45: 30 | F45: =+C45+D45 -> 187.40012 | G45: =+F45+M45 -> 193.61735 | H45: =+H44-C45 -> 7770.3009 | J45: =+H44*$J$18 -> 5.9781082 | K45: =+J45*$K$18 -> 0.20923379 | L45: =+J45*$L$18 -> 0.029890541 | M45: =+J45+K45+L45 -> 6.2172325
A46: 28 | B46: =+B45+E46 -> 46169.336 | C46: =+$D$11-D46 -> 96.746606 | D46: =+H45*$B$9/360*E46 -> 90.653511 | E46: 30 | F46: =+C46+D46 -> 187.40012 | G46: =+F46+M46 -> 193.54176 | H46: =+H45-C46 -> 7673.5543 | J46: =+H45*$J$18 -> 5.9054287 | K46: =+J46*$K$18 -> 0.20669 | L46: =+J46*$L$18 -> 0.029527143 | M46: =+J46+K46+L46 -> 6.1416458
A47: 29 | B47: =NOW() -> 46079.336 | C47: =+$D$11-D47 -> 97.875316 | D47: =+H46*$B$9/360*E47 -> 89.5248 | E47: 30 | F47: =+C47+D47 -> 187.40012 | G47: =+F47+M47 -> 193.46529 | H47: =+H46-C47 -> 7575.679 | J47: =+H46*$J$18 -> 5.8319013 | K47: =+J47*$K$18 -> 0.20411654 | L47: =+J47*$L$18 -> 0.029159506 | M47: =+J47+K47+L47 -> 6.0651773
A48: 30 | B48: =+B47+E48 -> 46109.336 | C48: =+$D$11-D48 -> 99.017195 | D48: =+H47*$B$9/360*E48 -> 88.382921 | E48: 30 | F48: =+C48+D48 -> 187.40012 | G48: =+F48+M48 -> 193.38793 | H48: =+H47-C48 -> 7476.6618 | J48: =+H47*$J$18 -> 5.757516 | K48: =+J48*$K$18 -> 0.20151306 | L48: =+J48*$L$18 -> 0.02878758 | M48: =+J48+K48+L48 -> 5.9878167
A49: 31 | B49: =+B48+E49 -> 46139.336 | C49: =+$D$11-D49 -> 100.1724 | D49: =+H48*$B$9/360*E49 -> 87.227721 | E49: 30 | F49: =+C49+D49 -> 187.40012 | G49: =+F49+M49 -> 193.30967 | H49: =+H48-C49 -> 7376.4894 | J49: =+H48*$J$18 -> 5.682263 | K49: =+J49*$K$18 -> 0.1988792 | L49: =+J49*$L$18 -> 0.028411315 | M49: =+J49+K49+L49 -> 5.9095535
A50: 32 | B50: =+B49+E50 -> 46169.336 | C50: =+$D$11-D50 -> 101.34107 | D50: =+H49*$B$9/360*E50 -> 86.059043 | E50: 30 | F50: =+C50+D50 -> 187.40012 | G50: =+F50+M50 -> 193.23049 | H50: =+H49-C50 -> 7275.1483 | J50: =+H49*$J$18 -> 5.6061319 | K50: =+J50*$K$18 -> 0.19621462 | L50: =+J50*$L$18 -> 0.02803066 | M50: =+J50+K50+L50 -> 5.8303772
A51: 33 | B51: =NOW() -> 46079.336 | C51: =+$D$11-D51 -> 102.52339 | D51: =+H50*$B$9/360*E51 -> 84.87673 | E51: 30 | F51: =+C51+D51 -> 187.40012 | G51: =+F51+M51 -> 193.15039 | H51: =+H50-C51 -> 7172.6249 | J51: =+H50*$J$18 -> 5.5291127 | K51: =+J51*$K$18 -> 0.19351895 | L51: =+J51*$L$18 -> 0.027645564 | M51: =+J51+K51+L51 -> 5.7502772
A52: 34 | B52: =+B51+E52 -> 46109.336 | C52: =+$D$11-D52 -> 103.71949 | D52: =+H51*$B$9/360*E52 -> 83.680624 | E52: 30 | F52: =+C52+D52 -> 187.40012 | G52: =+F52+M52 -> 193.06936 | H52: =+H51-C52 -> 7068.9054 | J52: =+H51*$J$18 -> 5.451195 | K52: =+J52*$K$18 -> 0.19079182 | L52: =+J52*$L$18 -> 0.027255975 | M52: =+J52+K52+L52 -> 5.6692427
A53: 35 | B53: =+B52+E53 -> 46139.336 | C53: =+$D$11-D53 -> 104.92955 | D53: =+H52*$B$9/360*E53 -> 82.470564 | E53: 30 | F53: =+C53+D53 -> 187.40012 | G53: =+F53+M53 -> 192.98738 | H53: =+H52-C53 -> 6963.9759 | J53: =+H52*$J$18 -> 5.3723681 | K53: =+J53*$K$18 -> 0.18803288 | L53: =+J53*$L$18 -> 0.026861841 | M53: =+J53+K53+L53 -> 5.5872629
A54: 36 | B54: =+B53+E54 -> 46169.336 | C54: =+$D$11-D54 -> 106.15373 | D54: =+H53*$B$9/360*E54 -> 81.246385 | E54: 30 | F54: =+C54+D54 -> 187.40012 | G54: =+F54+M54 -> 192.90444 | H54: =+H53-C54 -> 6857.8222 | J54: =+H53*$J$18 -> 5.2926217 | K54: =+J54*$K$18 -> 0.18524176 | L54: =+J54*$L$18 -> 0.026463108 | M54: =+J54+K54+L54 -> 5.5043265
A55: 37 | B55: =NOW() -> 46079.336 | C55: =+$D$11-D55 -> 107.39219 | D55: =+H54*$B$9/360*E55 -> 80.007925 | E55: 30 | F55: =+C55+D55 -> 187.40012 | G55: =+F55+M55 -> 192.82054 | H55: =+H54-C55 -> 6750.43 | J55: =+H54*$J$18 -> 5.2119448 | K55: =+J55*$K$18 -> 0.18241807 | L55: =+J55*$L$18 -> 0.026059724 | M55: =+J55+K55+L55 -> 5.4204226
A56: 38 | B56: =+B55+E56 -> 46109.336 | C56: =+$D$11-D56 -> 108.6451 | D56: =+H55*$B$9/360*E56 -> 78.755016 | E56: 30 | F56: =+C56+D56 -> 187.40012 | G56: =+F56+M56 -> 192.73566 | H56: =+H55-C56 -> 6641.7849 | J56: =+H55*$J$18 -> 5.1303268 | K56: =+J56*$K$18 -> 0.17956144 | L56: =+J56*$L$18 -> 0.025651634 | M56: =+J56+K56+L56 -> 5.3355398
A57: 39 | B57: =+B56+E57 -> 46139.336 | C57: =+$D$11-D57 -> 109.91263 | D57: =+H56*$B$9/360*E57 -> 77.48749 | E57: 30 | F57: =+C57+D57 -> 187.40012 | G57: =+F57+M57 -> 192.64978 | H57: =+H56-C57 -> 6531.8722 | J57: =+H56*$J$18 -> 5.0477565 | K57: =+J57*$K$18 -> 0.17667148 | L57: =+J57*$L$18 -> 0.025238783 | M57: =+J57+K57+L57 -> 5.2496668
A58: 40 | B58: =+B57+E58 -> 46169.336 | C58: =+$D$11-D58 -> 111.19494 | D58: =+H57*$B$9/360*E58 -> 76.205176 | E58: 30 | F58: =+C58+D58 -> 187.40012 | G58: =+F58+M58 -> 192.56291 | H58: =+H57-C58 -> 6420.6773 | J58: =+H57*$J$18 -> 4.9642229 | K58: =+J58*$K$18 -> 0.1737478 | L58: =+J58*$L$18 -> 0.024821115 | M58: =+J58+K58+L58 -> 5.1627918
A59: 41 | B59: =NOW() -> 46079.336 | C59: =+$D$11-D59 -> 112.49221 | D59: =+H58*$B$9/360*E59 -> 74.907902 | E59: 30 | F59: =+C59+D59 -> 187.40012 | G59: =+F59+M59 -> 192.47502 | H59: =+H58-C59 -> 6308.1851 | J59: =+H58*$J$18 -> 4.8797148 | K59: =+J59*$K$18 -> 0.17079002 | L59: =+J59*$L$18 -> 0.024398574 | M59: =+J59+K59+L59 -> 5.0749033
A60: 42 | B60: =+B59+E60 -> 46109.336 | C60: =+$D$11-D60 -> 113.80462 | D60: =+H59*$B$9/360*E60 -> 73.595493 | E60: 30 | F60: =+C60+D60 -> 187.40012 | G60: =+F60+M60 -> 192.38611 | H60: =+H59-C60 -> 6194.3805 | J60: =+H59*$J$18 -> 4.7942207 | K60: =+J60*$K$18 -> 0.16779772 | L60: =+J60*$L$18 -> 0.023971103 | M60: =+J60+K60+L60 -> 4.9859895
A61: 43 | B61: =+B60+E61 -> 46139.336 | C61: =+$D$11-D61 -> 115.13234 | D61: =+H60*$B$9/360*E61 -> 72.267772 | E61: 30 | F61: =+C61+D61 -> 187.40012 | G61: =+F61+M61 -> 192.29615 | H61: =+H60-C61 -> 6079.2481 | J61: =+H60*$J$18 -> 4.7077292 | K61: =+J61*$K$18 -> 0.16477052 | L61: =+J61*$L$18 -> 0.023538646 | M61: =+J61+K61+L61 -> 4.8960383
A62: 44 | B62: =+B61+E62 -> 46169.336 | C62: =+$D$11-D62 -> 116.47555 | D62: =+H61*$B$9/360*E62 -> 70.924561 | E62: 30 | F62: =+C62+D62 -> 187.40012 | G62: =+F62+M62 -> 192.20515 | H62: =+H61-C62 -> 5962.7726 | J62: =+H61*$J$18 -> 4.6202286 | K62: =+J62*$K$18 -> 0.161708 | L62: =+J62*$L$18 -> 0.023101143 | M62: =+J62+K62+L62 -> 4.8050377
A63: 45 | B63: =NOW() -> 46079.336 | C63: =+$D$11-D63 -> 117.83444 | D63: =+H62*$B$9/360*E63 -> 69.56568 | E63: 30 | F63: =+C63+D63 -> 187.40012 | G63: =+F63+M63 -> 192.11309 | H63: =+H62-C63 -> 5844.9381 | J63: =+H62*$J$18 -> 4.5317072 | K63: =+J63*$K$18 -> 0.15860975 | L63: =+J63*$L$18 -> 0.022658536 | M63: =+J63+K63+L63 -> 4.7129754
A64: 46 | B64: =+B63+E64 -> 46109.336 | C64: =+$D$11-D64 -> 119.20917 | D64: =+H63*$B$9/360*E64 -> 68.190945 | E64: 30 | F64: =+C64+D64 -> 187.40012 | G64: =+F64+M64 -> 192.01996 | H64: =+H63-C64 -> 5725.729 | J64: =+H63*$J$18 -> 4.442153 | K64: =+J64*$K$18 -> 0.15547535 | L64: =+J64*$L$18 -> 0.022210765 | M64: =+J64+K64+L64 -> 4.6198391
A65: 47 | B65: =+B64+E65 -> 46139.336 | C65: =+$D$11-D65 -> 120.59994 | D65: =+H64*$B$9/360*E65 -> 66.800171 | E65: 30 | F65: =+C65+D65 -> 187.40012 | G65: =+F65+M65 -> 191.92573 | H65: =+H64-C65 -> 5605.129 | J65: =+H64*$J$18 -> 4.351554 | K65: =+J65*$K$18 -> 0.15230439 | L65: =+J65*$L$18 -> 0.02175777 | M65: =+J65+K65+L65 -> 4.5256162
A66: 48 | B66: =+B65+E66 -> 46169.336 | C66: =+$D$11-D66 -> 122.00694 | D66: =+H65*$B$9/360*E66 -> 65.393172 | E66: 30 | F66: =+C66+D66 -> 187.40012 | G66: =+F66+M66 -> 191.83041 | H66: =+H65-C66 -> 5483.1221 | J66: =+H65*$J$18 -> 4.2598981 | K66: =+J66*$K$18 -> 0.14909643 | L66: =+J66*$L$18 -> 0.02129949 | M66: =+J66+K66+L66 -> 4.430294
A67: 49 | B67: =NOW() -> 46079.336 | C67: =+$D$11-D67 -> 123.43036 | D67: =+H66*$B$9/360*E67 -> 63.969757 | E67: 30 | F67: =+C67+D67 -> 187.40012 | G67: =+F67+M67 -> 191.73398 | H67: =+H66-C67 -> 5359.6917 | J67: =+H66*$J$18 -> 4.1671728 | K67: =+J67*$K$18 -> 0.14585105 | L67: =+J67*$L$18 -> 0.020835864 | M67: =+J67+K67+L67 -> 4.3338597
A68: 50 | B68: =NOW() -> 46079.336 | C68: =+$D$11-D68 -> 124.87038 | D68: =+H67*$B$9/360*E68 -> 62.529737 | E68: 30 | F68: =+C68+D68 -> 187.40012 | G68: =+F68+M68 -> 191.63642 | H68: =+H67-C68 -> 5234.8213 | J68: =+H67*$J$18 -> 4.0733657 | K68: =+J68*$K$18 -> 0.1425678 | L68: =+J68*$L$18 -> 0.020366829 | M68: =+J68+K68+L68 -> 4.2363003
A69: 51 | B69: =+B68+E69 -> 46109.336 | C69: =+$D$11-D69 -> 126.3272 | D69: =+H68*$B$9/360*E69 -> 61.072916 | E69: 30 | F69: =+C69+D69 -> 187.40012 | G69: =+F69+M69 -> 191.53772 | H69: =+H68-C69 -> 5108.4941 | J69: =+H68*$J$18 -> 3.9784642 | K69: =+J69*$K$18 -> 0.13924625 | L69: =+J69*$L$18 -> 0.019892321 | M69: =+J69+K69+L69 -> 4.1376028
A70: 52 | B70: =+B69+E70 -> 46139.336 | C70: =+$D$11-D70 -> 127.80102 | D70: =+H69*$B$9/360*E70 -> 59.599098 | E70: 30 | F70: =+C70+D70 -> 187.40012 | G70: =+F70+M70 -> 191.43787 | H70: =+H69-C70 -> 4980.6931 | J70: =+H69*$J$18 -> 3.8824555 | K70: =+J70*$K$18 -> 0.13588594 | L70: =+J70*$L$18 -> 0.019412278 | M70: =+J70+K70+L70 -> 4.0377538
A71: 53 | B71: =+B70+E71 -> 46169.336 | C71: =+$D$11-D71 -> 129.29203 | D71: =+H70*$B$9/360*E71 -> 58.108086 | E71: 30 | F71: =+C71+D71 -> 187.40012 | G71: =+F71+M71 -> 191.33686 | H71: =+H70-C71 -> 4851.4011 | J71: =+H70*$J$18 -> 3.7853268 | K71: =+J71*$K$18 -> 0.13248644 | L71: =+J71*$L$18 -> 0.018926634 | M71: =+J71+K71+L71 -> 3.9367398
A72: 54 | B72: =NOW() -> 46079.336 | C72: =+$D$11-D72 -> 130.80044 | D72: =+H71*$B$9/360*E72 -> 56.599679 | E72: 30 | F72: =+C72+D72 -> 187.40012 | G72: =+F72+M72 -> 191.23466 | H72: =+H71-C72 -> 4720.6006 | J72: =+H71*$J$18 -> 3.6870648 | K72: =+J72*$K$18 -> 0.12904727 | L72: =+J72*$L$18 -> 0.018435324 | M72: =+J72+K72+L72 -> 3.8345474
A73: 55 | B73: =+B72+E73 -> 46109.336 | C73: =+$D$11-D73 -> 132.32644 | D73: =+H72*$B$9/360*E73 -> 55.073674 | E73: 30 | F73: =+C73+D73 -> 187.40012 | G73: =+F73+M73 -> 191.13128 | H73: =+H72-C73 -> 4588.2742 | J73: =+H72*$J$18 -> 3.5876565 | K73: =+J73*$K$18 -> 0.12556798 | L73: =+J73*$L$18 -> 0.017938282 | M73: =+J73+K73+L73 -> 3.7311628
A74: 56 | B74: =+B73+E74 -> 46139.336 | C74: =+$D$11-D74 -> 133.87025 | D74: =+H73*$B$9/360*E74 -> 53.529866 | E74: 30 | F74: =+C74+D74 -> 187.40012 | G74: =+F74+M74 -> 191.02669 | H74: =+H73-C74 -> 4454.404 | J74: =+H73*$J$18 -> 3.4870884 | K74: =+J74*$K$18 -> 0.12204809 | L74: =+J74*$L$18 -> 0.017435442 | M74: =+J74+K74+L74 -> 3.6265719
A75: 57 | B75: =+B74+E75 -> 46169.336 | C75: =+$D$11-D75 -> 135.43207 | D75: =+H74*$B$9/360*E75 -> 51.968046 | E75: 30 | F75: =+C75+D75 -> 187.40012 | G75: =+F75+M75 -> 190.92088 | H75: =+H74-C75 -> 4318.9719 | J75: =+H74*$J$18 -> 3.385347 | K75: =+J75*$K$18 -> 0.11848715 | L75: =+J75*$L$18 -> 0.016926735 | M75: =+J75+K75+L75 -> 3.5207609
A76: 58 | B76: =NOW() -> 46079.336 | C76: =+$D$11-D76 -> 137.01211 | D76: =+H75*$B$9/360*E76 -> 50.388005 | E76: 30 | F76: =+C76+D76 -> 187.40012 | G76: =+F76+M76 -> 190.81383 | H76: =+H75-C76 -> 4181.9598 | J76: =+H75*$J$18 -> 3.2824186 | K76: =+J76*$K$18 -> 0.11488465 | L76: =+J76*$L$18 -> 0.016412093 | M76: =+J76+K76+L76 -> 3.4137154
A77: 59 | B77: =+B76+E77 -> 46109.336 | C77: =+$D$11-D77 -> 138.61059 | D77: =+H76*$B$9/360*E77 -> 48.789531 | E77: 30 | F77: =+C77+D77 -> 187.40012 | G77: =+F77+M77 -> 190.70554 | H77: =+H76-C77 -> 4043.3492 | J77: =+H76*$J$18 -> 3.1782894 | K77: =+J77*$K$18 -> 0.11124013 | L77: =+J77*$L$18 -> 0.015891447 | M77: =+J77+K77+L77 -> 3.305421
A78: 60 | B78: =+B77+E78 -> 46139.336 | C78: =+$D$11-D78 -> 140.22771 | D78: =+H77*$B$9/360*E78 -> 47.172407 | E78: 30 | F78: =+C78+D78 -> 187.40012 | G78: =+F78+M78 -> 190.59598 | H78: =+H77-C78 -> 3903.1215 | J78: =+H77*$J$18 -> 3.0729454 | K78: =+J78*$K$18 -> 0.10755309 | L78: =+J78*$L$18 -> 0.015364727 | M78: =+J78+K78+L78 -> 3.1958632
A79: 61 | B79: =+B78+E79 -> 46169.336 | C79: =+$D$11-D79 -> 141.8637 | D79: =+H78*$B$9/360*E79 -> 45.536417 | E79: 30 | F79: =+C79+D79 -> 187.40012 | G79: =+F79+M79 -> 190.48514 | H79: =+H78-C79 -> 3761.2578 | J79: =+H78*$J$18 -> 2.9663723 | K79: =+J79*$K$18 -> 0.10382303 | L79: =+J79*$L$18 -> 0.014831862 | M79: =+J79+K79+L79 -> 3.0850272
A80: 62 | B80: =NOW() -> 46079.336 | C80: =+$D$11-D80 -> 143.51878 | D80: =+H79*$B$9/360*E80 -> 43.881341 | E80: 30 | F80: =+C80+D80 -> 187.40012 | G80: =+F80+M80 -> 190.37301 | H80: =+H79-C80 -> 3617.739 | J80: =+H79*$J$18 -> 2.8585559 | K80: =+J80*$K$18 -> 0.10004946 | L80: =+J80*$L$18 -> 0.01429278 | M80: =+J80+K80+L80 -> 2.9728982
A81: 63 | B81: =+B80+E81 -> 46109.336 | C81: =+$D$11-D81 -> 145.19316 | D81: =+H80*$B$9/360*E81 -> 42.206955 | E81: 30 | F81: =+C81+D81 -> 187.40012 | G81: =+F81+M81 -> 190.25958 | H81: =+H80-C81 -> 3472.5458 | J81: =+H80*$J$18 -> 2.7494816 | K81: =+J81*$K$18 -> 0.096231858 | L81: =+J81*$L$18 -> 0.013747408 | M81: =+J81+K81+L81 -> 2.8594609
A82: 64 | B82: =+B81+E82 -> 46139.336 | C82: =+$D$11-D82 -> 146.88708 | D82: =+H81*$B$9/360*E82 -> 40.513035 | E82: 30 | F82: =+C82+D82 -> 187.40012 | G82: =+F82+M82 -> 190.14482 | H82: =+H81-C82 -> 3325.6588 | J82: =+H81*$J$18 -> 2.6391348 | K82: =+J82*$K$18 -> 0.09236972 | L82: =+J82*$L$18 -> 0.013195674 | M82: =+J82+K82+L82 -> 2.7447002
A83: 65 | B83: =+B82+E83 -> 46169.336 | C83: =+$D$11-D83 -> 148.60076 | D83: =+H82*$B$9/360*E83 -> 38.799352 | E83: 30 | F83: =+C83+D83 -> 187.40012 | G83: =+F83+M83 -> 190.02872 | H83: =+H82-C83 -> 3177.058 | J83: =+H82*$J$18 -> 2.5275007 | K83: =+J83*$K$18 -> 0.088462523 | L83: =+J83*$L$18 -> 0.012637503 | M83: =+J83+K83+L83 -> 2.6286007
A84: 66 | B84: =NOW() -> 46079.336 | C84: =+$D$11-D84 -> 150.33444 | D84: =+H83*$B$9/360*E84 -> 37.065677 | E84: 30 | F84: =+C84+D84 -> 187.40012 | G84: =+F84+M84 -> 189.91126 | H84: =+H83-C84 -> 3026.7236 | J84: =+H83*$J$18 -> 2.4145641 | K84: =+J84*$K$18 -> 0.084509743 | L84: =+J84*$L$18 -> 0.01207282 | M84: =+J84+K84+L84 -> 2.5111466
A85: 67 | B85: =+B84+E85 -> 46109.336 | C85: =+$D$11-D85 -> 152.08834 | D85: =+H84*$B$9/360*E85 -> 35.311775 | E85: 30 | F85: =+C85+D85 -> 187.40012 | G85: =+F85+M85 -> 189.79244 | H85: =+H84-C85 -> 2874.6352 | J85: =+H84*$J$18 -> 2.3003099 | K85: =+J85*$K$18 -> 0.080510847 | L85: =+J85*$L$18 -> 0.01150155 | M85: =+J85+K85+L85 -> 2.3923223
A86: 68 | B86: =+B85+E86 -> 46139.336 | C86: =+$D$11-D86 -> 153.86271 | D86: =+H85*$B$9/360*E86 -> 33.537411 | E86: 30 | F86: =+C86+D86 -> 187.40012 | G86: =+F86+M86 -> 189.67223 | H86: =+H85-C86 -> 2720.7725 | J86: =+H85*$J$18 -> 2.1847228 | K86: =+J86*$K$18 -> 0.076465297 | L86: =+J86*$L$18 -> 0.010923614 | M86: =+J86+K86+L86 -> 2.2721117
A87: 69 | B87: =+B86+E87 -> 46169.336 | C87: =+$D$11-D87 -> 155.65777 | D87: =+H86*$B$9/360*E87 -> 31.742346 | E87: 30 | F87: =+C87+D87 -> 187.40012 | G87: =+F87+M87 -> 189.55061 | H87: =+H86-C87 -> 2565.1147 | J87: =+H86*$J$18 -> 2.0677871 | K87: =+J87*$K$18 -> 0.072372549 | L87: =+J87*$L$18 -> 0.010338936 | M87: =+J87+K87+L87 -> 2.1504986
A88: 70 | B88: =NOW() -> 46079.336 | C88: =+$D$11-D88 -> 157.47378 | D88: =+H87*$B$9/360*E88 -> 29.926339 | E88: 30 | F88: =+C88+D88 -> 187.40012 | G88: =+F88+M88 -> 189.42758 | H88: =+H87-C88 -> 2407.641 | J88: =+H87*$J$18 -> 1.9494872 | K88: =+J88*$K$18 -> 0.068232052 | L88: =+J88*$L$18 -> 0.009747436 | M88: =+J88+K88+L88 -> 2.0274667
A89: 71 | B89: =+B88+E89 -> 46109.336 | C89: =+$D$11-D89 -> 159.31097 | D89: =+H88*$B$9/360*E89 -> 28.089145 | E89: 30 | F89: =+C89+D89 -> 187.40012 | G89: =+F89+M89 -> 189.30312 | H89: =+H88-C89 -> 2248.33 | J89: =+H88*$J$18 -> 1.8298071 | K89: =+J89*$K$18 -> 0.06404325 | L89: =+J89*$L$18 -> 0.0091490357 | M89: =+J89+K89+L89 -> 1.9029994
A90: 72 | B90: =+B89+E90 -> 46139.336 | C90: =+$D$11-D90 -> 161.1696 | D90: =+H89*$B$9/360*E90 -> 26.230517 | E90: 30 | F90: =+C90+D90 -> 187.40012 | G90: =+F90+M90 -> 189.1772 | H90: =+H89-C90 -> 2087.1604 | J90: =+H89*$J$18 -> 1.7087308 | K90: =+J90*$K$18 -> 0.059805578 | L90: =+J90*$L$18 -> 0.008543654 | M90: =+J90+K90+L90 -> 1.77708
A91: 73 | B91: =+B90+E91 -> 46169.336 | C91: =+$D$11-D91 -> 163.04991 | D91: =+H90*$B$9/360*E91 -> 24.350205 | E91: 30 | F91: =+C91+D91 -> 187.40012 | G91: =+F91+M91 -> 189.04981 | H91: =+H90-C91 -> 1924.1105 | J91: =+H90*$J$18 -> 1.5862419 | K91: =+J91*$K$18 -> 0.055518467 | L91: =+J91*$L$18 -> 0.0079312095 | M91: =+J91+K91+L91 -> 1.6496916
A92: 74 | B92: =NOW() -> 46079.336 | C92: =+$D$11-D92 -> 164.95216 | D92: =+H91*$B$9/360*E92 -> 22.447956 | E92: 30 | F92: =+C92+D92 -> 187.40012 | G92: =+F92+M92 -> 188.92093 | H92: =+H91-C92 -> 1759.1583 | J92: =+H91*$J$18 -> 1.462324 | K92: =+J92*$K$18 -> 0.051181339 | L92: =+J92*$L$18 -> 0.0073116198 | M92: =+J92+K92+L92 -> 1.5208169
A93: 75 | B93: =NOW() -> 46079.336 | C93: =+$D$11-D93 -> 166.8766 | D93: =+H92*$B$9/360*E93 -> 20.523514 | E93: 30 | F93: =+C93+D93 -> 187.40012 | G93: =+F93+M93 -> 188.79055 | H93: =+H92-C93 -> 1592.2817 | J93: =+H92*$J$18 -> 1.3369603 | K93: =+J93*$K$18 -> 0.046793611 | L93: =+J93*$L$18 -> 0.0066848016 | M93: =+J93+K93+L93 -> 1.3904387
A94: 76 | B94: =+B93+E94 -> 46109.336 | C94: =+$D$11-D94 -> 168.8235 | D94: =+H93*$B$9/360*E94 -> 18.57662 | E94: 30 | F94: =+C94+D94 -> 187.40012 | G94: =+F94+M94 -> 188.65866 | H94: =+H93-C94 -> 1423.4582 | J94: =+H93*$J$18 -> 1.2101341 | K94: =+J94*$K$18 -> 0.042354694 | L94: =+J94*$L$18 -> 0.0060506705 | M94: =+J94+K94+L94 -> 1.2585395
A95: 77 | B95: =+B94+E95 -> 46139.336 | C95: =+$D$11-D95 -> 170.7931 | D95: =+H94*$B$9/360*E95 -> 16.607013 | E95: 30 | F95: =+C95+D95 -> 187.40012 | G95: =+F95+M95 -> 188.52522 | H95: =+H94-C95 -> 1252.6651 | J95: =+H94*$J$18 -> 1.0818283 | K95: =+J95*$K$18 -> 0.037863989 | L95: =+J95*$L$18 -> 0.0054091413 | M95: =+J95+K95+L95 -> 1.1251014
A96: 78 | B96: =+B95+E96 -> 46169.336 | C96: =+$D$11-D96 -> 172.78569 | D96: =+H95*$B$9/360*E96 -> 14.614426 | E96: 30 | F96: =+C96+D96 -> 187.40012 | G96: =+F96+M96 -> 188.39022 | H96: =+H95-C96 -> 1079.8794 | J96: =+H95*$J$18 -> 0.95202549 | K96: =+J96*$K$18 -> 0.033320892 | L96: =+J96*$L$18 -> 0.0047601275 | M96: =+J96+K96+L96 -> 0.99010651
A97: 79 | B97: =NOW() -> 46079.336 | C97: =+$D$11-D97 -> 174.80152 | D97: =+H96*$B$9/360*E97 -> 12.598593 | E97: 30 | F97: =+C97+D97 -> 187.40012 | G97: =+F97+M97 -> 188.25365 | H97: =+H96-C97 -> 905.07791 | J97: =+H96*$J$18 -> 0.82070837 | K97: =+J97*$K$18 -> 0.028724793 | L97: =+J97*$L$18 -> 0.0041035418 | M97: =+J97+K97+L97 -> 0.8535367
A98: 80 | B98: =+B97+E98 -> 46109.336 | C98: =+$D$11-D98 -> 176.84087 | D98: =+H97*$B$9/360*E98 -> 10.559242 | E98: 30 | F98: =+C98+D98 -> 187.40012 | G98: =+F98+M98 -> 188.11549 | H98: =+H97-C98 -> 728.23704 | J98: =+H97*$J$18 -> 0.68785921 | K98: =+J98*$K$18 -> 0.024075072 | L98: =+J98*$L$18 -> 0.0034392961 | M98: =+J98+K98+L98 -> 0.71537358
A99: 81 | B99: =+B98+E99 -> 46139.336 | C99: =+$D$11-D99 -> 178.90402 | D99: =+H98*$B$9/360*E99 -> 8.4960988 | E99: 30 | F99: =+C99+D99 -> 187.40012 | G99: =+F99+M99 -> 187.97571 | H99: =+H98-C99 -> 549.33302 | J99: =+H98*$J$18 -> 0.55346015 | K99: =+J99*$K$18 -> 0.019371105 | L99: =+J99*$L$18 -> 0.0027673007 | M99: =+J99+K99+L99 -> 0.57559855
A100: 82 | B100: =+B99+E100 -> 46169.336 | C100: =+$D$11-D100 -> 180.99123 | D100: =+H99*$B$9/360*E100 -> 6.4088852 | E100: 30 | F100: =+C100+D100 -> 187.40012 | G100: =+F100+M100 -> 187.83431 | H100: =+H99-C100 -> 368.34179 | J100: =+H99*$J$18 -> 0.4174931 | K100: =+J100*$K$18 -> 0.014612258 | L100: =+J100*$L$18 -> 0.0020874655 | M100: =+J100+K100+L100 -> 0.43419282
A101: 83 | B101: =NOW() -> 46079.336 | C101: =+$D$11-D101 -> 183.1028 | D101: =+H100*$B$9/360*E101 -> 4.2973209 | E101: 30 | F101: =+C101+D101 -> 187.40012 | G101: =+F101+M101 -> 187.69125 | H101: =+H100-C101 -> 185.23899 | J101: =+H100*$J$18 -> 0.27993976 | K101: =+J101*$K$18 -> 0.0097978916 | L101: =+J101*$L$18 -> 0.0013996988 | M101: =+J101+K101+L101 -> 0.29113735
A102: 84 | B102: =+B101+E102 -> 46109.336 | C102: =+$D$11-D102 -> 185.23899 | D102: =+H101*$B$9/360*E102 -> 2.1611216 | E102: 30 | F102: =+C102+D102 -> 187.40012 | G102: =+F102+M102 -> 187.54653 | H102: =+H101-C102 -> 5.9117156e-11 | J102: =+H101*$J$18 -> 0.14078164 | K102: =+J102*$K$18 -> 0.0049273573 | L102: =+J102*$L$18 -> 0.00070390818 | M102: =+J102+K102+L102 -> 0.1464129
A103: 85 | B103: =+B102+E103 -> 46139.336 | C103: =+$D$11-D103 -> 187.40012 | D103: =+H102*$B$9/360*E103 -> 6.8970015e-13 | E103: 30 | F103: =+C103+D103 -> 187.40012 | G103: =+F103+M103 -> 187.40012 | H103: =+H102-C103 -> -187.40012 | J103: =+H102*$J$18 -> 4.4929038e-14 | K103: =+J103*$K$18 -> 1.5725163e-15 | L103: =+J103*$L$18 -> 2.2464519e-16 | M103: =+J103+K103+L103 -> 4.67262e-14
A104: 86 | B104: =+B103+E104 -> 46169.336 | C104: =+$D$11-D104 -> 189.58645 | D104: =+H103*$B$9/360*E104 -> -2.1863347 | E104: 30 | F104: =+C104+D104 -> 187.40012 | G104: =+F104+M104 -> 187.252 | H104: =+H103-C104 -> -376.98657 | J104: =+H103*$J$18 -> -0.14242409 | K104: =+J104*$K$18 -> -0.0049848431 | L104: =+J104*$L$18 -> -0.00071212044 | M104: =+J104+K104+L104 -> -0.14812105
A105: 87 | B105: =NOW() -> 46079.336 | C105: =+$D$11-D105 -> 191.79829 | D105: =+H104*$B$9/360*E105 -> -4.3981766 | E105: 30 | F105: =+C105+D105 -> 187.40012 | G105: =+F105+M105 -> 187.10215 | H105: =+H104-C105 -> -568.78486 | J105: =+H104*$J$18 -> -0.28650979 | K105: =+J105*$K$18 -> -0.010027843 | L105: =+J105*$L$18 -> -0.001432549 | M105: =+J105+K105+L105 -> -0.29797018
A106: 88 | B106: =+B105+E106 -> 46109.336 | C106: =+$D$11-D106 -> 194.03594 | D106: =+H105*$B$9/360*E106 -> -6.6358234 | E106: 30 | F106: =+C106+D106 -> 187.40012 | G106: =+F106+M106 -> 186.95055 | H106: =+H105-C106 -> -762.8208 | J106: =+H105*$J$18 -> -0.43227649 | K106: =+J106*$K$18 -> -0.015129677 | L106: =+J106*$L$18 -> -0.0021613825 | M106: =+J106+K106+L106 -> -0.44956755
A107: 89 | B107: =+B106+E107 -> 46139.336 | C107: =+$D$11-D107 -> 196.29969 | D107: =+H106*$B$9/360*E107 -> -8.899576 | E107: 30 | F107: =+C107+D107 -> 187.40012 | G107: =+F107+M107 -> 186.79718 | H107: =+H106-C107 -> -959.12049 | J107: =+H106*$J$18 -> -0.57974381 | K107: =+J107*$K$18 -> -0.020291033 | L107: =+J107*$L$18 -> -0.002898719 | M107: =+J107+K107+L107 -> -0.60293356
...

Sheet TIPO DE CARTERA
B28: TIPO DE CARTERA
B29: 1 | C29: PRODUCTIVO
B30: 1-01 | C30: PRODUCTIVO REFINANCIADO
B31: 1-02 | C31: PRODUCTIVO REESTRUCTURADO
B32: 2 | C32: MICROCREDITO
B33: 2-01 | C33: MICROCREDITO REFINANCIADO
B34: 2-02 | C34: MICROCREDITO REESTRUCTURADO
B35: 3 | C35: INMOBILIARIO
B36: 3-01 | C36: INMOBILIARIO REFINANCIADO
B37: 3-02 | C37: INMOBILIARIO REESTRUCTURADO
B38: 4 | C38: CONSUMO
B39: 4-01 | C39: CONSUMO REFINANCIADO
B40: 4-02 | C40: CONSUMO REESTRUCTURADO
... B43: 5-02 | C43: EDUCATIVO REESTRUCTURADO

Sheet SEGMENTOS DE CREDITO
B4: SEGMENTOS DE CRÉDITO
B5: Nº | C5: SEGMENTO / SUBSEGMENTO | D5: DESCRIPCIÓN
B6: 1-01 | C6: PRODUCTIVO CORPORATIVO | D6: Son operaciones de crédito productivo otorgadas a personas naturales o personas jurídicas que registren ventas anuales superiores a USD 7,000,000.00.
B7: 1-02 | C7: PRODUCTIVO EMPRESARIAL | D7: Son operaciones de crédito productivo otorgadas a personas naturales o personas jurídicas que registren ventas anuales superiores a USD 1,500,000.00 y hasta USD 7,000,000.00.
B8: 1-03 | C8: PRODUCTIVO PYMES | D8: Son operaciones de crédito productivo otorgadas a personas naturales o personas jurídicas que registren ventas anuales superiores a USD 300,000.00 y hasta USD 1,500,000.00.
B9: 2-01 | C9: MICROCRÉDITO MINORISTA | D9: Operaciones otorgadas a solicitantes de crédito que registren ventas anuales iguales o inferiores a USD 20,000.00.
B10: 2-02 | C10: MICROCRÉDITO ACUMULACIÓN SIMPLE | D10: Operaciones otorgadas a solicitantes de crédito que registren ventas anuales superiores a USD 20.000,00 y hasta USD 120.000,00.
B11: 2-03 | C11: MICROCRÉDITO ACUMULACIÓN AMPLIADA | D11: Operaciones otorgadas a solicitantes de crédito que registren ventas anuales superiores a USD 120.000,00 y hasta USD 300.000,00.
B12: 3-0 | C12: INMOBILIARIO | D12: Son aquellas operaciones otorgadas con garantía hipotecaria a personas naturales para la construcción, reparación, remodelación y mejora de inmuebles propios; para la adquisición de terrenos destinados a la construcción de vivienda propia; y, para la adquisición de vivienda terminada para uso del deudor y su familia no categorizada en el segmento de crédito Vivienda de Interés Social y Público.
B13: 4-0 | C13: CONSUMO | D13: Son aquellas operaciones otorgadas a personas naturales, destinado a la compra de bienes, servicios o gastos no relacionados con una actividad productiva, comercial y otras compras y gastos, se incluyen los créditos prendarios de joyas, así como para adquisición de vehículos livianos que no sean de uso para una actividad productiva y comercial.
B14: 5-0 | C14: EDUCATIVO | D14: Son aquellas operaciones otorgadas a personas naturales para su formación y capacitación profesional o técnica y a personas juridicas para el financiamiento de formación y capacitación profesional o técnica de su talento humano en ambos casos la formación y capacitación deberá ser debidamente acreditada por los órganos competentes.

Sheet CÓDIGO OFICINA
A2: CODIFICACIÓN DE LA OFICINA
A3: DE ACUERDO A LA CREACIÓN
A4: NRO. | B4: OFICINA
A5: 1 | B5: TULCAN
A6: 2 | B6: SAN GABRIEL
A7: 3 | B7: BOLIVAR
A8: 4 | B8: MIRA
A9: 5 | B9: IBARRA
A10: 6 | B10: QUITO
A11: 7 | B11: LAGO AGRIO
A12: 8 | B12: IBARRA AMAZONAS
A13: 9 | B13: IBARRA MAYORISTA
A14: 10 | B14: ATUNTAQUI
A15: 11 | B15: OTAVALO
A16: 12 | B16: CAYAMBE
... A18: 14 | B18: TUMBACO
